BlockMemory.vhd
library ieee;
use ieee.std_logic_1164.all;
use ieee.numeric_std.all;
use ieee.math_real.all;

entity BlockMemory is 
    port (
        cLK             : in std_logic;
        W_ADDR, R_ADDR  : in std_logic_vector(7  downto 0);
        W_DATA          : in std_logic_vector(15 downto 0);
        CLEAR, W_EN     : in std_logic;
        R_DATA          : out std_logic_vector(15 downto 0)
    );
end BlockMemory;

architecture behavioral of BlockMemory is

    constant ADDRBITS : integer := 8;
    constant REGDEPTH : integer := 2**ADDRBITS;
    constant REGWIDTH : integer := 16;

    type regfile_type is array (0 to REGDEPTH-1) of STD_LOGIC_VECTOR(REGWIDTH-1 downto 0);
    signal regfile : regfile_type := (others => (others => '0'));

begin

    -- Synchronous write
    process (cLK)
    begin

        if rising_edge(cLK) then
            -- Write
            if W_EN = '1' then
                regfile(to_integer(unsigned(W_ADDR))) <= W_DATA;
            end if;

            -- Clear
            if CLEAR = '1' then
                regfile <= (others => (others => '0'));
            end if;
        end if;

    end process;

    -- Asynchronous read
    R_DATA <= regfile(to_integer(unsigned(R_ADDR)));

end architecture;

BlockMemory_tb.vhd
-- Code your testbench here
library IEEE;
use IEEE.std_logic_1164.all;

entity BlockMemory_tb is
end BlockMemory_tb;

architecture testbench of BlockMemory_tb is

component BlockMemory IS
PORT ( 	cLK				:	in	STD_LOGIC; 
		W_ADDR, R_ADDR	: 	in 	STD_LOGIC_VECTOR(7 downto 0);
		W_DATA				: 	in 	STD_LOGIC_VECTOR(15 downto 0);
        CLEAR, W_EN	: 	in	STD_LOGIC;
        R_DATA	:	out	STD_LOGIC_VECTOR(15 downto 0));
end COMPONENT BlockMemory;



signal 	CLK		:	STD_LOGIC := '0'; --10 MHz clock
signal 	W_ADDR	: 	STD_LOGIC_VECTOR(7 downto 0) := (others => '0');
signal 	R_ADDR	: 	STD_LOGIC_VECTOR(7 downto 0) := (others => '0');
signal	W_DATA	:	STD_LOGIC_VECTOR(15 downto 0) := (others => '0');
signal	R_DATA	:	STD_LOGIC_VECTOR(15 downto 0) := (others => '0');
signal 	CLEAR	: 	STD_LOGIC := '0';
signal 	W_EN	:	STD_LOGIC := '0';


begin

uut : BlockMemory PORT MAP(
		clk  => CLK,
		W_ADDR => W_ADDR,
        R_ADDR => R_ADDR,
        W_DATA => W_DATA,
        CLEAR => CLEAR,
        W_EN => W_EN,
       	R_DATA => R_DATA);
    
    
clk_proc : process
BEGIN

  CLK <= '0';
  wait for 5 ns;   

  CLK <= '1';
  wait for 5 ns;

END PROCESS clk_proc;

stim_proc : process
begin
	
    R_ADDR <= "00000011"; --3
    
    wait for 10 ns;
    
    W_DATA <= "0000000100000001";--0x0101
    W_ADDR <= "00000000"; --0
    W_EN <= '1';
    Wait for 10 ns;
    W_EN <= '0';

	Wait for 10 ns;
    W_DATA<= "0000001100000011";--0x0303
    W_ADDR <= "00000001"; --1
    W_EN <= '1';
    Wait for 10 ns;
    W_EN <= '0';
    
    Wait for 10 ns;
    W_DATA <= "0000011100000111";--0x0707
    W_ADDR <= "00000010"; --2
    W_EN <= '1';
    Wait for 10 ns;
    W_EN <= '0';

	Wait for 10 ns;
    W_DATA <= "0000111100001111";--0x0F0F
    W_ADDR <= "00000011"; --3
   	W_EN <= '1';
    Wait for 10 ns;
    W_EN <= '0';
    
    Wait for 10 ns;
    W_DATA <= "0001111100011111";--0x1F1F
    W_ADDR <= "00000100"; --4
    W_EN <= '1';
    Wait for 10 ns;
    W_EN <= '0';
	
    Wait for 10 ns;
    W_DATA <= "0011111100111111";--0x3F3F
    W_ADDR <= "00000101"; --5
    W_EN <= '1';
    Wait for 10 ns;
    W_EN <= '0';
    
    Wait for 10 ns;
    W_DATA <= "0111111101111111";--0x7F7F
    W_ADDR <= "00000110"; --6
    W_EN <= '1';
    Wait for 10 ns;
    W_EN <= '0';
	
    Wait for 10 ns;
    W_DATA <= "1111111111111111";--0xFFFF
    W_ADDR <= "00000111"; --7
    W_EN <= '1';
    Wait for 10 ns;
    W_EN <= '0';
    
    --Cycle through each location in memory
    R_ADDR <= "00000001"; --1
    wait for 10 ns;
    R_ADDR <= "00000010"; --2
    wait for 10 ns;
    R_ADDR <= "00000011"; --3
    wait for 10 ns;
    R_ADDR <= "00000100"; --4
    wait for 10 ns;
    R_ADDR <= "00000101"; --5
    wait for 10 ns;
    R_ADDR <= "00000110"; --6
    wait for 10 ns;
    R_ADDR <= "00000111"; --7
    wait for 10 ns;
    
    --Clear the memory
    wait for 10 ns;
    CLEAR <= '1';
    wait for 10 ns;
    CLEAR <= '0';
    wait for 10 ns;
  
  	 --Cycle through each location in memory
    R_ADDR <= "00000000"; --0
    wait for 10 ns;
    R_ADDR <= "00000001"; --1
    wait for 10 ns;
    R_ADDR <= "00000010"; --2
    wait for 10 ns;
    R_ADDR <= "00000011"; --3
    wait for 10 ns;
    R_ADDR <= "00000100"; --4
    wait for 10 ns;
    R_ADDR <= "00000101"; --5
    wait for 10 ns;
    R_ADDR <= "00000110"; --6
    wait for 10 ns;
    R_ADDR <= "00000111"; --7
    wait for 10 ns;
    
    wait;
end process stim_proc;
end testbench;

BlockMemory_tb.vcd
$date
  Fri May  9 13:53:32 2025
$end
$version
  GHDL v0
$end
$timescale
  1 fs
$end
$scope module standard $end
$upscope $end
$scope module textio $end
$upscope $end
$scope module std_logic_1164 $end
$upscope $end
$scope module numeric_std $end
$upscope $end
$scope module math_real $end
$upscope $end
$scope module blockmemory_tb $end
$var reg 1 ! clk $end
$var reg 8 " w_addr[7:0] $end
$var reg 8 # r_addr[7:0] $end
$var reg 16 $ w_data[15:0] $end
$var reg 16 % r_data[15:0] $end
$var reg 1 & clear $end
$var reg 1 ' w_en $end
$scope module uut $end
$var reg 1 ( clk $end
$var reg 8 ) w_addr[7:0] $end
$var reg 8 * r_addr[7:0] $end
$var reg 16 + w_data[15:0] $end
$var reg 1 , clear $end
$var reg 1 - w_en $end
$var reg 16 . r_data[15:0] $end
$comment regfile is not handled $end
$upscope $end
$upscope $end
$enddefinitions $end
#0
0!
b00000000 "
b00000011 #
b0000000000000000 $
b0000000000000000 %
0&
0'
0(
b00000000 )
b00000011 *
b0000000000000000 +
0,
0-
b0000000000000000 .
#5000000
1!
1(
#10000000
0!
b0000000100000001 $
1'
0(
b0000000100000001 +
1-
#15000000
1!
1(
#20000000
0!
0'
0(
0-
#25000000
1!
1(
#30000000
0!
b00000001 "
b0000001100000011 $
1'
0(
b00000001 )
b0000001100000011 +
1-
#35000000
1!
1(
#40000000
0!
0'
0(
0-
#45000000
1!
1(
#50000000
0!
b00000010 "
b0000011100000111 $
1'
0(
b00000010 )
b0000011100000111 +
1-
#55000000
1!
1(
#60000000
0!
0'
0(
0-
#65000000
1!
1(
#70000000
0!
b00000011 "
b0000111100001111 $
1'
0(
b00000011 )
b0000111100001111 +
1-
#75000000
1!
b0000111100001111 %
1(
b0000111100001111 .
#80000000
0!
0'
0(
0-
#85000000
1!
1(
#90000000
0!
b00000100 "
b0001111100011111 $
1'
0(
b00000100 )
b0001111100011111 +
1-
#95000000
1!
1(
#100000000
0!
0'
0(
0-
#105000000
1!
1(
#110000000
0!
b00000101 "
b0011111100111111 $
1'
0(
b00000101 )
b0011111100111111 +
1-
#115000000
1!
1(
#120000000
0!
0'
0(
0-
#125000000
1!
1(
#130000000
0!
b00000110 "
b0111111101111111 $
1'
0(
b00000110 )
b0111111101111111 +
1-
#135000000
1!
1(
#140000000
0!
0'
0(
0-
#145000000
1!
1(
#150000000
0!
b00000111 "
b1111111111111111 $
1'
0(
b00000111 )
b1111111111111111 +
1-
#155000000
1!
1(
#160000000
0!
b00000001 #
b0000001100000011 %
0'
0(
b00000001 *
0-
b0000001100000011 .
#165000000
1!
1(
#170000000
0!
b00000010 #
b0000011100000111 %
0(
b00000010 *
b0000011100000111 .
#175000000
1!
1(
#180000000
0!
b00000011 #
b0000111100001111 %
0(
b00000011 *
b0000111100001111 .
#185000000
1!
1(
#190000000
0!
b00000100 #
b0001111100011111 %
0(
b00000100 *
b0001111100011111 .
#195000000
1!
1(
#200000000
0!
b00000101 #
b0011111100111111 %
0(
b00000101 *
b0011111100111111 .
#205000000
1!
1(
#210000000
0!
b00000110 #
b0111111101111111 %
0(
b00000110 *
b0111111101111111 .
#215000000
1!
1(
#220000000
0!
b00000111 #
b1111111111111111 %
0(
b00000111 *
b1111111111111111 .
#225000000
1!
1(
#230000000
0!
0(
#235000000
1!
1(
#240000000
0!
1&
0(
1,
#245000000
1!
b0000000000000000 %
1(
b0000000000000000 .
#250000000
0!
0&
0(
0,
#255000000
1!
1(
#260000000
0!
b00000000 #
0(
b00000000 *
#265000000
1!
1(
#270000000
0!
b00000001 #
0(
b00000001 *
#275000000
1!
1(
#280000000
0!
b00000010 #
0(
b00000010 *
#285000000
1!
1(
#290000000
0!
b00000011 #
0(
b00000011 *
#295000000
1!
1(
#300000000
0!
b00000100 #
0(
b00000100 *
#305000000
1!
1(
#310000000
0!
b00000101 #
0(
b00000101 *
#315000000
1!
1(
#320000000
0!
b00000110 #
0(
b00000110 *
#325000000
1!
1(
#330000000
0!
b00000111 #
0(
b00000111 *
