CodeGame.vhd
library IEEE;
use IEEE.STD_LOGIC_1164.ALL;
use IEEE.NUMERIC_STD.ALL;

entity CodeGame is
    Port ( clk      : in  STD_LOGIC;
           Number   : in  STD_LOGIC_VECTOR(3 downto 0); -- Input digit from user
           KeyPress : in  STD_LOGIC;                   -- High for 1 cycle when Number is valid
           GT       : out STD_LOGIC_VECTOR(3 downto 0); -- Code[i] > Guess[i]
           EQ       : out STD_LOGIC_VECTOR(3 downto 0); -- Code[i] = Guess[i]
           LT       : out STD_LOGIC_VECTOR(3 downto 0); -- Code[i] < Guess[i]
           Win      : out STD_LOGIC;                   -- Player B wins
           Lose     : out STD_LOGIC);                  -- Player B loses
end CodeGame;

architecture Behavioral of CodeGame is

    -- FSM State Definition
    type State_type is (sInit, sEnterCode, sEnterGuess, sCheck, sWin, sLose);
    signal current_state, next_state : State_type;

    -- Datapath Registers
    type four_digit_array is array (0 to 3) of STD_LOGIC_VECTOR(3 downto 0);
    signal code_r  : four_digit_array; -- Stores Player A's code
    signal guess_r : four_digit_array; -- Stores Player B's current guess

    -- Counters
    signal digit_idx_r         : unsigned(1 downto 0); -- Counts 0 to 3 for digit entry index
    signal attempts_r          : unsigned(2 downto 0); -- Counts 0 to 4 for guess attempts

    -- Internal Datapath Status Signals (inputs to FSM logic)
    signal digits_entered_4_s   : STD_LOGIC; -- True when 4 digits have been input for current code/guess
    signal code_is_correct_s    : STD_LOGIC; -- True if all guess digits match code digits
    signal attempts_reached_4_s : STD_LOGIC := '0'; -- True if 4 guesses have been made

begin

    -- Datapath Logic

    -- 1. Code and Guess Registers
    process(clk)
    begin
        if rising_edge(clk) then
            -- Actions based on FSM state and KeyPress
            if current_state = sInit then
                code_r <= (others => (others => '0')); -- Clear code register
                guess_r <= (others => (others => '0')); -- Clear guess register
            end if;

            if KeyPress = '1' then
                if current_state = sEnterCode then
                    code_r(to_integer(digit_idx_r)) <= Number;
                elsif current_state = sEnterGuess then
                    guess_r(to_integer(digit_idx_r)) <= Number;
                end if;
            end if;
        end if;
    end process;

    -- 2. Digit Index Counter (for code_r and guess_r)
    process(clk)
    begin
        if rising_edge(clk) then
            if current_state = sInit or next_state = sEnterCode or next_state = sEnterGuess then
                 -- Reset when initializing or when starting a new code/guess entry phase
                if (current_state /= sEnterCode and next_state = sEnterCode) or 
                   (current_state /= sEnterGuess and next_state = sEnterGuess) or
                   current_state = sInit then
                    digit_idx_r <= (others => '0');
                end if;
            end if;
            
            if KeyPress = '1' and (current_state = sEnterCode or current_state = sEnterGuess) then
                if digit_idx_r < 3 then
                    digit_idx_r <= digit_idx_r + 1;
                else
                    digit_idx_r <= (others => '0'); -- Ready for next phase 
                end if;
            end if;
        end if;
    end process;

    -- Status signal: 4 digits entered for the current phase
    digits_entered_4_s <= '1' when KeyPress = '1' and 
                                   (current_state = sEnterCode or current_state = sEnterGuess) and 
                                   digit_idx_r = "11" else '0';

    -- 3. Guess Attempt Counter
    process(clk)
    begin
        if rising_edge(clk) then
            if current_state = sInit then
                attempts_r <= (others => '0');
            elsif current_state = sEnterGuess and digits_entered_4_s = '1' then 
                -- Increment when a full guess has been entered and we are about to check
                if attempts_r < 4 then -- only increment if not already at max useful count for check
                    attempts_r <= attempts_r + 1;
                end if;
            end if;
        end if;
    end process;

    -- Status signal: 4 attempts made (check after current guess is processed)
    attempts_reached_4_s <= '1' when attempts_r = 4 else '0'; -- attempts_r will be 1 after 1st guess, 4 after 4th

    -- 4. Comparators and Game Outputs (GT, EQ, LT)
    comparators_gen: for i in 0 to 3 generate
    begin
        GT(i) <= '1' when code_r(i) > guess_r(i) else '0';
        EQ(i) <= '1' when code_r(i) = guess_r(i) else '0';
        LT(i) <= '1' when code_r(i) < guess_r(i) else '0'; 
    end generate;

    -- Status signal: Current guess is correct
    code_is_correct_s <= EQ(0) and EQ(1) and EQ(2) and EQ(3);


    -- FSM Logic

    -- Process for determining next_state and combinatorial FSM outputs (Win, Lose)
    fsm_next_state_logic: process(current_state, KeyPress, digits_entered_4_s, code_is_correct_s, attempts_reached_4_s)
    begin
        -- Default assignments
        next_state <= current_state; 
        Win <= '0';
        Lose <= '0';

        case current_state is
            when sInit =>
                next_state <= sEnterCode;

            when sEnterCode =>
                if digits_entered_4_s = '1' then -- 4th digit of code was just entered
                    next_state <= sEnterGuess;
                else
                    next_state <= sEnterCode; -- Wait for more digits
                end if;

            when sEnterGuess =>
                if digits_entered_4_s = '1' then -- 4th digit of guess was just entered
                    next_state <= sCheck;
                else
                    next_state <= sEnterGuess; -- Wait for more digits
                end if;

            when sCheck =>
                if code_is_correct_s = '1' then
                    next_state <= sWin;
                elsif attempts_reached_4_s = '1' then -- And code is not correct
                    next_state <= sLose;
                else -- Code incorrect, more attempts left
                    next_state <= sEnterGuess;
                end if;

            when sWin =>
                Win <= '1'; -- Assert Win for one cycle
                next_state <= sInit; -- Go back to init for a new game

            when sLose =>
                Lose <= '1'; -- Assert Lose for one cycle
                next_state <= sInit; -- Go back to init for a new game
                
            when others =>
                next_state <= sInit;

        end case;
    end process fsm_next_state_logic;

    -- Process for updating current_state
    fsm_state_register: process(clk)
    begin
        if rising_edge(clk) then
            current_state <= next_state;
        end if;
    end process fsm_state_register;

end Behavioral;

CodeGame_tb.vhd
library IEEE;
use IEEE.STD_LOGIC_1164.ALL;
use IEEE.NUMERIC_STD.ALL;

entity CodeGame_tb is
-- No ports for a testbench
end CodeGame_tb;

architecture Testbench of CodeGame_tb is
    -- Component Declaration for the Unit Under Test (UUT)
    component CodeGame
        Port ( clk : in STD_LOGIC;
               Number : in STD_LOGIC_VECTOR(3 downto 0);
               KeyPress : in STD_LOGIC;
               GT : out STD_LOGIC_VECTOR(3 downto 0);
               EQ : out STD_LOGIC_VECTOR(3 downto 0);
               LT : out STD_LOGIC_VECTOR(3 downto 0);
               Win : out STD_LOGIC;
               Lose : out STD_LOGIC);
    end component;

    -- Inputs
    signal clk : STD_LOGIC := '0';
    signal Number : STD_LOGIC_VECTOR(3 downto 0) := (others => '0');
    signal KeyPress : STD_LOGIC := '0';

    -- Outputs
    signal GT : STD_LOGIC_VECTOR(3 downto 0);
    signal EQ : STD_LOGIC_VECTOR(3 downto 0);
    signal LT : STD_LOGIC_VECTOR(3 downto 0);
    signal Win : STD_LOGIC;
    signal Lose : STD_LOGIC;

    -- Clock period definition
    constant clk_period : time := 10 ns;

begin
    -- Instantiate the Unit Under Test (UUT)
    uut: CodeGame Port Map (
        clk => clk,
        Number => Number,
        KeyPress => KeyPress,
        GT => GT,
        EQ => EQ,
        LT => LT,
        Win => Win,
        Lose => Lose
    );

    -- Clock process definitions
    clk_process : process
    begin
        clk <= '0';
        wait for clk_period/2;
        clk <= '1';
        wait for clk_period/2;
    end process;

    -- Stimulus process to simulate input conditions
    stim_proc: process
    begin
        -- Initialization Phase
        wait for 10 ns;
        KeyPress <= '0';
        Number <= "0000";
        wait for clk_period * 10;

        -- Testing Code Input
        KeyPress <= '1';
        Number <= "1010"; -- 1st digit of the code
        wait for clk_period;
        KeyPress <= '0';
        wait for clk_period * 2;
        
        KeyPress <= '1';
        Number <= "0101"; -- 2nd digit of the code
        wait for clk_period;
        KeyPress <= '0';
        wait for clk_period * 2;
        
        KeyPress <= '1';
        Number <= "0001"; -- 3rd digit of the code
        wait for clk_period;
        KeyPress <= '0';
        wait for clk_period * 2;
		
         KeyPress <= '1';
        Number <= "1111"; -- 4th digit of the code
        wait for clk_period;
        KeyPress <= '0';
        wait for clk_period * 10;
        
        -- Simulate guesses and check outputs
        KeyPress <= '1';
        Number <= "1011"; -- 1st digit of the guess
        wait for clk_period;
        KeyPress <= '0';
        wait for clk_period * 2;
        
        KeyPress <= '1';
        Number <= "0101"; -- 2nd digit of the guess
        wait for clk_period;
        KeyPress <= '0';
        wait for clk_period * 2;
        
        KeyPress <= '1';
        Number <= "0001"; -- 3rd digit of the guess
        wait for clk_period;
        KeyPress <= '0';
        wait for clk_period * 2;
		
         KeyPress <= '1';
        Number <= "0000"; -- 4th digit of the guess
        wait for clk_period;
        KeyPress <= '0';
        wait for clk_period * 10;
        
        
        --try number 2
        KeyPress <= '1';
        Number <= "1010"; -- 1st digit of the guess
        wait for clk_period;
        KeyPress <= '0';
        wait for clk_period * 2;
        
        KeyPress <= '1';
        Number <= "0101"; -- 2nd digit of the guess
        wait for clk_period;
        KeyPress <= '0';
        wait for clk_period * 2;
        
        KeyPress <= '1';
        Number <= "0001"; -- 3rd digit of the guess
        wait for clk_period;
        KeyPress <= '0';
        wait for clk_period * 2;
		
         KeyPress <= '1';
        Number <= "1111"; -- 4th digit of the guess
        wait for clk_period;
        KeyPress <= '0';
        wait for clk_period * 10;
        
         -- Testing Code Input
        KeyPress <= '1';
        Number <= "1010"; -- 1st digit of the code
        wait for clk_period;
        KeyPress <= '0';
        wait for clk_period * 2;
        
        KeyPress <= '1';
        Number <= "0101"; -- 2nd digit of the code
        wait for clk_period;
        KeyPress <= '0';
        wait for clk_period * 2;
        
        KeyPress <= '1';
        Number <= "0001"; -- 3rd digit of the code
        wait for clk_period;
        KeyPress <= '0';
        wait for clk_period * 2;
		
         KeyPress <= '1';
        Number <= "1101"; -- 4th digit of the code
        wait for clk_period;
        KeyPress <= '0';
        wait for clk_period * 10;
        
         -- Simulate guesses and check outputs
        KeyPress <= '1';
        Number <= "1011"; -- 1st digit of the guess
        wait for clk_period;
        KeyPress <= '0';
        wait for clk_period * 2;
        
        KeyPress <= '1';
        Number <= "0101"; -- 2nd digit of the guess
        wait for clk_period;
        KeyPress <= '0';
        wait for clk_period * 2;
        
        KeyPress <= '1';
        Number <= "0001"; -- 3rd digit of the guess
        wait for clk_period;
        KeyPress <= '0';
        wait for clk_period * 2;
		
         KeyPress <= '1';
        Number <= "0000"; -- 4th digit of the guess
        wait for clk_period;
        KeyPress <= '0';
        wait for clk_period * 10;
        
        
        --try number 2
        KeyPress <= '1';
        Number <= "1010"; -- 1st digit of the guess
        wait for clk_period;
        KeyPress <= '0';
        wait for clk_period * 2;
        
        KeyPress <= '1';
        Number <= "0101"; -- 2nd digit of the guess
        wait for clk_period;
        KeyPress <= '0';
        wait for clk_period * 2;
        
        KeyPress <= '1';
        Number <= "0001"; -- 3rd digit of the guess
        wait for clk_period;
        KeyPress <= '0';
        wait for clk_period * 2;
		
         KeyPress <= '1';
        Number <= "1111"; -- 4th digit of the guess
        wait for clk_period;
        KeyPress <= '0';
        wait for clk_period * 10;
        
         --try number 2
        KeyPress <= '1';
        Number <= "1010"; -- 1st digit of the guess
        wait for clk_period;
        KeyPress <= '0';
        wait for clk_period * 2;
        
        KeyPress <= '1';
        Number <= "0101"; -- 2nd digit of the guess
        wait for clk_period;
        KeyPress <= '0';
        wait for clk_period * 2;
        
        KeyPress <= '1';
        Number <= "0001"; -- 3rd digit of the guess
        wait for clk_period;
        KeyPress <= '0';
        wait for clk_period * 2;
		
         KeyPress <= '1';
        Number <= "1111"; -- 4th digit of the guess
        wait for clk_period;
        KeyPress <= '0';
        wait for clk_period * 10;
        
         --try number 2
        KeyPress <= '1';
        Number <= "1010"; -- 1st digit of the guess
        wait for clk_period;
        KeyPress <= '0';
        wait for clk_period * 2;
        
        KeyPress <= '1';
        Number <= "0101"; -- 2nd digit of the guess
        wait for clk_period;
        KeyPress <= '0';
        wait for clk_period * 2;
        
        KeyPress <= '1';
        Number <= "0001"; -- 3rd digit of the guess
        wait for clk_period;
        KeyPress <= '0';
        wait for clk_period * 2;
		
         KeyPress <= '1';
        Number <= "1111"; -- 4th digit of the guess
        wait for clk_period;
        KeyPress <= '0';
        wait for clk_period * 10;
        

        -- Finish the simulation
        wait;
    end process;

end Testbench;

CodeGame_tb.vcd
$date
  Thu May  8 20:20:39 2025
$end
$version
  GHDL v0
$end
$timescale
  1 fs
$end
$scope module standard $end
$upscope $end
$scope module textio $end
$upscope $end
$scope module std_logic_1164 $end
$upscope $end
$scope module numeric_std $end
$upscope $end
$scope module codegame_tb $end
$var reg 1 ! clk $end
$var reg 4 " number[3:0] $end
$var reg 1 # keypress $end
$var reg 4 $ gt[3:0] $end
$var reg 4 % eq[3:0] $end
$var reg 4 & lt[3:0] $end
$var reg 1 ' win $end
$var reg 1 ( lose $end
$scope module uut $end
$var reg 1 ) clk $end
$var reg 4 * number[3:0] $end
$var reg 1 + keypress $end
$var reg 4 , gt[3:0] $end
$var reg 4 - eq[3:0] $end
$var reg 4 . lt[3:0] $end
$var reg 1 / win $end
$var reg 1 0 lose $end
$comment current_state is not handled $end
$comment next_state is not handled $end
$comment code_r is not handled $end
$comment guess_r is not handled $end
$var reg 2 1 digit_idx_r[1:0] $end
$var reg 3 2 attempts_r[2:0] $end
$var reg 1 3 digits_entered_4_s $end
$var reg 1 4 code_is_correct_s $end
$var reg 1 5 attempts_reached_4_s $end
$scope module comparators_gen(0) $end
$upscope $end
$scope module comparators_gen(1) $end
$upscope $end
$scope module comparators_gen(2) $end
$upscope $end
$scope module comparators_gen(3) $end
$upscope $end
$upscope $end
$upscope $end
$enddefinitions $end
#0
0!
b0000 "
0#
b0000 $
b1111 %
b0000 &
0'
0(
0)
b0000 *
0+
b0000 ,
b1111 -
b0000 .
0/
00
bUU 1
bUUU 2
03
14
05
#5000000
1!
1)
b00 1
b000 2
#10000000
0!
0)
#15000000
1!
1)
#20000000
0!
0)
#25000000
1!
1)
#30000000
0!
0)
#35000000
1!
1)
#40000000
0!
0)
#45000000
1!
1)
#50000000
0!
0)
#55000000
1!
1)
#60000000
0!
0)
#65000000
1!
1)
#70000000
0!
0)
#75000000
1!
1)
#80000000
0!
0)
#85000000
1!
1)
#90000000
0!
0)
#95000000
1!
1)
#100000000
0!
0)
#105000000
1!
1)
#110000000
0!
b1010 "
1#
0)
b1010 *
1+
#115000000
1!
b0001 $
b1110 %
1)
b0001 ,
b1110 -
b01 1
04
#120000000
0!
0#
0)
0+
#125000000
1!
1)
#130000000
0!
0)
#135000000
1!
1)
#140000000
0!
b0101 "
1#
0)
b0101 *
1+
#145000000
1!
b0011 $
b1100 %
1)
b0011 ,
b1100 -
b10 1
#150000000
0!
0#
0)
0+
#155000000
1!
1)
#160000000
0!
0)
#165000000
1!
1)
#170000000
0!
b0001 "
1#
0)
b0001 *
1+
#175000000
1!
b0111 $
b1000 %
1)
b0111 ,
b1000 -
b11 1
13
#180000000
0!
0#
0)
0+
03
#185000000
1!
1)
#190000000
0!
0)
#195000000
1!
1)
#200000000
0!
b1111 "
1#
0)
b1111 *
1+
13
#205000000
1!
b1111 $
b0000 %
1)
b1111 ,
b0000 -
b00 1
03
#210000000
0!
0#
0)
0+
#215000000
1!
1)
#220000000
0!
0)
#225000000
1!
1)
#230000000
0!
0)
#235000000
1!
1)
#240000000
0!
0)
#245000000
1!
1)
#250000000
0!
0)
#255000000
1!
1)
#260000000
0!
0)
#265000000
1!
1)
#270000000
0!
0)
#275000000
1!
1)
#280000000
0!
0)
#285000000
1!
1)
#290000000
0!
0)
#295000000
1!
1)
#300000000
0!
0)
#305000000
1!
1)
#310000000
0!
b1011 "
1#
0)
b1011 *
1+
#315000000
1!
b1110 $
b0001 &
1)
b1110 ,
b0001 .
b01 1
#320000000
0!
0#
0)
0+
#325000000
1!
1)
#330000000
0!
0)
#335000000
1!
1)
#340000000
0!
b0101 "
1#
0)
b0101 *
1+
#345000000
1!
b1100 $
b0010 %
1)
b1100 ,
b0010 -
b10 1
#350000000
0!
0#
0)
0+
#355000000
1!
1)
#360000000
0!
0)
#365000000
1!
1)
#370000000
0!
b0001 "
1#
0)
b0001 *
1+
#375000000
1!
b1000 $
b0110 %
1)
b1000 ,
b0110 -
b11 1
13
#380000000
0!
0#
0)
0+
03
#385000000
1!
1)
#390000000
0!
0)
#395000000
1!
1)
#400000000
0!
b0000 "
1#
0)
b0000 *
1+
13
#405000000
1!
1)
b00 1
b001 2
03
#410000000
0!
0#
0)
0+
#415000000
1!
1)
#420000000
0!
0)
#425000000
1!
1)
#430000000
0!
0)
#435000000
1!
1)
#440000000
0!
0)
#445000000
1!
1)
#450000000
0!
0)
#455000000
1!
1)
#460000000
0!
0)
#465000000
1!
1)
#470000000
0!
0)
#475000000
1!
1)
#480000000
0!
0)
#485000000
1!
1)
#490000000
0!
0)
#495000000
1!
1)
#500000000
0!
0)
#505000000
1!
1)
#510000000
0!
b1010 "
1#
0)
b1010 *
1+
#515000000
1!
b0111 %
b0000 &
1)
b0111 -
b0000 .
b01 1
#520000000
0!
0#
0)
0+
#525000000
1!
1)
#530000000
0!
0)
#535000000
1!
1)
#540000000
0!
b0101 "
1#
0)
b0101 *
1+
#545000000
1!
1)
b10 1
#550000000
0!
0#
0)
0+
#555000000
1!
1)
#560000000
0!
0)
#565000000
1!
1)
#570000000
0!
b0001 "
1#
0)
b0001 *
1+
#575000000
1!
1)
b11 1
13
#580000000
0!
0#
0)
0+
03
#585000000
1!
1)
#590000000
0!
0)
#595000000
1!
1)
#600000000
0!
b1111 "
1#
0)
b1111 *
1+
13
#605000000
1!
b0000 $
b1111 %
1)
b0000 ,
b1111 -
b00 1
b010 2
03
14
#610000000
0!
0#
0)
0+
#615000000
1!
1'
1)
1/
#620000000
0!
0)
#625000000
1!
0'
1)
0/
#630000000
0!
0)
#635000000
1!
1)
b000 2
#640000000
0!
0)
#645000000
1!
1)
#650000000
0!
0)
#655000000
1!
1)
#660000000
0!
0)
#665000000
1!
1)
#670000000
0!
0)
#675000000
1!
1)
#680000000
0!
0)
#685000000
1!
1)
#690000000
0!
0)
#695000000
1!
1)
#700000000
0!
0)
#705000000
1!
1)
#710000000
0!
b1010 "
1#
0)
b1010 *
1+
#715000000
1!
b0001 $
b1110 %
1)
b0001 ,
b1110 -
b01 1
04
#720000000
0!
0#
0)
0+
#725000000
1!
1)
#730000000
0!
0)
#735000000
1!
1)
#740000000
0!
b0101 "
1#
0)
b0101 *
1+
#745000000
1!
b0011 $
b1100 %
1)
b0011 ,
b1100 -
b10 1
#750000000
0!
0#
0)
0+
#755000000
1!
1)
#760000000
0!
0)
#765000000
1!
1)
#770000000
0!
b0001 "
1#
0)
b0001 *
1+
#775000000
1!
b0111 $
b1000 %
1)
b0111 ,
b1000 -
b11 1
13
#780000000
0!
0#
0)
0+
03
#785000000
1!
1)
#790000000
0!
0)
#795000000
1!
1)
#800000000
0!
b1101 "
1#
0)
b1101 *
1+
13
#805000000
1!
b1111 $
b0000 %
1)
b1111 ,
b0000 -
b00 1
03
#810000000
0!
0#
0)
0+
#815000000
1!
1)
#820000000
0!
0)
#825000000
1!
1)
#830000000
0!
0)
#835000000
1!
1)
#840000000
0!
0)
#845000000
1!
1)
#850000000
0!
0)
#855000000
1!
1)
#860000000
0!
0)
#865000000
1!
1)
#870000000
0!
0)
#875000000
1!
1)
#880000000
0!
0)
#885000000
1!
1)
#890000000
0!
0)
#895000000
1!
1)
#900000000
0!
0)
#905000000
1!
1)
#910000000
0!
b1011 "
1#
0)
b1011 *
1+
#915000000
1!
b1110 $
b0001 &
1)
b1110 ,
b0001 .
b01 1
#920000000
0!
0#
0)
0+
#925000000
1!
1)
#930000000
0!
0)
#935000000
1!
1)
#940000000
0!
b0101 "
1#
0)
b0101 *
1+
#945000000
1!
b1100 $
b0010 %
1)
b1100 ,
b0010 -
b10 1
#950000000
0!
0#
0)
0+
#955000000
1!
1)
#960000000
0!
0)
#965000000
1!
1)
#970000000
0!
b0001 "
1#
0)
b0001 *
1+
#975000000
1!
b1000 $
b0110 %
1)
b1000 ,
b0110 -
b11 1
13
#980000000
0!
0#
0)
0+
03
#985000000
1!
1)
#990000000
0!
0)
#995000000
1!
1)
#1000000000
0!
b0000 "
1#
0)
b0000 *
1+
13
#1005000000
1!
1)
b00 1
b001 2
03
#1010000000
0!
0#
0)
0+
#1015000000
1!
1)
#1020000000
0!
0)
#1025000000
1!
1)
#1030000000
0!
0)
#1035000000
1!
1)
#1040000000
0!
0)
#1045000000
1!
1)
#1050000000
0!
0)
#1055000000
1!
1)
#1060000000
0!
0)
#1065000000
1!
1)
#1070000000
0!
0)
#1075000000
1!
1)
#1080000000
0!
0)
#1085000000
1!
1)
#1090000000
0!
0)
#1095000000
1!
1)
#1100000000
0!
0)
#1105000000
1!
1)
#1110000000
0!
b1010 "
1#
0)
b1010 *
1+
#1115000000
1!
b0111 %
b0000 &
1)
b0111 -
b0000 .
b01 1
#1120000000
0!
0#
0)
0+
#1125000000
1!
1)
#1130000000
0!
0)
#1135000000
1!
1)
#1140000000
0!
b0101 "
1#
0)
b0101 *
1+
#1145000000
1!
1)
b10 1
#1150000000
0!
0#
0)
0+
#1155000000
1!
1)
#1160000000
0!
0)
#1165000000
1!
1)
#1170000000
0!
b0001 "
1#
0)
b0001 *
1+
#1175000000
1!
1)
b11 1
13
#1180000000
0!
0#
0)
0+
03
#1185000000
1!
1)
#1190000000
0!
0)
#1195000000
1!
1)
#1200000000
0!
b1111 "
1#
0)
b1111 *
1+
13
#1205000000
1!
b0000 $
b1000 &
1)
b0000 ,
b1000 .
b00 1
b010 2
03
#1210000000
0!
0#
0)
0+
#1215000000
1!
1)
#1220000000
0!
0)
#1225000000
1!
1)
#1230000000
0!
0)
#1235000000
1!
1)
#1240000000
0!
0)
#1245000000
1!
1)
#1250000000
0!
0)
#1255000000
1!
1)
#1260000000
0!
0)
#1265000000
1!
1)
#1270000000
0!
0)
#1275000000
1!
1)
#1280000000
0!
0)
#1285000000
1!
1)
#1290000000
0!
0)
#1295000000
1!
1)
#1300000000
0!
0)
#1305000000
1!
1)
#1310000000
0!
b1010 "
1#
0)
b1010 *
1+
#1315000000
1!
1)
b01 1
#1320000000
0!
0#
0)
0+
#1325000000
1!
1)
#1330000000
0!
0)
#1335000000
1!
1)
#1340000000
0!
b0101 "
1#
0)
b0101 *
1+
#1345000000
1!
1)
b10 1
#1350000000
0!
0#
0)
0+
#1355000000
1!
1)
#1360000000
0!
0)
#1365000000
1!
1)
#1370000000
0!
b0001 "
1#
0)
b0001 *
1+
#1375000000
1!
1)
b11 1
13
#1380000000
0!
0#
0)
0+
03
#1385000000
1!
1)
#1390000000
0!
0)
#1395000000
1!
1)
#1400000000
0!
b1111 "
1#
0)
b1111 *
1+
13
#1405000000
1!
1)
b00 1
b011 2
03
#1410000000
0!
0#
0)
0+
#1415000000
1!
1)
#1420000000
0!
0)
#1425000000
1!
1)
#1430000000
0!
0)
#1435000000
1!
1)
#1440000000
0!
0)
#1445000000
1!
1)
#1450000000
0!
0)
#1455000000
1!
1)
#1460000000
0!
0)
#1465000000
1!
1)
#1470000000
0!
0)
#1475000000
1!
1)
#1480000000
0!
0)
#1485000000
1!
1)
#1490000000
0!
0)
#1495000000
1!
1)
#1500000000
0!
0)
#1505000000
1!
1)
#1510000000
0!
b1010 "
1#
0)
b1010 *
1+
#1515000000
1!
1)
b01 1
#1520000000
0!
0#
0)
0+
#1525000000
1!
1)
#1530000000
0!
0)
#1535000000
1!
1)
#1540000000
0!
b0101 "
1#
0)
b0101 *
1+
#1545000000
1!
1)
b10 1
#1550000000
0!
0#
0)
0+
#1555000000
1!
1)
#1560000000
0!
0)
#1565000000
1!
1)
#1570000000
0!
b0001 "
1#
0)
b0001 *
1+
#1575000000
1!
1)
b11 1
13
#1580000000
0!
0#
0)
0+
03
#1585000000
1!
1)
#1590000000
0!
0)
#1595000000
1!
1)
#1600000000
0!
b1111 "
1#
0)
b1111 *
1+
13
#1605000000
1!
1)
b00 1
b100 2
03
15
#1610000000
0!
0#
0)
0+
#1615000000
1!
1(
1)
10
#1620000000
0!
0)
#1625000000
1!
0(
1)
00
#1630000000
0!
0)
#1635000000
1!
b1111 %
b0000 &
1)
b1111 -
b0000 .
b000 2
14
05
