CountByN.vhd
library IEEE;
use IEEE.std_logic_1164.all;
use IEEE.numeric_std.all;

ENTITY CountByN IS
PORT (	clk		: 	in 	STD_LOGIC; -- Clock input
		enable	: 	in 	STD_LOGIC; -- Enable signal for counting
		reset	: 	in 	STD_LOGIC; -- Synchronous reset for the counter
		n		:	in	STD_LOGIC_VECTOR(3 downto 0); -- 4-bit count step size
		count	:	out	STD_LOGIC_VECTOR(7 downto 0); -- 8-bit counter output
        overflow: 	out STD_LOGIC); -- Overflow signal, high for one clock cycle on rollover
end CountByN;

ARCHITECTURE behavior of CountByN is

    -- Internal signal for the 8-bit count register
    signal count_reg    : unsigned(7 downto 0) := (others => '0');
    
    -- Internal signal for the overflow output
    signal overflow_reg : std_logic := '0';

BEGIN

    process(clk)

        -- Variable to hold the intermediate sum of count_reg + n
        variable temp_sum : unsigned(8 downto 0); 

    begin

        if rising_edge(clk) then

            -- If reset is high, the counter is set to 0 and overflow is cleared.
            if reset = '1' then
                count_reg    <= (others => '0'); -- Reset count to 0
                overflow_reg <= '0';             -- Clear overflow flag

            -- If not reset, check if counting is enabled.
            elsif enable = '1' then

                -- Perform addition
                -- The sum is stored in a 9-bit variable (temp_sum) to detect overflow.
                temp_sum := ('0' & count_reg) + ("0000" & unsigned(n));

                -- Check if overflow occurred
                if temp_sum(8) = '1' then 
                    overflow_reg <= '1';
                else
                    overflow_reg <= '0'; -- Clear overflow flag
                end if;
                
                -- Update count_reg with the lower 8 bits of the sum
                count_reg <= temp_sum(7 downto 0); 

            -- If not reset and not enabled (enable = '0'), the counter holds its current value.
            else 

                overflow_reg <= '0'; 

            end if;
        end if;
    end process;

    -- Assign internal registered signals to output ports
    count    <= std_logic_vector(count_reg);
    overflow <= overflow_reg;                

end behavior;

CountByN_tb.vhd
-- Code your testbench here
library IEEE;
use IEEE.std_logic_1164.all;

entity CountByN_tb is
end CountByN_tb;

architecture testbench of CountByN_tb is

component CountByN
PORT (	clk, enable, reset 	: 	in 	STD_LOGIC;
		n					:	in	STD_LOGIC_VECTOR(3 downto 0);
		count				:	out	STD_LOGIC_VECTOR(7 downto 0);
        overflow			: 	out STD_LOGIC);
end component;


signal enable 	: std_logic := '0';
signal reset 	: std_logic := '0';
signal clk 		: std_logic := '0';
signal overflow	: std_logic := '0'; 
signal n		: std_logic_vector(3 downto 0) := "0000";
signal count	: std_logic_vector(7 downto 0);

constant CLK_PERIOD : time := 10 ns;

begin

uut : CountByN PORT MAP(
	clk => clk,
    enable => enable,
    reset => reset,
    n => n,
    count => count,
    overflow => overflow);
    
    
    
stim_proc : process
BEGIN
	clk <= '0';
	wait for CLK_PERIOD/2;
	clk <= '1';
	wait for CLK_PERIOD/2;
end process stim_proc;

inputs: process
begin
	n <= "1111";
    wait for 200 ns;
    
    enable <= '1';
    wait for 170 ns;
    
    enable <= '0';
    wait for 80 ns;
    
    enable <= '1';
    wait for 10 ns;
    
    enable <= '0';
    wait for 80 ns;
    
    enable <= '1';
    wait for 200 ns;
    
    reset <= '1';
    wait for 80 ns;
    
    reset <= '0';    
    wait;
end process inputs;

end testbench;

CountByN_tb.vcd
$date
  Thu May  8 21:06:05 2025
$end
$version
  GHDL v0
$end
$timescale
  1 fs
$end
$scope module standard $end
$upscope $end
$scope module textio $end
$upscope $end
$scope module std_logic_1164 $end
$upscope $end
$scope module numeric_std $end
$upscope $end
$scope module countbyn_tb $end
$var reg 1 ! enable $end
$var reg 1 " reset $end
$var reg 1 # clk $end
$var reg 1 $ overflow $end
$var reg 4 % n[3:0] $end
$var reg 8 & count[7:0] $end
$scope module uut $end
$var reg 1 ' clk $end
$var reg 1 ( enable $end
$var reg 1 ) reset $end
$var reg 4 * n[3:0] $end
$var reg 8 + count[7:0] $end
$var reg 1 , overflow $end
$var reg 8 - count_reg[7:0] $end
$var reg 1 . overflow_reg $end
$upscope $end
$upscope $end
$enddefinitions $end
#0
0!
0"
0#
0$
b1111 %
b00000000 &
0'
0(
0)
b1111 *
b00000000 +
0,
b00000000 -
0.
#5000000
1#
1'
#10000000
0#
0'
#15000000
1#
1'
#20000000
0#
0'
#25000000
1#
1'
#30000000
0#
0'
#35000000
1#
1'
#40000000
0#
0'
#45000000
1#
1'
#50000000
0#
0'
#55000000
1#
1'
#60000000
0#
0'
#65000000
1#
1'
#70000000
0#
0'
#75000000
1#
1'
#80000000
0#
0'
#85000000
1#
1'
#90000000
0#
0'
#95000000
1#
1'
#100000000
0#
0'
#105000000
1#
1'
#110000000
0#
0'
#115000000
1#
1'
#120000000
0#
0'
#125000000
1#
1'
#130000000
0#
0'
#135000000
1#
1'
#140000000
0#
0'
#145000000
1#
1'
#150000000
0#
0'
#155000000
1#
1'
#160000000
0#
0'
#165000000
1#
1'
#170000000
0#
0'
#175000000
1#
1'
#180000000
0#
0'
#185000000
1#
1'
#190000000
0#
0'
#195000000
1#
1'
#200000000
1!
0#
0'
1(
#205000000
1#
b00001111 &
1'
b00001111 +
b00001111 -
#210000000
0#
0'
#215000000
1#
b00011110 &
1'
b00011110 +
b00011110 -
#220000000
0#
0'
#225000000
1#
b00101101 &
1'
b00101101 +
b00101101 -
#230000000
0#
0'
#235000000
1#
b00111100 &
1'
b00111100 +
b00111100 -
#240000000
0#
0'
#245000000
1#
b01001011 &
1'
b01001011 +
b01001011 -
#250000000
0#
0'
#255000000
1#
b01011010 &
1'
b01011010 +
b01011010 -
#260000000
0#
0'
#265000000
1#
b01101001 &
1'
b01101001 +
b01101001 -
#270000000
0#
0'
#275000000
1#
b01111000 &
1'
b01111000 +
b01111000 -
#280000000
0#
0'
#285000000
1#
b10000111 &
1'
b10000111 +
b10000111 -
#290000000
0#
0'
#295000000
1#
b10010110 &
1'
b10010110 +
b10010110 -
#300000000
0#
0'
#305000000
1#
b10100101 &
1'
b10100101 +
b10100101 -
#310000000
0#
0'
#315000000
1#
b10110100 &
1'
b10110100 +
b10110100 -
#320000000
0#
0'
#325000000
1#
b11000011 &
1'
b11000011 +
b11000011 -
#330000000
0#
0'
#335000000
1#
b11010010 &
1'
b11010010 +
b11010010 -
#340000000
0#
0'
#345000000
1#
b11100001 &
1'
b11100001 +
b11100001 -
#350000000
0#
0'
#355000000
1#
b11110000 &
1'
b11110000 +
b11110000 -
#360000000
0#
0'
#365000000
1#
b11111111 &
1'
b11111111 +
b11111111 -
#370000000
0!
0#
0'
0(
#375000000
1#
1'
#380000000
0#
0'
#385000000
1#
1'
#390000000
0#
0'
#395000000
1#
1'
#400000000
0#
0'
#405000000
1#
1'
#410000000
0#
0'
#415000000
1#
1'
#420000000
0#
0'
#425000000
1#
1'
#430000000
0#
0'
#435000000
1#
1'
#440000000
0#
0'
#445000000
1#
1'
#450000000
1!
0#
0'
1(
#455000000
1#
1$
b00001110 &
1'
b00001110 +
1,
b00001110 -
1.
#460000000
0!
0#
0'
0(
#465000000
1#
0$
1'
0,
0.
#470000000
0#
0'
#475000000
1#
1'
#480000000
0#
0'
#485000000
1#
1'
#490000000
0#
0'
#495000000
1#
1'
#500000000
0#
0'
#505000000
1#
1'
#510000000
0#
0'
#515000000
1#
1'
#520000000
0#
0'
#525000000
1#
1'
#530000000
0#
0'
#535000000
1#
1'
#540000000
1!
0#
0'
1(
#545000000
1#
b00011101 &
1'
b00011101 +
b00011101 -
#550000000
0#
0'
#555000000
1#
b00101100 &
1'
b00101100 +
b00101100 -
#560000000
0#
0'
#565000000
1#
b00111011 &
1'
b00111011 +
b00111011 -
#570000000
0#
0'
#575000000
1#
b01001010 &
1'
b01001010 +
b01001010 -
#580000000
0#
0'
#585000000
1#
b01011001 &
1'
b01011001 +
b01011001 -
#590000000
0#
0'
#595000000
1#
b01101000 &
1'
b01101000 +
b01101000 -
#600000000
0#
0'
#605000000
1#
b01110111 &
1'
b01110111 +
b01110111 -
#610000000
0#
0'
#615000000
1#
b10000110 &
1'
b10000110 +
b10000110 -
#620000000
0#
0'
#625000000
1#
b10010101 &
1'
b10010101 +
b10010101 -
#630000000
0#
0'
#635000000
1#
b10100100 &
1'
b10100100 +
b10100100 -
#640000000
0#
0'
#645000000
1#
b10110011 &
1'
b10110011 +
b10110011 -
#650000000
0#
0'
#655000000
1#
b11000010 &
1'
b11000010 +
b11000010 -
#660000000
0#
0'
#665000000
1#
b11010001 &
1'
b11010001 +
b11010001 -
#670000000
0#
0'
#675000000
1#
b11100000 &
1'
b11100000 +
b11100000 -
#680000000
0#
0'
#685000000
1#
b11101111 &
1'
b11101111 +
b11101111 -
#690000000
0#
0'
#695000000
1#
b11111110 &
1'
b11111110 +
b11111110 -
#700000000
0#
0'
#705000000
1#
1$
b00001101 &
1'
b00001101 +
1,
b00001101 -
1.
#710000000
0#
0'
#715000000
1#
0$
b00011100 &
1'
b00011100 +
0,
b00011100 -
0.
#720000000
0#
0'
#725000000
1#
b00101011 &
1'
b00101011 +
b00101011 -
#730000000
0#
0'
#735000000
1#
b00111010 &
1'
b00111010 +
b00111010 -
#740000000
1"
0#
0'
1)
#745000000
1#
b00000000 &
1'
b00000000 +
b00000000 -
#750000000
0#
0'
#755000000
1#
1'
#760000000
0#
0'
#765000000
1#
1'
#770000000
0#
0'
#775000000
1#
1'
#780000000
0#
0'
#785000000
1#
1'
#790000000
0#
0'
#795000000
1#
1'
#800000000
0#
0'
#805000000
1#
1'
#810000000
0#
0'
#815000000
1#
1'
#820000000
0"
0#
0'
0)
#825000000
1#
b00001111 &
1'
b00001111 +
b00001111 -
#830000000
0#
0'
#835000000
1#
b00011110 &
1'
b00011110 +
b00011110 -
#840000000
0#
0'
#845000000
1#
b00101101 &
1'
b00101101 +
b00101101 -
#850000000
0#
0'
#855000000
1#
b00111100 &
1'
b00111100 +
b00111100 -
#860000000
0#
0'
#865000000
1#
b01001011 &
1'
b01001011 +
b01001011 -
#870000000
0#
0'
#875000000
1#
b01011010 &
1'
b01011010 +
b01011010 -
#880000000
0#
0'
#885000000
1#
b01101001 &
1'
b01101001 +
b01101001 -
#890000000
0#
0'
#895000000
1#
b01111000 &
1'
b01111000 +
b01111000 -
#900000000
0#
0'
#905000000
1#
b10000111 &
1'
b10000111 +
b10000111 -
#910000000
0#
0'
#915000000
1#
b10010110 &
1'
b10010110 +
b10010110 -
#920000000
0#
0'
#925000000
1#
b10100101 &
1'
b10100101 +
b10100101 -
#930000000
0#
0'
#935000000
1#
b10110100 &
1'
b10110100 +
b10110100 -
#940000000
0#
0'
#945000000
1#
b11000011 &
1'
b11000011 +
b11000011 -
#950000000
0#
0'
#955000000
1#
b11010010 &
1'
b11010010 +
b11010010 -
#960000000
0#
0'
#965000000
1#
b11100001 &
1'
b11100001 +
b11100001 -
#970000000
0#
0'
#975000000
1#
b11110000 &
1'
b11110000 +
b11110000 -
#980000000
0#
0'
#985000000
1#
b11111111 &
1'
b11111111 +
b11111111 -
#990000000
0#
0'
#995000000
1#
1$
b00001110 &
1'
b00001110 +
1,
b00001110 -
1.
#1000000000
0#
0'
#1005000000
1#
0$
b00011101 &
1'
b00011101 +
0,
b00011101 -
0.
#1010000000
0#
0'
#1015000000
1#
b00101100 &
1'
b00101100 +
b00101100 -
#1020000000
0#
0'
#1025000000
1#
b00111011 &
1'
b00111011 +
b00111011 -
#1030000000
0#
0'
#1035000000
1#
b01001010 &
1'
b01001010 +
b01001010 -
#1040000000
0#
0'
#1045000000
1#
b01011001 &
1'
b01011001 +
b01011001 -
#1050000000
0#
0'
#1055000000
1#
b01101000 &
1'
b01101000 +
b01101000 -
#1060000000
0#
0'
#1065000000
1#
b01110111 &
1'
b01110111 +
b01110111 -
#1070000000
0#
0'
#1075000000
1#
b10000110 &
1'
b10000110 +
b10000110 -
#1080000000
0#
0'
#1085000000
1#
b10010101 &
1'
b10010101 +
b10010101 -
#1090000000
0#
0'
#1095000000
1#
b10100100 &
1'
b10100100 +
b10100100 -
#1100000000
0#
0'
#1105000000
1#
b10110011 &
1'
b10110011 +
b10110011 -
#1110000000
0#
0'
#1115000000
1#
b11000010 &
1'
b11000010 +
b11000010 -
#1120000000
0#
0'
#1125000000
1#
b11010001 &
1'
b11010001 +
b11010001 -
#1130000000
0#
0'
#1135000000
1#
b11100000 &
1'
b11100000 +
b11100000 -
#1140000000
0#
0'
#1145000000
1#
b11101111 &
1'
b11101111 +
b11101111 -
#1150000000
0#
0'
#1155000000
1#
b11111110 &
1'
b11111110 +
b11111110 -
#1160000000
0#
0'
#1165000000
1#
1$
b00001101 &
1'
b00001101 +
1,
b00001101 -
1.
#1170000000
0#
0'
#1175000000
1#
0$
b00011100 &
1'
b00011100 +
0,
b00011100 -
0.
#1180000000
0#
0'
#1185000000
1#
b00101011 &
1'
b00101011 +
b00101011 -
#1190000000
0#
0'
#1195000000
1#
b00111010 &
1'
b00111010 +
b00111010 -
#1200000000
0#
0'
#1205000000
1#
b01001001 &
1'
b01001001 +
b01001001 -
#1210000000
0#
0'
#1215000000
1#
b01011000 &
1'
b01011000 +
b01011000 -
#1220000000
0#
0'
#1225000000
1#
b01100111 &
1'
b01100111 +
b01100111 -
#1230000000
0#
0'
#1235000000
1#
b01110110 &
1'
b01110110 +
b01110110 -
#1240000000
0#
0'
#1245000000
1#
b10000101 &
1'
b10000101 +
b10000101 -
#1250000000
0#
0'
#1255000000
1#
b10010100 &
1'
b10010100 +
b10010100 -
#1260000000
0#
0'
#1265000000
1#
b10100011 &
1'
b10100011 +
b10100011 -
#1270000000
0#
0'
#1275000000
1#
b10110010 &
1'
b10110010 +
b10110010 -
#1280000000
0#
0'
#1285000000
1#
b11000001 &
1'
b11000001 +
b11000001 -
#1290000000
0#
0'
#1295000000
1#
b11010000 &
1'
b11010000 +
b11010000 -
#1300000000
0#
0'
#1305000000
1#
b11011111 &
1'
b11011111 +
b11011111 -
#1310000000
0#
0'
#1315000000
1#
b11101110 &
1'
b11101110 +
b11101110 -
#1320000000
0#
0'
#1325000000
1#
b11111101 &
1'
b11111101 +
b11111101 -
#1330000000
0#
0'
#1335000000
1#
1$
b00001100 &
1'
b00001100 +
1,
b00001100 -
1.
#1340000000
0#
0'
#1345000000
1#
0$
b00011011 &
1'
b00011011 +
0,
b00011011 -
0.
#1350000000
0#
0'
#1355000000
1#
b00101010 &
1'
b00101010 +
b00101010 -
#1360000000
0#
0'
#1365000000
1#
b00111001 &
1'
b00111001 +
b00111001 -
#1370000000
0#
0'
#1375000000
1#
b01001000 &
1'
b01001000 +
b01001000 -
#1380000000
0#
0'
#1385000000
1#
b01010111 &
1'
b01010111 +
b01010111 -
#1390000000
0#
0'
#1395000000
1#
b01100110 &
1'
b01100110 +
b01100110 -
#1400000000
0#
0'
#1405000000
1#
b01110101 &
1'
b01110101 +
b01110101 -
#1410000000
0#
0'
#1415000000
1#
b10000100 &
1'
b10000100 +
b10000100 -
#1420000000
0#
0'
#1425000000
1#
b10010011 &
1'
b10010011 +
b10010011 -
#1430000000
0#
0'
#1435000000
1#
b10100010 &
1'
b10100010 +
b10100010 -
#1440000000
0#
0'
#1445000000
1#
b10110001 &
1'
b10110001 +
b10110001 -
#1450000000
0#
0'
#1455000000
1#
b11000000 &
1'
b11000000 +
b11000000 -
#1460000000
0#
0'
#1465000000
1#
b11001111 &
1'
b11001111 +
b11001111 -
#1470000000
0#
0'
#1475000000
1#
b11011110 &
1'
b11011110 +
b11011110 -
#1480000000
0#
0'
#1485000000
1#
b11101101 &
1'
b11101101 +
b11101101 -
#1490000000
0#
0'
#1495000000
1#
b11111100 &
1'
b11111100 +
b11111100 -
#1500000000
0#
0'
#1505000000
1#
1$
b00001011 &
1'
b00001011 +
1,
b00001011 -
1.
#1510000000
0#
0'
#1515000000
1#
0$
b00011010 &
1'
b00011010 +
0,
b00011010 -
0.
#1520000000
0#
0'
#1525000000
1#
b00101001 &
1'
b00101001 +
b00101001 -
#1530000000
0#
0'
#1535000000
1#
b00111000 &
1'
b00111000 +
b00111000 -
#1540000000
0#
0'
#1545000000
1#
b01000111 &
1'
b01000111 +
b01000111 -
#1550000000
0#
0'
#1555000000
1#
b01010110 &
1'
b01010110 +
b01010110 -
#1560000000
0#
0'
#1565000000
1#
b01100101 &
1'
b01100101 +
b01100101 -
#1570000000
0#
0'
#1575000000
1#
b01110100 &
1'
b01110100 +
b01110100 -
#1580000000
0#
0'
#1585000000
1#
b10000011 &
1'
b10000011 +
b10000011 -
#1590000000
0#
0'
#1595000000
1#
b10010010 &
1'
b10010010 +
b10010010 -
#1600000000
0#
0'
#1605000000
1#
b10100001 &
1'
b10100001 +
b10100001 -
#1610000000
0#
0'
#1615000000
1#
b10110000 &
1'
b10110000 +
b10110000 -
#1620000000
0#
0'
#1625000000
1#
b10111111 &
1'
b10111111 +
b10111111 -
#1630000000
0#
0'
#1635000000
1#
b11001110 &
1'
b11001110 +
b11001110 -
#1640000000
0#
0'
#1645000000
1#
b11011101 &
1'
b11011101 +
b11011101 -
#1650000000
0#
0'
#1655000000
1#
b11101100 &
1'
b11101100 +
b11101100 -
#1660000000
0#
0'
#1665000000
1#
b11111011 &
1'
b11111011 +
b11111011 -
#1670000000
0#
0'
#1675000000
1#
1$
b00001010 &
1'
b00001010 +
1,
b00001010 -
1.
#1680000000
0#
0'
#1685000000
1#
0$
b00011001 &
1'
b00011001 +
0,
b00011001 -
0.
#1690000000
0#
0'
#1695000000
1#
b00101000 &
1'
b00101000 +
b00101000 -
#1700000000
0#
0'
#1705000000
1#
b00110111 &
1'
b00110111 +
b00110111 -
#1710000000
0#
0'
#1715000000
1#
b01000110 &
1'
b01000110 +
b01000110 -
#1720000000
0#
0'
#1725000000
1#
b01010101 &
1'
b01010101 +
b01010101 -
#1730000000
0#
0'
#1735000000
1#
b01100100 &
1'
b01100100 +
b01100100 -
#1740000000
0#
0'
#1745000000
1#
b01110011 &
1'
b01110011 +
b01110011 -
#1750000000
0#
0'
#1755000000
1#
b10000010 &
1'
b10000010 +
b10000010 -
#1760000000
0#
0'
#1765000000
1#
b10010001 &
1'
b10010001 +
b10010001 -
#1770000000
0#
0'
#1775000000
1#
b10100000 &
1'
b10100000 +
b10100000 -
#1780000000
0#
0'
#1785000000
1#
b10101111 &
1'
b10101111 +
b10101111 -
#1790000000
0#
0'
#1795000000
1#
b10111110 &
1'
b10111110 +
b10111110 -
#1800000000
0#
0'
#1805000000
1#
b11001101 &
1'
b11001101 +
b11001101 -
#1810000000
0#
0'
#1815000000
1#
b11011100 &
1'
b11011100 +
b11011100 -
#1820000000
0#
0'
#1825000000
1#
b11101011 &
1'
b11101011 +
b11101011 -
#1830000000
0#
0'
#1835000000
1#
b11111010 &
1'
b11111010 +
b11111010 -
#1840000000
0#
0'
#1845000000
1#
1$
b00001001 &
1'
b00001001 +
1,
b00001001 -
1.
#1850000000
0#
0'
#1855000000
1#
0$
b00011000 &
1'
b00011000 +
0,
b00011000 -
0.
#1860000000
0#
0'
#1865000000
1#
b00100111 &
1'
b00100111 +
b00100111 -
#1870000000
0#
0'
#1875000000
1#
b00110110 &
1'
b00110110 +
b00110110 -
#1880000000
0#
0'
#1885000000
1#
b01000101 &
1'
b01000101 +
b01000101 -
#1890000000
0#
0'
#1895000000
1#
b01010100 &
1'
b01010100 +
b01010100 -
#1900000000
0#
0'
#1905000000
1#
b01100011 &
1'
b01100011 +
b01100011 -
#1910000000
0#
0'
#1915000000
1#
b01110010 &
1'
b01110010 +
b01110010 -
#1920000000
0#
0'
#1925000000
1#
b10000001 &
1'
b10000001 +
b10000001 -
#1930000000
0#
0'
#1935000000
1#
b10010000 &
1'
b10010000 +
b10010000 -
#1940000000
0#
0'
#1945000000
1#
b10011111 &
1'
b10011111 +
b10011111 -
#1950000000
0#
0'
#1955000000
1#
b10101110 &
1'
b10101110 +
b10101110 -
#1960000000
0#
0'
#1965000000
1#
b10111101 &
1'
b10111101 +
b10111101 -
#1970000000
0#
0'
#1975000000
1#
b11001100 &
1'
b11001100 +
b11001100 -
#1980000000
0#
0'
#1985000000
1#
b11011011 &
1'
b11011011 +
b11011011 -
#1990000000
0#
0'
#1995000000
1#
b11101010 &
1'
b11101010 +
b11101010 -
#2000000000
0#
0'
#2005000000
1#
b11111001 &
1'
b11111001 +
b11111001 -
#2010000000
0#
0'
#2015000000
1#
1$
b00001000 &
1'
b00001000 +
1,
b00001000 -
1.
#2020000000
0#
0'
#2025000000
1#
0$
b00010111 &
1'
b00010111 +
0,
b00010111 -
0.
#2030000000
0#
0'
#2035000000
1#
b00100110 &
1'
b00100110 +
b00100110 -
#2040000000
0#
0'
#2045000000
1#
b00110101 &
1'
b00110101 +
b00110101 -
#2050000000
0#
0'
#2055000000
1#
b01000100 &
1'
b01000100 +
b01000100 -
#2060000000
0#
0'
#2065000000
1#
b01010011 &
1'
b01010011 +
b01010011 -
#2070000000
0#
0'
#2075000000
1#
b01100010 &
1'
b01100010 +
b01100010 -
#2080000000
0#
0'
#2085000000
1#
b01110001 &
1'
b01110001 +
b01110001 -
#2090000000
0#
0'
#2095000000
1#
b10000000 &
1'
b10000000 +
b10000000 -
#2100000000
0#
0'
#2105000000
1#
b10001111 &
1'
b10001111 +
b10001111 -
#2110000000
0#
0'
#2115000000
1#
b10011110 &
1'
b10011110 +
b10011110 -
#2120000000
0#
0'
#2125000000
1#
b10101101 &
1'
b10101101 +
b10101101 -
#2130000000
0#
0'
#2135000000
1#
b10111100 &
1'
b10111100 +
b10111100 -
#2140000000
0#
0'
#2145000000
1#
b11001011 &
1'
b11001011 +
b11001011 -
#2150000000
0#
0'
#2155000000
1#
b11011010 &
1'
b11011010 +
b11011010 -
#2160000000
0#
0'
#2165000000
1#
b11101001 &
1'
b11101001 +
b11101001 -
#2170000000
0#
0'
#2175000000
1#
b11111000 &
1'
b11111000 +
b11111000 -
#2180000000
0#
0'
#2185000000
1#
1$
b00000111 &
1'
b00000111 +
1,
b00000111 -
1.
#2190000000
0#
0'
#2195000000
1#
0$
b00010110 &
1'
b00010110 +
0,
b00010110 -
0.
#2200000000
0#
0'
#2205000000
1#
b00100101 &
1'
b00100101 +
b00100101 -
#2210000000
0#
0'
#2215000000
1#
b00110100 &
1'
b00110100 +
b00110100 -
#2220000000
0#
0'
#2225000000
1#
b01000011 &
1'
b01000011 +
b01000011 -
#2230000000
0#
0'
#2235000000
1#
b01010010 &
1'
b01010010 +
b01010010 -
#2240000000
0#
0'
#2245000000
1#
b01100001 &
1'
b01100001 +
b01100001 -
#2250000000
0#
0'
#2255000000
1#
b01110000 &
1'
b01110000 +
b01110000 -
#2260000000
0#
0'
#2265000000
1#
b01111111 &
1'
b01111111 +
b01111111 -
#2270000000
0#
0'
#2275000000
1#
b10001110 &
1'
b10001110 +
b10001110 -
#2280000000
0#
0'
#2285000000
1#
b10011101 &
1'
b10011101 +
b10011101 -
#2290000000
0#
0'
#2295000000
1#
b10101100 &
1'
b10101100 +
b10101100 -
#2300000000
0#
0'
#2305000000
1#
b10111011 &
1'
b10111011 +
b10111011 -
#2310000000
0#
0'
#2315000000
1#
b11001010 &
1'
b11001010 +
b11001010 -
#2320000000
0#
0'
#2325000000
1#
b11011001 &
1'
b11011001 +
b11011001 -
#2330000000
0#
0'
#2335000000
1#
b11101000 &
1'
b11101000 +
b11101000 -
#2340000000
0#
0'
#2345000000
1#
b11110111 &
1'
b11110111 +
b11110111 -
#2350000000
0#
0'
#2355000000
1#
1$
b00000110 &
1'
b00000110 +
1,
b00000110 -
1.
#2360000000
0#
0'
#2365000000
1#
0$
b00010101 &
1'
b00010101 +
0,
b00010101 -
0.
#2370000000
0#
0'
#2375000000
1#
b00100100 &
1'
b00100100 +
b00100100 -
#2380000000
0#
0'
#2385000000
1#
b00110011 &
1'
b00110011 +
b00110011 -
#2390000000
0#
0'
#2395000000
1#
b01000010 &
1'
b01000010 +
b01000010 -
#2400000000
0#
0'
#2405000000
1#
b01010001 &
1'
b01010001 +
b01010001 -
#2410000000
0#
0'
#2415000000
1#
b01100000 &
1'
b01100000 +
b01100000 -
#2420000000
0#
0'
#2425000000
1#
b01101111 &
1'
b01101111 +
b01101111 -
#2430000000
0#
0'
#2435000000
1#
b01111110 &
1'
b01111110 +
b01111110 -
#2440000000
0#
0'
#2445000000
1#
b10001101 &
1'
b10001101 +
b10001101 -
#2450000000
0#
0'
#2455000000
1#
b10011100 &
1'
b10011100 +
b10011100 -
#2460000000
0#
0'
#2465000000
1#
b10101011 &
1'
b10101011 +
b10101011 -
#2470000000
0#
0'
#2475000000
1#
b10111010 &
1'
b10111010 +
b10111010 -
#2480000000
0#
0'
#2485000000
1#
b11001001 &
1'
b11001001 +
b11001001 -
#2490000000
0#
0'
#2495000000
1#
b11011000 &
1'
b11011000 +
b11011000 -
#2500000000
0#
0'
#2505000000
1#
b11100111 &
1'
b11100111 +
b11100111 -
#2510000000
0#
0'
#2515000000
1#
b11110110 &
1'
b11110110 +
b11110110 -
#2520000000
0#
0'
#2525000000
1#
1$
b00000101 &
1'
b00000101 +
1,
b00000101 -
1.
#2530000000
0#
0'
#2535000000
1#
0$
b00010100 &
1'
b00010100 +
0,
b00010100 -
0.
#2540000000
0#
0'
#2545000000
1#
b00100011 &
1'
b00100011 +
b00100011 -
#2550000000
0#
0'
#2555000000
1#
b00110010 &
1'
b00110010 +
b00110010 -
#2560000000
0#
0'
#2565000000
1#
b01000001 &
1'
b01000001 +
b01000001 -
#2570000000
0#
0'
#2575000000
1#
b01010000 &
1'
b01010000 +
b01010000 -
#2580000000
0#
0'
#2585000000
1#
b01011111 &
1'
b01011111 +
b01011111 -
#2590000000
0#
0'
#2595000000
1#
b01101110 &
1'
b01101110 +
b01101110 -
#2600000000
0#
0'
#2605000000
1#
b01111101 &
1'
b01111101 +
b01111101 -
#2610000000
0#
0'
#2615000000
1#
b10001100 &
1'
b10001100 +
b10001100 -
#2620000000
0#
0'
#2625000000
1#
b10011011 &
1'
b10011011 +
b10011011 -
#2630000000
0#
0'
#2635000000
1#
b10101010 &
1'
b10101010 +
b10101010 -
#2640000000
0#
0'
#2645000000
1#
b10111001 &
1'
b10111001 +
b10111001 -
#2650000000
0#
0'
#2655000000
1#
b11001000 &
1'
b11001000 +
b11001000 -
#2660000000
0#
0'
#2665000000
1#
b11010111 &
1'
b11010111 +
b11010111 -
#2670000000
0#
0'
#2675000000
1#
b11100110 &
1'
b11100110 +
b11100110 -
#2680000000
0#
0'
#2685000000
1#
b11110101 &
1'
b11110101 +
b11110101 -
#2690000000
0#
0'
#2695000000
1#
1$
b00000100 &
1'
b00000100 +
1,
b00000100 -
1.
#2700000000
0#
0'
#2705000000
1#
0$
b00010011 &
1'
b00010011 +
0,
b00010011 -
0.
#2710000000
0#
0'
#2715000000
1#
b00100010 &
1'
b00100010 +
b00100010 -
#2720000000
0#
0'
#2725000000
1#
b00110001 &
1'
b00110001 +
b00110001 -
#2730000000
0#
0'
#2735000000
1#
b01000000 &
1'
b01000000 +
b01000000 -
#2740000000
0#
0'
#2745000000
1#
b01001111 &
1'
b01001111 +
b01001111 -
#2750000000
0#
0'
#2755000000
1#
b01011110 &
1'
b01011110 +
b01011110 -
#2760000000
0#
0'
#2765000000
1#
b01101101 &
1'
b01101101 +
b01101101 -
#2770000000
0#
0'
#2775000000
1#
b01111100 &
1'
b01111100 +
b01111100 -
#2780000000
0#
0'
#2785000000
1#
b10001011 &
1'
b10001011 +
b10001011 -
#2790000000
0#
0'
#2795000000
1#
b10011010 &
1'
b10011010 +
b10011010 -
#2800000000
0#
0'
#2805000000
1#
b10101001 &
1'
b10101001 +
b10101001 -
#2810000000
0#
0'
#2815000000
1#
b10111000 &
1'
b10111000 +
b10111000 -
#2820000000
0#
0'
#2825000000
1#
b11000111 &
1'
b11000111 +
b11000111 -
#2830000000
0#
0'
#2835000000
1#
b11010110 &
1'
b11010110 +
b11010110 -
#2840000000
0#
0'
#2845000000
1#
b11100101 &
1'
b11100101 +
b11100101 -
#2850000000
0#
0'
#2855000000
1#
b11110100 &
1'
b11110100 +
b11110100 -
#2860000000
0#
0'
#2865000000
1#
1$
b00000011 &
1'
b00000011 +
1,
b00000011 -
1.
#2870000000
0#
0'
#2875000000
1#
0$
b00010010 &
1'
b00010010 +
0,
b00010010 -
0.
#2880000000
0#
0'
#2885000000
1#
b00100001 &
1'
b00100001 +
b00100001 -
#2890000000
0#
0'
#2895000000
1#
b00110000 &
1'
b00110000 +
b00110000 -
#2900000000
0#
0'
#2905000000
1#
b00111111 &
1'
b00111111 +
b00111111 -
#2910000000
0#
0'
#2915000000
1#
b01001110 &
1'
b01001110 +
b01001110 -
#2920000000
0#
0'
#2925000000
1#
b01011101 &
1'
b01011101 +
b01011101 -
#2930000000
0#
0'
#2935000000
1#
b01101100 &
1'
b01101100 +
b01101100 -
#2940000000
0#
0'
#2945000000
1#
b01111011 &
1'
b01111011 +
b01111011 -
#2950000000
0#
0'
#2955000000
1#
b10001010 &
1'
b10001010 +
b10001010 -
#2960000000
0#
0'
#2965000000
1#
b10011001 &
1'
b10011001 +
b10011001 -
#2970000000
0#
0'
#2975000000
1#
b10101000 &
1'
b10101000 +
b10101000 -
#2980000000
0#
0'
#2985000000
1#
b10110111 &
1'
b10110111 +
b10110111 -
#2990000000
0#
0'
#2995000000
1#
b11000110 &
1'
b11000110 +
b11000110 -
