DecadeCounter.vhd
library ieee;
use ieee.std_logic_1164.all;
use ieee.numeric_std.all;
use ieee.math_real.all;

entity DecadeCounter is
    port (
        CE,clk   : in   std_logic;
        TC       : out  std_logic
    );
end entity DecadeCounter;

architecture rtl of DecadeCounter is

    signal counter : unsigned(3 downto 0) := (others => '0');

begin
    -- Counting up
    process(clk)
    begin
        if rising_edge(clk) then
            if CE = '1' then
                counter <=  "0000" when (counter = "1001") else
                            counter + 1;
            end if;
        end if;
    end process;

    -- Emitting TC
    process(counter)
    begin
        TC <=   '1' when (counter = "1001") else
                '0';
    end process;
end architecture;

DecadeCounter_tb.vhd
library ieee;
use ieee.std_logic_1164.all;
use ieee.numeric_std.all;
use ieee.math_real.all;

entity DecadeCounter_tb is
end entity DecadeCounter_tb;

architecture rtl_tb of DecadeCounter_tb is

    constant CLK_PERIOD : time := 5 ns;

    signal CE   : std_logic := '0';
    signal CLK  : std_logic := '0';
    signal TC   : std_logic := '0'; 

    component DecadeCounter
        port (
            CE,clk  : in    std_logic;
            TC      : out   std_logic
        );
    end component;

begin

    dut: DecadeCounter
    port map (
        CE      => CE,
        CLK     => CLK,
        TC      => TC
    );

    CLK <= not CLK after CLK_PERIOD;

    stim: process
    begin
        CE <= '0';
        wait for 4 * CLK_PERIOD;

        CE <= '1';
        wait for 100 * CLK_PERIOD;

        CE <= '0';
        wait for 4 * CLK_PERIOD;

        wait;
    end process;

end;

DecadeCounter_tb.vcd
$date
  Fri May  2 02:00:48 2025
$end
$version
  GHDL v0
$end
$timescale
  1 fs
$end
$scope module standard $end
$upscope $end
$scope module textio $end
$upscope $end
$scope module std_logic_1164 $end
$upscope $end
$scope module numeric_std $end
$upscope $end
$scope module math_real $end
$upscope $end
$scope module decadecounter_tb $end
$var reg 1 ! ce $end
$var reg 1 " clk $end
$var reg 1 # tc $end
$scope module dut $end
$var reg 1 $ ce $end
$var reg 1 % clk $end
$var reg 1 & tc $end
$var reg 4 ' counter[3:0] $end
$upscope $end
$upscope $end
$enddefinitions $end
#0
0!
0"
0#
0$
0%
0&
b0000 '
#5000000
1"
1%
#10000000
0"
0%
#15000000
1"
1%
#20000000
1!
0"
1$
0%
#25000000
1"
1%
b0001 '
#30000000
0"
0%
#35000000
1"
1%
b0010 '
#40000000
0"
0%
#45000000
1"
1%
b0011 '
#50000000
0"
0%
#55000000
1"
1%
b0100 '
#60000000
0"
0%
#65000000
1"
1%
b0101 '
#70000000
0"
0%
#75000000
1"
1%
b0110 '
#80000000
0"
0%
#85000000
1"
1%
b0111 '
#90000000
0"
0%
#95000000
1"
1%
b1000 '
#100000000
0"
0%
#105000000
1"
1#
1%
1&
b1001 '
#110000000
0"
0%
#115000000
1"
0#
1%
0&
b0000 '
#120000000
0"
0%
#125000000
1"
1%
b0001 '
#130000000
0"
0%
#135000000
1"
1%
b0010 '
#140000000
0"
0%
#145000000
1"
1%
b0011 '
#150000000
0"
0%
#155000000
1"
1%
b0100 '
#160000000
0"
0%
#165000000
1"
1%
b0101 '
#170000000
0"
0%
#175000000
1"
1%
b0110 '
#180000000
0"
0%
#185000000
1"
1%
b0111 '
#190000000
0"
0%
#195000000
1"
1%
b1000 '
#200000000
0"
0%
#205000000
1"
1#
1%
1&
b1001 '
#210000000
0"
0%
#215000000
1"
0#
1%
0&
b0000 '
#220000000
0"
0%
#225000000
1"
1%
b0001 '
#230000000
0"
0%
#235000000
1"
1%
b0010 '
#240000000
0"
0%
#245000000
1"
1%
b0011 '
#250000000
0"
0%
#255000000
1"
1%
b0100 '
#260000000
0"
0%
#265000000
1"
1%
b0101 '
#270000000
0"
0%
#275000000
1"
1%
b0110 '
#280000000
0"
0%
#285000000
1"
1%
b0111 '
#290000000
0"
0%
#295000000
1"
1%
b1000 '
#300000000
0"
0%
#305000000
1"
1#
1%
1&
b1001 '
#310000000
0"
0%
#315000000
1"
0#
1%
0&
b0000 '
#320000000
0"
0%
#325000000
1"
1%
b0001 '
#330000000
0"
0%
#335000000
1"
1%
b0010 '
#340000000
0"
0%
#345000000
1"
1%
b0011 '
#350000000
0"
0%
#355000000
1"
1%
b0100 '
#360000000
0"
0%
#365000000
1"
1%
b0101 '
#370000000
0"
0%
#375000000
1"
1%
b0110 '
#380000000
0"
0%
#385000000
1"
1%
b0111 '
#390000000
0"
0%
#395000000
1"
1%
b1000 '
#400000000
0"
0%
#405000000
1"
1#
1%
1&
b1001 '
#410000000
0"
0%
#415000000
1"
0#
1%
0&
b0000 '
#420000000
0"
0%
#425000000
1"
1%
b0001 '
#430000000
0"
0%
#435000000
1"
1%
b0010 '
#440000000
0"
0%
#445000000
1"
1%
b0011 '
#450000000
0"
0%
#455000000
1"
1%
b0100 '
#460000000
0"
0%
#465000000
1"
1%
b0101 '
#470000000
0"
0%
#475000000
1"
1%
b0110 '
#480000000
0"
0%
#485000000
1"
1%
b0111 '
#490000000
0"
0%
#495000000
1"
1%
b1000 '
#500000000
0"
0%
#505000000
1"
1#
1%
1&
b1001 '
#510000000
0"
0%
#515000000
1"
0#
1%
0&
b0000 '
#520000000
0!
0"
0$
0%
