DecadeCounter.vhd
library ieee;
use ieee.std_logic_1164.all;
use ieee.numeric_std.all;
use ieee.math_real.all;

entity DecadeCounter is
    port (
        CE,clk   : in   std_logic;
        TC       : out  std_logic
    );
end entity DecadeCounter;

architecture rtl of DecadeCounter is

    signal counter : unsigned(3 downto 0) := (others => '0');

begin
    -- Counting up
    process(clk)
    begin
        if rising_edge(clk) then
            if CE = '1' then
                counter <=  "0000" when (counter = "1001") else
                            counter + 1;
            end if;
        end if;
    end process;

    -- Emitting TC
    process(counter)
    begin
        TC <=   '1' when (counter = "1001") else
                '0';
    end process;
end architecture;

FourDigitCounter.vhd
library IEEE;
use IEEE.std_logic_1164.all;
use IEEE.numeric_std.all;


ENTITY FourDigitCounter IS
PORT ( 	CE,clk	:	in	STD_LOGIC;
        TC		:	out	STD_LOGIC);
end FourDigitCounter;


ARCHITECTURE Structural of FourDigitCounter is

component DecadeCounter
PORT ( 	CE,clk	:	in	STD_LOGIC;
        TC		:	out	STD_LOGIC);
end component;

--create intermediate signals (used to wire up the multiple decade counters)
signal CE_tens, CE_hundreds, CE_thousands : std_logic;


BEGIN

	--Define the 4 different decade counters. Wire them up to the appropriate signals and inputs/outputs of the top-level.
    Ones: DecadeCounter
    port map (
        CE => CE,
        clk => CLK,
        TC => CE_tens
    );

    Tens: DecadeCounter
    port map (
        CE => CE_tens,
        clk => CLK,
        TC => CE_hundreds
    );

    Hundreds: DecadeCounter
    port map (
        CE => CE_hundreds,
        clk => CLK,
        TC => CE_thousands
    );

    Thousands: DecadeCounter
    port map (
        CE => CE_thousands,
        clk => CLK,
        TC => TC
    );

end Structural;

FourDigitCounter_tb.vhd
library IEEE;
use IEEE.std_logic_1164.all;

entity FourDigitCounter_tb is
end FourDigitCounter_tb;

architecture testbench of FourDigitCounter_tb is

component FourDigitCounter
PORT ( 	CE,clk	:	in	STD_LOGIC;
        TC		:	out	STD_LOGIC);
end component;

signal 	CE, clk, TC	:	STD_LOGIC := '0';



begin

uut : FourDigitCounter PORT MAP(
	clk => clk,
    CE => CE,
    TC => TC);
    
    
    
    clk_proc : process
    begin
    	clk <= '0';
        wait for 5 ns;
        clk <= '1';
        wait for 5 ns;
    end process clk_proc;
    
stim_proc : process
BEGIN
	wait for 20 ns;
	
    CE <= '1';
    
 
    wait;
    
END PROCESS stim_proc;

end testbench;

FourDigitCounter_tb.vcd
$date
  Fri May  2 13:48:30 2025
$end
$version
  GHDL v0
$end
$timescale
  1 fs
$end
$scope module standard $end
$upscope $end
$scope module textio $end
$upscope $end
$scope module std_logic_1164 $end
$upscope $end
$scope module numeric_std $end
$upscope $end
$scope module math_real $end
$upscope $end
$scope module fourdigitcounter_tb $end
$var reg 1 ! ce $end
$var reg 1 " clk $end
$var reg 1 # tc $end
$scope module uut $end
$var reg 1 $ ce $end
$var reg 1 % clk $end
$var reg 1 & tc $end
$var reg 1 ' ce_tens $end
$var reg 1 ( ce_hundreds $end
$var reg 1 ) ce_thousands $end
$scope module ones $end
$var reg 1 * ce $end
$var reg 1 + clk $end
$var reg 1 , tc $end
$var reg 4 - counter[3:0] $end
$upscope $end
$scope module tens $end
$var reg 1 . ce $end
$var reg 1 / clk $end
$var reg 1 0 tc $end
$var reg 4 1 counter[3:0] $end
$upscope $end
$scope module hundreds $end
$var reg 1 2 ce $end
$var reg 1 3 clk $end
$var reg 1 4 tc $end
$var reg 4 5 counter[3:0] $end
$upscope $end
$scope module thousands $end
$var reg 1 6 ce $end
$var reg 1 7 clk $end
$var reg 1 8 tc $end
$var reg 4 9 counter[3:0] $end
$upscope $end
$upscope $end
$upscope $end
$enddefinitions $end
#0
0!
0"
0#
0$
0%
0&
0'
0(
0)
0*
0+
0,
b0000 -
0.
0/
00
b0000 1
02
03
04
b0000 5
06
07
08
b0000 9
#5000000
1"
1%
1+
1/
13
17
#10000000
0"
0%
0+
0/
03
07
#15000000
1"
1%
1+
1/
13
17
#20000000
1!
0"
1$
0%
1*
0+
0/
03
07
#25000000
1"
1%
1+
b0001 -
1/
13
17
#30000000
0"
0%
0+
0/
03
07
#35000000
1"
1%
1+
b0010 -
1/
13
17
#40000000
0"
0%
0+
0/
03
07
#45000000
1"
1%
1+
b0011 -
1/
13
17
#50000000
0"
0%
0+
0/
03
07
#55000000
1"
1%
1+
b0100 -
1/
13
17
#60000000
0"
0%
0+
0/
03
07
#65000000
1"
1%
1+
b0101 -
1/
13
17
#70000000
0"
0%
0+
0/
03
07
#75000000
1"
1%
1+
b0110 -
1/
13
17
#80000000
0"
0%
0+
0/
03
07
#85000000
1"
1%
1+
b0111 -
1/
13
17
#90000000
0"
0%
0+
0/
03
07
#95000000
1"
1%
1+
b1000 -
1/
13
17
#100000000
0"
0%
0+
0/
03
07
#105000000
1"
1%
1'
1+
1,
b1001 -
1.
1/
13
17
#110000000
0"
0%
0+
0/
03
07
#115000000
1"
1%
0'
1+
0,
b0000 -
0.
1/
b0001 1
13
17
#120000000
0"
0%
0+
0/
03
07
#125000000
1"
1%
1+
b0001 -
1/
13
17
#130000000
0"
0%
0+
0/
03
07
#135000000
1"
1%
1+
b0010 -
1/
13
17
#140000000
0"
0%
0+
0/
03
07
#145000000
1"
1%
1+
b0011 -
1/
13
17
#150000000
0"
0%
0+
0/
03
07
#155000000
1"
1%
1+
b0100 -
1/
13
17
#160000000
0"
0%
0+
0/
03
07
#165000000
1"
1%
1+
b0101 -
1/
13
17
#170000000
0"
0%
0+
0/
03
07
#175000000
1"
1%
1+
b0110 -
1/
13
17
#180000000
0"
0%
0+
0/
03
07
#185000000
1"
1%
1+
b0111 -
1/
13
17
#190000000
0"
0%
0+
0/
03
07
#195000000
1"
1%
1+
b1000 -
1/
13
17
#200000000
0"
0%
0+
0/
03
07
#205000000
1"
1%
1'
1+
1,
b1001 -
1.
1/
13
17
#210000000
0"
0%
0+
0/
03
07
#215000000
1"
1%
0'
1+
0,
b0000 -
0.
1/
b0010 1
13
17
#220000000
0"
0%
0+
0/
03
07
#225000000
1"
1%
1+
b0001 -
1/
13
17
#230000000
0"
0%
0+
0/
03
07
#235000000
1"
1%
1+
b0010 -
1/
13
17
#240000000
0"
0%
0+
0/
03
07
#245000000
1"
1%
1+
b0011 -
1/
13
17
#250000000
0"
0%
0+
0/
03
07
#255000000
1"
1%
1+
b0100 -
1/
13
17
#260000000
0"
0%
0+
0/
03
07
#265000000
1"
1%
1+
b0101 -
1/
13
17
#270000000
0"
0%
0+
0/
03
07
#275000000
1"
1%
1+
b0110 -
1/
13
17
#280000000
0"
0%
0+
0/
03
07
#285000000
1"
1%
1+
b0111 -
1/
13
17
#290000000
0"
0%
0+
0/
03
07
#295000000
1"
1%
1+
b1000 -
1/
13
17
#300000000
0"
0%
0+
0/
03
07
#305000000
1"
1%
1'
1+
1,
b1001 -
1.
1/
13
17
#310000000
0"
0%
0+
0/
03
07
#315000000
1"
1%
0'
1+
0,
b0000 -
0.
1/
b0011 1
13
17
#320000000
0"
0%
0+
0/
03
07
#325000000
1"
1%
1+
b0001 -
1/
13
17
#330000000
0"
0%
0+
0/
03
07
#335000000
1"
1%
1+
b0010 -
1/
13
17
#340000000
0"
0%
0+
0/
03
07
#345000000
1"
1%
1+
b0011 -
1/
13
17
#350000000
0"
0%
0+
0/
03
07
#355000000
1"
1%
1+
b0100 -
1/
13
17
#360000000
0"
0%
0+
0/
03
07
#365000000
1"
1%
1+
b0101 -
1/
13
17
#370000000
0"
0%
0+
0/
03
07
#375000000
1"
1%
1+
b0110 -
1/
13
17
#380000000
0"
0%
0+
0/
03
07
#385000000
1"
1%
1+
b0111 -
1/
13
17
#390000000
0"
0%
0+
0/
03
07
#395000000
1"
1%
1+
b1000 -
1/
13
17
#400000000
0"
0%
0+
0/
03
07
#405000000
1"
1%
1'
1+
1,
b1001 -
1.
1/
13
17
#410000000
0"
0%
0+
0/
03
07
#415000000
1"
1%
0'
1+
0,
b0000 -
0.
1/
b0100 1
13
17
#420000000
0"
0%
0+
0/
03
07
#425000000
1"
1%
1+
b0001 -
1/
13
17
#430000000
0"
0%
0+
0/
03
07
#435000000
1"
1%
1+
b0010 -
1/
13
17
#440000000
0"
0%
0+
0/
03
07
#445000000
1"
1%
1+
b0011 -
1/
13
17
#450000000
0"
0%
0+
0/
03
07
#455000000
1"
1%
1+
b0100 -
1/
13
17
#460000000
0"
0%
0+
0/
03
07
#465000000
1"
1%
1+
b0101 -
1/
13
17
#470000000
0"
0%
0+
0/
03
07
#475000000
1"
1%
1+
b0110 -
1/
13
17
#480000000
0"
0%
0+
0/
03
07
#485000000
1"
1%
1+
b0111 -
1/
13
17
#490000000
0"
0%
0+
0/
03
07
#495000000
1"
1%
1+
b1000 -
1/
13
17
#500000000
0"
0%
0+
0/
03
07
#505000000
1"
1%
1'
1+
1,
b1001 -
1.
1/
13
17
#510000000
0"
0%
0+
0/
03
07
#515000000
1"
1%
0'
1+
0,
b0000 -
0.
1/
b0101 1
13
17
#520000000
0"
0%
0+
0/
03
07
#525000000
1"
1%
1+
b0001 -
1/
13
17
#530000000
0"
0%
0+
0/
03
07
#535000000
1"
1%
1+
b0010 -
1/
13
17
#540000000
0"
0%
0+
0/
03
07
#545000000
1"
1%
1+
b0011 -
1/
13
17
#550000000
0"
0%
0+
0/
03
07
#555000000
1"
1%
1+
b0100 -
1/
13
17
#560000000
0"
0%
0+
0/
03
07
#565000000
1"
1%
1+
b0101 -
1/
13
17
#570000000
0"
0%
0+
0/
03
07
#575000000
1"
1%
1+
b0110 -
1/
13
17
#580000000
0"
0%
0+
0/
03
07
#585000000
1"
1%
1+
b0111 -
1/
13
17
#590000000
0"
0%
0+
0/
03
07
#595000000
1"
1%
1+
b1000 -
1/
13
17
#600000000
0"
0%
0+
0/
03
07
#605000000
1"
1%
1'
1+
1,
b1001 -
1.
1/
13
17
#610000000
0"
0%
0+
0/
03
07
#615000000
1"
1%
0'
1+
0,
b0000 -
0.
1/
b0110 1
13
17
#620000000
0"
0%
0+
0/
03
07
#625000000
1"
1%
1+
b0001 -
1/
13
17
#630000000
0"
0%
0+
0/
03
07
#635000000
1"
1%
1+
b0010 -
1/
13
17
#640000000
0"
0%
0+
0/
03
07
#645000000
1"
1%
1+
b0011 -
1/
13
17
#650000000
0"
0%
0+
0/
03
07
#655000000
1"
1%
1+
b0100 -
1/
13
17
#660000000
0"
0%
0+
0/
03
07
#665000000
1"
1%
1+
b0101 -
1/
13
17
#670000000
0"
0%
0+
0/
03
07
#675000000
1"
1%
1+
b0110 -
1/
13
17
#680000000
0"
0%
0+
0/
03
07
#685000000
1"
1%
1+
b0111 -
1/
13
17
#690000000
0"
0%
0+
0/
03
07
#695000000
1"
1%
1+
b1000 -
1/
13
17
#700000000
0"
0%
0+
0/
03
07
#705000000
1"
1%
1'
1+
1,
b1001 -
1.
1/
13
17
#710000000
0"
0%
0+
0/
03
07
#715000000
1"
1%
0'
1+
0,
b0000 -
0.
1/
b0111 1
13
17
#720000000
0"
0%
0+
0/
03
07
#725000000
1"
1%
1+
b0001 -
1/
13
17
#730000000
0"
0%
0+
0/
03
07
#735000000
1"
1%
1+
b0010 -
1/
13
17
#740000000
0"
0%
0+
0/
03
07
#745000000
1"
1%
1+
b0011 -
1/
13
17
#750000000
0"
0%
0+
0/
03
07
#755000000
1"
1%
1+
b0100 -
1/
13
17
#760000000
0"
0%
0+
0/
03
07
#765000000
1"
1%
1+
b0101 -
1/
13
17
#770000000
0"
0%
0+
0/
03
07
#775000000
1"
1%
1+
b0110 -
1/
13
17
#780000000
0"
0%
0+
0/
03
07
#785000000
1"
1%
1+
b0111 -
1/
13
17
#790000000
0"
0%
0+
0/
03
07
#795000000
1"
1%
1+
b1000 -
1/
13
17
#800000000
0"
0%
0+
0/
03
07
#805000000
1"
1%
1'
1+
1,
b1001 -
1.
1/
13
17
#810000000
0"
0%
0+
0/
03
07
#815000000
1"
1%
0'
1+
0,
b0000 -
0.
1/
b1000 1
13
17
#820000000
0"
0%
0+
0/
03
07
#825000000
1"
1%
1+
b0001 -
1/
13
17
#830000000
0"
0%
0+
0/
03
07
#835000000
1"
1%
1+
b0010 -
1/
13
17
#840000000
0"
0%
0+
0/
03
07
#845000000
1"
1%
1+
b0011 -
1/
13
17
#850000000
0"
0%
0+
0/
03
07
#855000000
1"
1%
1+
b0100 -
1/
13
17
#860000000
0"
0%
0+
0/
03
07
#865000000
1"
1%
1+
b0101 -
1/
13
17
#870000000
0"
0%
0+
0/
03
07
#875000000
1"
1%
1+
b0110 -
1/
13
17
#880000000
0"
0%
0+
0/
03
07
#885000000
1"
1%
1+
b0111 -
1/
13
17
#890000000
0"
0%
0+
0/
03
07
#895000000
1"
1%
1+
b1000 -
1/
13
17
#900000000
0"
0%
0+
0/
03
07
#905000000
1"
1%
1'
1+
1,
b1001 -
1.
1/
13
17
#910000000
0"
0%
0+
0/
03
07
#915000000
1"
1%
0'
1(
1+
0,
b0000 -
0.
1/
10
b1001 1
12
13
17
#920000000
0"
0%
0+
0/
03
07
#925000000
1"
1%
1+
b0001 -
1/
13
b0001 5
17
#930000000
0"
0%
0+
0/
03
07
#935000000
1"
1%
1+
b0010 -
1/
13
b0010 5
17
#940000000
0"
0%
0+
0/
03
07
#945000000
1"
1%
1+
b0011 -
1/
13
b0011 5
17
#950000000
0"
0%
0+
0/
03
07
#955000000
1"
1%
1+
b0100 -
1/
13
b0100 5
17
#960000000
0"
0%
0+
0/
03
07
#965000000
1"
1%
1+
b0101 -
1/
13
b0101 5
17
#970000000
0"
0%
0+
0/
03
07
#975000000
1"
1%
1+
b0110 -
1/
13
b0110 5
17
#980000000
0"
0%
0+
0/
03
07
#985000000
1"
1%
1+
b0111 -
1/
13
b0111 5
17
#990000000
0"
0%
0+
0/
03
07
#995000000
1"
1%
1+
b1000 -
1/
13
b1000 5
17
#1000000000
0"
0%
0+
0/
03
07
#1005000000
1"
1%
1'
1)
1+
1,
b1001 -
1.
1/
13
14
b1001 5
16
17
#1010000000
0"
0%
0+
0/
03
07
#1015000000
1"
1%
0'
0(
0)
1+
0,
b0000 -
0.
1/
00
b0000 1
02
13
04
b0000 5
06
17
b0001 9
#1020000000
0"
0%
0+
0/
03
07
#1025000000
1"
1%
1+
b0001 -
1/
13
17
#1030000000
0"
0%
0+
0/
03
07
#1035000000
1"
1%
1+
b0010 -
1/
13
17
#1040000000
0"
0%
0+
0/
03
07
#1045000000
1"
1%
1+
b0011 -
1/
13
17
#1050000000
0"
0%
0+
0/
03
07
#1055000000
1"
1%
1+
b0100 -
1/
13
17
#1060000000
0"
0%
0+
0/
03
07
#1065000000
1"
1%
1+
b0101 -
1/
13
17
#1070000000
0"
0%
0+
0/
03
07
#1075000000
1"
1%
1+
b0110 -
1/
13
17
#1080000000
0"
0%
0+
0/
03
07
#1085000000
1"
1%
1+
b0111 -
1/
13
17
#1090000000
0"
0%
0+
0/
03
07
#1095000000
1"
1%
1+
b1000 -
1/
13
17
#1100000000
0"
0%
0+
0/
03
07
#1105000000
1"
1%
1'
1+
1,
b1001 -
1.
1/
13
17
#1110000000
0"
0%
0+
0/
03
07
#1115000000
1"
1%
0'
1+
0,
b0000 -
0.
1/
b0001 1
13
17
#1120000000
0"
0%
0+
0/
03
07
#1125000000
1"
1%
1+
b0001 -
1/
13
17
#1130000000
0"
0%
0+
0/
03
07
#1135000000
1"
1%
1+
b0010 -
1/
13
17
#1140000000
0"
0%
0+
0/
03
07
#1145000000
1"
1%
1+
b0011 -
1/
13
17
#1150000000
0"
0%
0+
0/
03
07
#1155000000
1"
1%
1+
b0100 -
1/
13
17
#1160000000
0"
0%
0+
0/
03
07
#1165000000
1"
1%
1+
b0101 -
1/
13
17
#1170000000
0"
0%
0+
0/
03
07
#1175000000
1"
1%
1+
b0110 -
1/
13
17
#1180000000
0"
0%
0+
0/
03
07
#1185000000
1"
1%
1+
b0111 -
1/
13
17
#1190000000
0"
0%
0+
0/
03
07
#1195000000
1"
1%
1+
b1000 -
1/
13
17
#1200000000
0"
0%
0+
0/
03
07
#1205000000
1"
1%
1'
1+
1,
b1001 -
1.
1/
13
17
#1210000000
0"
0%
0+
0/
03
07
#1215000000
1"
1%
0'
1+
0,
b0000 -
0.
1/
b0010 1
13
17
#1220000000
0"
0%
0+
0/
03
07
#1225000000
1"
1%
1+
b0001 -
1/
13
17
#1230000000
0"
0%
0+
0/
03
07
#1235000000
1"
1%
1+
b0010 -
1/
13
17
#1240000000
0"
0%
0+
0/
03
07
#1245000000
1"
1%
1+
b0011 -
1/
13
17
#1250000000
0"
0%
0+
0/
03
07
#1255000000
1"
1%
1+
b0100 -
1/
13
17
#1260000000
0"
0%
0+
0/
03
07
#1265000000
1"
1%
1+
b0101 -
1/
13
17
#1270000000
0"
0%
0+
0/
03
07
#1275000000
1"
1%
1+
b0110 -
1/
13
17
#1280000000
0"
0%
0+
0/
03
07
#1285000000
1"
1%
1+
b0111 -
1/
13
17
#1290000000
0"
0%
0+
0/
03
07
#1295000000
1"
1%
1+
b1000 -
1/
13
17
#1300000000
0"
0%
0+
0/
03
07
#1305000000
1"
1%
1'
1+
1,
b1001 -
1.
1/
13
17
#1310000000
0"
0%
0+
0/
03
07
#1315000000
1"
1%
0'
1+
0,
b0000 -
0.
1/
b0011 1
13
17
#1320000000
0"
0%
0+
0/
03
07
#1325000000
1"
1%
1+
b0001 -
1/
13
17
#1330000000
0"
0%
0+
0/
03
07
#1335000000
1"
1%
1+
b0010 -
1/
13
17
#1340000000
0"
0%
0+
0/
03
07
#1345000000
1"
1%
1+
b0011 -
1/
13
17
#1350000000
0"
0%
0+
0/
03
07
#1355000000
1"
1%
1+
b0100 -
1/
13
17
#1360000000
0"
0%
0+
0/
03
07
#1365000000
1"
1%
1+
b0101 -
1/
13
17
#1370000000
0"
0%
0+
0/
03
07
#1375000000
1"
1%
1+
b0110 -
1/
13
17
#1380000000
0"
0%
0+
0/
03
07
#1385000000
1"
1%
1+
b0111 -
1/
13
17
#1390000000
0"
0%
0+
0/
03
07
#1395000000
1"
1%
1+
b1000 -
1/
13
17
#1400000000
0"
0%
0+
0/
03
07
#1405000000
1"
1%
1'
1+
1,
b1001 -
1.
1/
13
17
#1410000000
0"
0%
0+
0/
03
07
#1415000000
1"
1%
0'
1+
0,
b0000 -
0.
1/
b0100 1
13
17
#1420000000
0"
0%
0+
0/
03
07
#1425000000
1"
1%
1+
b0001 -
1/
13
17
#1430000000
0"
0%
0+
0/
03
07
#1435000000
1"
1%
1+
b0010 -
1/
13
17
#1440000000
0"
0%
0+
0/
03
07
#1445000000
1"
1%
1+
b0011 -
1/
13
17
#1450000000
0"
0%
0+
0/
03
07
#1455000000
1"
1%
1+
b0100 -
1/
13
17
#1460000000
0"
0%
0+
0/
03
07
#1465000000
1"
1%
1+
b0101 -
1/
13
17
#1470000000
0"
0%
0+
0/
03
07
#1475000000
1"
1%
1+
b0110 -
1/
13
17
#1480000000
0"
0%
0+
0/
03
07
#1485000000
1"
1%
1+
b0111 -
1/
13
17
#1490000000
0"
0%
0+
0/
03
07
#1495000000
1"
1%
1+
b1000 -
1/
13
17
#1500000000
0"
0%
0+
0/
03
07
#1505000000
1"
1%
1'
1+
1,
b1001 -
1.
1/
13
17
#1510000000
0"
0%
0+
0/
03
07
#1515000000
1"
1%
0'
1+
0,
b0000 -
0.
1/
b0101 1
13
17
#1520000000
0"
0%
0+
0/
03
07
#1525000000
1"
1%
1+
b0001 -
1/
13
17
#1530000000
0"
0%
0+
0/
03
07
#1535000000
1"
1%
1+
b0010 -
1/
13
17
#1540000000
0"
0%
0+
0/
03
07
#1545000000
1"
1%
1+
b0011 -
1/
13
17
#1550000000
0"
0%
0+
0/
03
07
#1555000000
1"
1%
1+
b0100 -
1/
13
17
#1560000000
0"
0%
0+
0/
03
07
#1565000000
1"
1%
1+
b0101 -
1/
13
17
#1570000000
0"
0%
0+
0/
03
07
#1575000000
1"
1%
1+
b0110 -
1/
13
17
#1580000000
0"
0%
0+
0/
03
07
#1585000000
1"
1%
1+
b0111 -
1/
13
17
#1590000000
0"
0%
0+
0/
03
07
#1595000000
1"
1%
1+
b1000 -
1/
13
17
#1600000000
0"
0%
0+
0/
03
07
#1605000000
1"
1%
1'
1+
1,
b1001 -
1.
1/
13
17
#1610000000
0"
0%
0+
0/
03
07
#1615000000
1"
1%
0'
1+
0,
b0000 -
0.
1/
b0110 1
13
17
#1620000000
0"
0%
0+
0/
03
07
#1625000000
1"
1%
1+
b0001 -
1/
13
17
#1630000000
0"
0%
0+
0/
03
07
#1635000000
1"
1%
1+
b0010 -
1/
13
17
#1640000000
0"
0%
0+
0/
03
07
#1645000000
1"
1%
1+
b0011 -
1/
13
17
#1650000000
0"
0%
0+
0/
03
07
#1655000000
1"
1%
1+
b0100 -
1/
13
17
#1660000000
0"
0%
0+
0/
03
07
#1665000000
1"
1%
1+
b0101 -
1/
13
17
#1670000000
0"
0%
0+
0/
03
07
#1675000000
1"
1%
1+
b0110 -
1/
13
17
#1680000000
0"
0%
0+
0/
03
07
#1685000000
1"
1%
1+
b0111 -
1/
13
17
#1690000000
0"
0%
0+
0/
03
07
#1695000000
1"
1%
1+
b1000 -
1/
13
17
#1700000000
0"
0%
0+
0/
03
07
#1705000000
1"
1%
1'
1+
1,
b1001 -
1.
1/
13
17
#1710000000
0"
0%
0+
0/
03
07
#1715000000
1"
1%
0'
1+
0,
b0000 -
0.
1/
b0111 1
13
17
#1720000000
0"
0%
0+
0/
03
07
#1725000000
1"
1%
1+
b0001 -
1/
13
17
#1730000000
0"
0%
0+
0/
03
07
#1735000000
1"
1%
1+
b0010 -
1/
13
17
#1740000000
0"
0%
0+
0/
03
07
#1745000000
1"
1%
1+
b0011 -
1/
13
17
#1750000000
0"
0%
0+
0/
03
07
#1755000000
1"
1%
1+
b0100 -
1/
13
17
#1760000000
0"
0%
0+
0/
03
07
#1765000000
1"
1%
1+
b0101 -
1/
13
17
#1770000000
0"
0%
0+
0/
03
07
#1775000000
1"
1%
1+
b0110 -
1/
13
17
#1780000000
0"
0%
0+
0/
03
07
#1785000000
1"
1%
1+
b0111 -
1/
13
17
#1790000000
0"
0%
0+
0/
03
07
#1795000000
1"
1%
1+
b1000 -
1/
13
17
#1800000000
0"
0%
0+
0/
03
07
#1805000000
1"
1%
1'
1+
1,
b1001 -
1.
1/
13
17
#1810000000
0"
0%
0+
0/
03
07
#1815000000
1"
1%
0'
1+
0,
b0000 -
0.
1/
b1000 1
13
17
#1820000000
0"
0%
0+
0/
03
07
#1825000000
1"
1%
1+
b0001 -
1/
13
17
#1830000000
0"
0%
0+
0/
03
07
#1835000000
1"
1%
1+
b0010 -
1/
13
17
#1840000000
0"
0%
0+
0/
03
07
#1845000000
1"
1%
1+
b0011 -
1/
13
17
#1850000000
0"
0%
0+
0/
03
07
#1855000000
1"
1%
1+
b0100 -
1/
13
17
#1860000000
0"
0%
0+
0/
03
07
#1865000000
1"
1%
1+
b0101 -
1/
13
17
#1870000000
0"
0%
0+
0/
03
07
#1875000000
1"
1%
1+
b0110 -
1/
13
17
#1880000000
0"
0%
0+
0/
03
07
#1885000000
1"
1%
1+
b0111 -
1/
13
17
#1890000000
0"
0%
0+
0/
03
07
#1895000000
1"
1%
1+
b1000 -
1/
13
17
#1900000000
0"
0%
0+
0/
03
07
#1905000000
1"
1%
1'
1+
1,
b1001 -
1.
1/
13
17
#1910000000
0"
0%
0+
0/
03
07
#1915000000
1"
1%
0'
1(
1+
0,
b0000 -
0.
1/
10
b1001 1
12
13
17
#1920000000
0"
0%
0+
0/
03
07
#1925000000
1"
1%
1+
b0001 -
1/
13
b0001 5
17
#1930000000
0"
0%
0+
0/
03
07
#1935000000
1"
1%
1+
b0010 -
1/
13
b0010 5
17
#1940000000
0"
0%
0+
0/
03
07
#1945000000
1"
1%
1+
b0011 -
1/
13
b0011 5
17
#1950000000
0"
0%
0+
0/
03
07
#1955000000
1"
1%
1+
b0100 -
1/
13
b0100 5
17
#1960000000
0"
0%
0+
0/
03
07
#1965000000
1"
1%
1+
b0101 -
1/
13
b0101 5
17
#1970000000
0"
0%
0+
0/
03
07
#1975000000
1"
1%
1+
b0110 -
1/
13
b0110 5
17
#1980000000
0"
0%
0+
0/
03
07
#1985000000
1"
1%
1+
b0111 -
1/
13
b0111 5
17
#1990000000
0"
0%
0+
0/
03
07
#1995000000
1"
1%
1+
b1000 -
1/
13
b1000 5
17
#2000000000
0"
0%
0+
0/
03
07
#2005000000
1"
1%
1'
1)
1+
1,
b1001 -
1.
1/
13
14
b1001 5
16
17
#2010000000
0"
0%
0+
0/
03
07
#2015000000
1"
1%
0'
0(
0)
1+
0,
b0000 -
0.
1/
00
b0000 1
02
13
04
b0000 5
06
17
b0010 9
#2020000000
0"
0%
0+
0/
03
07
#2025000000
1"
1%
1+
b0001 -
1/
13
17
#2030000000
0"
0%
0+
0/
03
07
#2035000000
1"
1%
1+
b0010 -
1/
13
17
#2040000000
0"
0%
0+
0/
03
07
#2045000000
1"
1%
1+
b0011 -
1/
13
17
#2050000000
0"
0%
0+
0/
03
07
#2055000000
1"
1%
1+
b0100 -
1/
13
17
#2060000000
0"
0%
0+
0/
03
07
#2065000000
1"
1%
1+
b0101 -
1/
13
17
#2070000000
0"
0%
0+
0/
03
07
#2075000000
1"
1%
1+
b0110 -
1/
13
17
#2080000000
0"
0%
0+
0/
03
07
#2085000000
1"
1%
1+
b0111 -
1/
13
17
#2090000000
0"
0%
0+
0/
03
07
#2095000000
1"
1%
1+
b1000 -
1/
13
17
#2100000000
0"
0%
0+
0/
03
07
#2105000000
1"
1%
1'
1+
1,
b1001 -
1.
1/
13
17
#2110000000
0"
0%
0+
0/
03
07
#2115000000
1"
1%
0'
1+
0,
b0000 -
0.
1/
b0001 1
13
17
#2120000000
0"
0%
0+
0/
03
07
#2125000000
1"
1%
1+
b0001 -
1/
13
17
#2130000000
0"
0%
0+
0/
03
07
#2135000000
1"
1%
1+
b0010 -
1/
13
17
#2140000000
0"
0%
0+
0/
03
07
#2145000000
1"
1%
1+
b0011 -
1/
13
17
#2150000000
0"
0%
0+
0/
03
07
#2155000000
1"
1%
1+
b0100 -
1/
13
17
#2160000000
0"
0%
0+
0/
03
07
#2165000000
1"
1%
1+
b0101 -
1/
13
17
#2170000000
0"
0%
0+
0/
03
07
#2175000000
1"
1%
1+
b0110 -
1/
13
17
#2180000000
0"
0%
0+
0/
03
07
#2185000000
1"
1%
1+
b0111 -
1/
13
17
#2190000000
0"
0%
0+
0/
03
07
#2195000000
1"
1%
1+
b1000 -
1/
13
17
#2200000000
0"
0%
0+
0/
03
07
#2205000000
1"
1%
1'
1+
1,
b1001 -
1.
1/
13
17
#2210000000
0"
0%
0+
0/
03
07
#2215000000
1"
1%
0'
1+
0,
b0000 -
0.
1/
b0010 1
13
17
#2220000000
0"
0%
0+
0/
03
07
#2225000000
1"
1%
1+
b0001 -
1/
13
17
#2230000000
0"
0%
0+
0/
03
07
#2235000000
1"
1%
1+
b0010 -
1/
13
17
#2240000000
0"
0%
0+
0/
03
07
#2245000000
1"
1%
1+
b0011 -
1/
13
17
#2250000000
0"
0%
0+
0/
03
07
#2255000000
1"
1%
1+
b0100 -
1/
13
17
#2260000000
0"
0%
0+
0/
03
07
#2265000000
1"
1%
1+
b0101 -
1/
13
17
#2270000000
0"
0%
0+
0/
03
07
#2275000000
1"
1%
1+
b0110 -
1/
13
17
#2280000000
0"
0%
0+
0/
03
07
#2285000000
1"
1%
1+
b0111 -
1/
13
17
#2290000000
0"
0%
0+
0/
03
07
#2295000000
1"
1%
1+
b1000 -
1/
13
17
#2300000000
0"
0%
0+
0/
03
07
#2305000000
1"
1%
1'
1+
1,
b1001 -
1.
1/
13
17
#2310000000
0"
0%
0+
0/
03
07
#2315000000
1"
1%
0'
1+
0,
b0000 -
0.
1/
b0011 1
13
17
#2320000000
0"
0%
0+
0/
03
07
#2325000000
1"
1%
1+
b0001 -
1/
13
17
#2330000000
0"
0%
0+
0/
03
07
#2335000000
1"
1%
1+
b0010 -
1/
13
17
#2340000000
0"
0%
0+
0/
03
07
#2345000000
1"
1%
1+
b0011 -
1/
13
17
#2350000000
0"
0%
0+
0/
03
07
#2355000000
1"
1%
1+
b0100 -
1/
13
17
#2360000000
0"
0%
0+
0/
03
07
#2365000000
1"
1%
1+
b0101 -
1/
13
17
#2370000000
0"
0%
0+
0/
03
07
#2375000000
1"
1%
1+
b0110 -
1/
13
17
#2380000000
0"
0%
0+
0/
03
07
#2385000000
1"
1%
1+
b0111 -
1/
13
17
#2390000000
0"
0%
0+
0/
03
07
#2395000000
1"
1%
1+
b1000 -
1/
13
17
#2400000000
0"
0%
0+
0/
03
07
#2405000000
1"
1%
1'
1+
1,
b1001 -
1.
1/
13
17
#2410000000
0"
0%
0+
0/
03
07
#2415000000
1"
1%
0'
1+
0,
b0000 -
0.
1/
b0100 1
13
17
#2420000000
0"
0%
0+
0/
03
07
#2425000000
1"
1%
1+
b0001 -
1/
13
17
#2430000000
0"
0%
0+
0/
03
07
#2435000000
1"
1%
1+
b0010 -
1/
13
17
#2440000000
0"
0%
0+
0/
03
07
#2445000000
1"
1%
1+
b0011 -
1/
13
17
#2450000000
0"
0%
0+
0/
03
07
#2455000000
1"
1%
1+
b0100 -
1/
13
17
#2460000000
0"
0%
0+
0/
03
07
#2465000000
1"
1%
1+
b0101 -
1/
13
17
#2470000000
0"
0%
0+
0/
03
07
#2475000000
1"
1%
1+
b0110 -
1/
13
17
#2480000000
0"
0%
0+
0/
03
07
#2485000000
1"
1%
1+
b0111 -
1/
13
17
#2490000000
0"
0%
0+
0/
03
07
#2495000000
1"
1%
1+
b1000 -
1/
13
17
#2500000000
0"
0%
0+
0/
03
07
