Queue.vhd
-- Code your design here
library IEEE;
use IEEE.std_logic_1164.all;
use IEEE.numeric_std.all;

ENTITY Queue IS
PORT ( 	clk		:	in	STD_LOGIC; --10 MHz clock
		Write	: 	in 	STD_LOGIC;
		Read	: 	in 	STD_LOGIC;
        Data_in	:	in	STD_LOGIC_VECTOR(7 downto 0);
		Data_out:	out	STD_LOGIC_VECTOR(7 downto 0);
        Empty	:	out	STD_LOGIC;
        Full	:	out	STD_LOGIC);
end Queue;


architecture behavior of Queue is

CONSTANT QUEUE_LENGTH : integer := 8;

type regfile is array(0 to QUEUE_LENGTH-1) of STD_LOGIC_VECTOR(7 downto 0);
signal Queue_reg : regfile := (others =>(others => '0'));

signal W_ADDR : integer := 0;
signal R_ADDR : integer := 0;
signal Element_cnt : integer := 0;
signal Full_sig, Empty_sig : std_logic := '0';

BEGIN

--------------
-- Element_cnt 
--------------
process(all)
begin
    if rising_edge(clk) then
        if Write = '1' and Full_sig = '0' then
            Element_cnt <= Element_cnt + 1;
        end if;

        if Read = '1' and Empty_sig = '0' then
            Element_cnt <= Element_cnt - 1;
        end if;
    end if;

    Empty_sig <= '0';
    if Element_cnt = 0 then
        Empty_sig <= '1';
    end if;

    Full_sig <= '0';
    if Element_cnt = 8 then
        Full_sig <= '1';
    end if;
end process;

---------------------
-- Read Address Count
---------------------
process(all)
begin
    if rising_edge(clk) then
        if Read = '1' and Empty_Sig = '0' then
            if R_ADDR <= 7 then
                R_ADDR <= 0;
            else
                R_ADDR <= R_ADDR + 1;
            end if;
        end if;
    end if;
end process;

---------------------
-- Write Address Count
---------------------
process(all)
begin
    if rising_edge(clk) then
        if Write = '1' and Full_Sig = '0' then
            if W_ADDR = 7 then
                W_ADDR <= 0;
            else
                W_ADDR <= W_ADDR + 1;
            end if;
        end if;
    end if;
end process;

------------------
-- Regfile process
------------------
process(all)
begin
    if rising_edge(clk) then
        if Write = '1' and Full_Sig = '0' then
            Queue_reg(W_ADDR) <= Data_in;
        end if;
    end if;
end process;

--Assign internal signals to the outputs
Full <= Full_sig;
Empty <= Empty_sig;

--We always want the Data_out to be displaying the front of the queue
Data_out <= Queue_reg(R_ADDR);

end behavior;

Queue_tb.vhd
-- Code your testbench here
library IEEE;
use IEEE.std_logic_1164.all;

entity Queue_tb is
end Queue_tb;

architecture testbench of Queue_tb is

component Queue IS
PORT ( 	clk		:	in	STD_LOGIC; --10 MHz clock
		Write	: 	in 	STD_LOGIC;
		read	: 	in 	STD_LOGIC;
        Data_in	:	in	STD_LOGIC_VECTOR(7 downto 0);
		Data_out:	out	STD_LOGIC_VECTOR(7 downto 0));
end component;



signal 	clk		:	STD_LOGIC; --10 MHz clock
signal 	Write	: 	STD_LOGIC 	:= '0';
signal 	Read	: 	STD_LOGIC	:= '0';
signal 	Data_in	:	STD_LOGIC_Vector(7 downto 0) := "00000000";
signal 	Data_out:	STD_LOGIC_Vector(7 downto 0) := "00000000";


begin

uut : Queue PORT MAP(
		clk  => CLK,
		Read => Read,
        Write => Write,
        Data_in => Data_in,
		Data_out => Data_out);
    
    
clk_proc : process
BEGIN

  CLK <= '0';
  wait for 5 ns;   

  CLK <= '1';
  wait for 5 ns;

END PROCESS clk_proc;

stim_proc : process
begin
	
    wait for 10 ns;
    
    Data_in <= "11110000";--0xF0
    Write <= '1';
    Wait for 10 ns;
    Write <= '0';
    
    wait for 40 ns;
    Data_in <= "00001111";--0x0F
    Write <= '1';
    wait for 10 ns;
    write <= '0';
    
    wait for 40 ns;
    Data_in <= "10101010";--0xAA
    Write <= '1';
    wait for 10 ns;
    write <= '0';
  
  	wait for 40 ns;
    Data_in <= "01010011";--0x53
    Write <= '1';
    wait for 10 ns;
    write <= '0';
    
    wait for 40 ns;
    Data_in <= "11010010";--0xD2
    Write <= '1';
    wait for 10 ns;
    write <= '0';
    
    wait for 40 ns;
    Data_in <= "11111111";--0xFF
    Write <= '1';
    wait for 10 ns;
    write <= '0';
    
    wait for 40 ns;
    Data_in <= "00110001";--0x31
    Write <= '1';
    wait for 10 ns;
    write <= '0';
    
    wait for 40 ns;
    Data_in <= "01010101";--0x55
    Write <= '1';
    wait for 10 ns;
    write <= '0';
    
    wait for 40 ns;
    Data_in <= "10001100";--0x8C  --The queue should be full and this should not get stored
    Write <= '1';
    wait for 10 ns;
    write <= '0';
   
    wait for 40 ns; -- Read once
    read <= '1';
    wait for 10 ns;
    read <= '0';
	
    wait for 40 ns; -- Read once
    read <= '1';
    wait for 10 ns;
    read <= '0';
    
    wait for 40 ns;
    Data_in <= "11000111";--0xC7
    Write <= '1';
    wait for 10 ns;
    write <= '0';
  
  	wait for 40 ns;
    Data_in <= "00000001";--0x01
    Write <= '1';
    wait for 10 ns;
    write <= '0';
    
    wait for 40 ns; -- Read once
    read <= '1';
    wait for 10 ns;
    read <= '0';
	
    wait for 40 ns; -- Read once
    read <= '1';
    wait for 10 ns;
    read <= '0';
    
    wait for 40 ns; -- Read once
    read <= '1';
    wait for 10 ns;
    read <= '0';
	
    wait for 40 ns; -- Read once
    read <= '1';
    wait for 10 ns;
    read <= '0';
    
    wait for 40 ns; -- Read once
    read <= '1';
    wait for 10 ns;
    read <= '0';
    
    wait for 40 ns; -- Read once
    read <= '1';
    wait for 10 ns;
    read <= '0';
    
    wait for 40 ns; -- Read once
    read <= '1';
    wait for 10 ns;
    read <= '0';
    
    wait for 40 ns; -- Read once
    read <= '1';
    wait for 10 ns;
    read <= '0';
    
    wait for 40 ns; -- Read once --tbe queue is already empty, so this should do nothing.
    read <= '1';
    wait for 10 ns;
    read <= '0';
    
    wait for 40 ns;
    Data_in <= "11111111";--0xFF
    Write <= '1';
    wait for 10 ns;
    write <= '0';
    
    wait;
end process stim_proc;
end testbench;

Queue_tb.vcd
$date
  Mon May 12 13:45:42 2025
$end
$version
  GHDL v0
$end
$timescale
  1 fs
$end
$scope module standard $end
$upscope $end
$scope module textio $end
$upscope $end
$scope module std_logic_1164 $end
$upscope $end
$scope module numeric_std $end
$upscope $end
$scope module queue_tb $end
$var reg 1 ! clk $end
$var reg 1 " write $end
$var reg 1 # read $end
$var reg 8 $ data_in[7:0] $end
$var reg 8 % data_out[7:0] $end
$scope module uut $end
$var reg 1 & clk $end
$var reg 1 ' write $end
$var reg 1 ( read $end
$var reg 8 ) data_in[7:0] $end
$var reg 8 * data_out[7:0] $end
$var reg 1 + empty $end
$var reg 1 , full $end
$comment queue_reg is not handled $end
$var integer 32 - w_addr $end
$var integer 32 . r_addr $end
$var integer 32 / element_cnt $end
$var reg 1 0 full_sig $end
$var reg 1 1 empty_sig $end
$upscope $end
$upscope $end
$enddefinitions $end
#0
0!
0"
0#
b00000000 $
b00000000 %
0&
0'
0(
b00000000 )
b00000000 *
1+
0,
b0 -
b0 .
b0 /
00
11
#5000000
1!
1&
#10000000
0!
1"
b11110000 $
0&
1'
b11110000 )
#15000000
1!
b11110000 %
1&
b11110000 *
0+
b1 -
b1 /
01
#20000000
0!
0"
0&
0'
#25000000
1!
1&
#30000000
0!
0&
#35000000
1!
1&
#40000000
0!
0&
#45000000
1!
1&
#50000000
0!
0&
#55000000
1!
1&
#60000000
0!
1"
b00001111 $
0&
1'
b00001111 )
#65000000
1!
1&
b10 -
b10 /
#70000000
0!
0"
0&
0'
#75000000
1!
1&
#80000000
0!
0&
#85000000
1!
1&
#90000000
0!
0&
#95000000
1!
1&
#100000000
0!
0&
#105000000
1!
1&
#110000000
0!
1"
b10101010 $
0&
1'
b10101010 )
#115000000
1!
1&
b11 -
b11 /
#120000000
0!
0"
0&
0'
#125000000
1!
1&
#130000000
0!
0&
#135000000
1!
1&
#140000000
0!
0&
#145000000
1!
1&
#150000000
0!
0&
#155000000
1!
1&
#160000000
0!
1"
b01010011 $
0&
1'
b01010011 )
#165000000
1!
1&
b100 -
b100 /
#170000000
0!
0"
0&
0'
#175000000
1!
1&
#180000000
0!
0&
#185000000
1!
1&
#190000000
0!
0&
#195000000
1!
1&
#200000000
0!
0&
#205000000
1!
1&
#210000000
0!
1"
b11010010 $
0&
1'
b11010010 )
#215000000
1!
1&
b101 -
b101 /
#220000000
0!
0"
0&
0'
#225000000
1!
1&
#230000000
0!
0&
#235000000
1!
1&
#240000000
0!
0&
#245000000
1!
1&
#250000000
0!
0&
#255000000
1!
1&
#260000000
0!
1"
b11111111 $
0&
1'
b11111111 )
#265000000
1!
1&
b110 -
b110 /
#270000000
0!
0"
0&
0'
#275000000
1!
1&
#280000000
0!
0&
#285000000
1!
1&
#290000000
0!
0&
#295000000
1!
1&
#300000000
0!
0&
#305000000
1!
1&
#310000000
0!
1"
b00110001 $
0&
1'
b00110001 )
#315000000
1!
1&
b111 -
b111 /
#320000000
0!
0"
0&
0'
#325000000
1!
1&
#330000000
0!
0&
#335000000
1!
1&
#340000000
0!
0&
#345000000
1!
1&
#350000000
0!
0&
#355000000
1!
1&
#360000000
0!
1"
b01010101 $
0&
1'
b01010101 )
#365000000
1!
1&
1,
b0 -
b1000 /
10
#370000000
0!
0"
0&
0'
#375000000
1!
1&
#380000000
0!
0&
#385000000
1!
1&
#390000000
0!
0&
#395000000
1!
1&
#400000000
0!
0&
#405000000
1!
1&
#410000000
0!
1"
b10001100 $
0&
1'
b10001100 )
#415000000
1!
1&
#420000000
0!
0"
0&
0'
#425000000
1!
1&
#430000000
0!
0&
#435000000
1!
1&
#440000000
0!
0&
#445000000
1!
1&
#450000000
0!
0&
#455000000
1!
1&
#460000000
0!
1#
0&
1(
#465000000
1!
1&
0,
b111 /
00
#470000000
0!
0#
0&
0(
#475000000
1!
1&
#480000000
0!
0&
#485000000
1!
1&
#490000000
0!
0&
#495000000
1!
1&
#500000000
0!
0&
#505000000
1!
1&
#510000000
0!
1#
0&
1(
#515000000
1!
1&
b110 /
#520000000
0!
0#
0&
0(
#525000000
1!
1&
#530000000
0!
0&
#535000000
1!
1&
#540000000
0!
0&
#545000000
1!
1&
#550000000
0!
0&
#555000000
1!
1&
#560000000
0!
1"
b11000111 $
0&
1'
b11000111 )
#565000000
1!
b11000111 %
1&
b11000111 *
b1 -
b111 /
#570000000
0!
0"
0&
0'
#575000000
1!
1&
#580000000
0!
0&
#585000000
1!
1&
#590000000
0!
0&
#595000000
1!
1&
#600000000
0!
0&
#605000000
1!
1&
#610000000
0!
1"
b00000001 $
0&
1'
b00000001 )
#615000000
1!
1&
1,
b10 -
b1000 /
10
#620000000
0!
0"
0&
0'
#625000000
1!
1&
#630000000
0!
0&
#635000000
1!
1&
#640000000
0!
0&
#645000000
1!
1&
#650000000
0!
0&
#655000000
1!
1&
#660000000
0!
1#
0&
1(
#665000000
1!
1&
0,
b111 /
00
#670000000
0!
0#
0&
0(
#675000000
1!
1&
#680000000
0!
0&
#685000000
1!
1&
#690000000
0!
0&
#695000000
1!
1&
#700000000
0!
0&
#705000000
1!
1&
#710000000
0!
1#
0&
1(
#715000000
1!
1&
b110 /
#720000000
0!
0#
0&
0(
#725000000
1!
1&
#730000000
0!
0&
#735000000
1!
1&
#740000000
0!
0&
#745000000
1!
1&
#750000000
0!
0&
#755000000
1!
1&
#760000000
0!
1#
0&
1(
#765000000
1!
1&
b101 /
#770000000
0!
0#
0&
0(
#775000000
1!
1&
#780000000
0!
0&
#785000000
1!
1&
#790000000
0!
0&
#795000000
1!
1&
#800000000
0!
0&
#805000000
1!
1&
#810000000
0!
1#
0&
1(
#815000000
1!
1&
b100 /
#820000000
0!
0#
0&
0(
#825000000
1!
1&
#830000000
0!
0&
#835000000
1!
1&
#840000000
0!
0&
#845000000
1!
1&
#850000000
0!
0&
#855000000
1!
1&
#860000000
0!
1#
0&
1(
#865000000
1!
1&
b11 /
#870000000
0!
0#
0&
0(
#875000000
1!
1&
#880000000
0!
0&
#885000000
1!
1&
#890000000
0!
0&
#895000000
1!
1&
#900000000
0!
0&
#905000000
1!
1&
#910000000
0!
1#
0&
1(
#915000000
1!
1&
b10 /
#920000000
0!
0#
0&
0(
#925000000
1!
1&
#930000000
0!
0&
#935000000
1!
1&
#940000000
0!
0&
#945000000
1!
1&
#950000000
0!
0&
#955000000
1!
1&
#960000000
0!
1#
0&
1(
#965000000
1!
1&
b1 /
#970000000
0!
0#
0&
0(
#975000000
1!
1&
#980000000
0!
0&
#985000000
1!
1&
#990000000
0!
0&
#995000000
1!
1&
#1000000000
0!
0&
#1005000000
1!
1&
#1010000000
0!
1#
0&
1(
#1015000000
1!
1&
1+
b0 /
11
#1020000000
0!
0#
0&
0(
#1025000000
1!
1&
#1030000000
0!
0&
#1035000000
1!
1&
#1040000000
0!
0&
#1045000000
1!
1&
#1050000000
0!
0&
#1055000000
1!
1&
#1060000000
0!
1#
0&
1(
#1065000000
1!
1&
#1070000000
0!
0#
0&
0(
#1075000000
1!
1&
#1080000000
0!
0&
#1085000000
1!
1&
#1090000000
0!
0&
#1095000000
1!
1&
#1100000000
0!
0&
#1105000000
1!
1&
#1110000000
0!
1"
b11111111 $
0&
1'
b11111111 )
#1115000000
1!
1&
0+
b11 -
b1 /
01
#1120000000
0!
0"
0&
0'
