lab5/lab5_controller.vhd
library IEEE;
use IEEE.STD_LOGIC_1164.ALL;
use IEEE.NUMERIC_STD.ALL;

entity lab5_controller is
    Port (
        --timing:
        clk_port            : in std_logic;

        --control inputs:
        load_port           : in std_logic;
        clear_port          : in std_logic;

        --control outputs:
        term1_en_port       : out std_logic;
        term2_en_port       : out std_logic;
        sum_en_port         : out std_logic;
        reset_port          : out std_logic);
end lab5_controller;

architecture behavioral_architecture of lab5_controller is

    type state is (S_Idle, S_GotA, S_GotA_Idle, S_GotB, S_GotB_Idle, S_ShowY);

    signal curr_state, next_state : state;

begin

    StateUpdate: process(clk_port, clear_port)
    begin
        if clear_port = '1' then -- Asynchronous clear
            curr_state <= S_Idle;
        elsif rising_edge(clk_port) then -- Synchronous state update
            curr_state <= next_state;
        end if;
    end process StateUpdate;

    NextStateLogic: process(curr_state, load_port)
    begin
        next_state <= curr_state;

        case curr_state is

            when S_Idle =>
                if load_port = '1' then
                    next_state <= S_GotA;
                end if;

            when S_GotA =>
                next_state <= S_GotA_Idle;

            when S_GotA_Idle =>
                if load_port = '1' then 
                    next_state <= S_GotB;
                end if;

            when S_GotB =>
                next_state <= S_GotB_Idle;

            when S_GotB_Idle =>
                if load_port = '1' then
                    next_state <= S_ShowY;
                end if;

            when S_ShowY =>
                -- Stay in S_ShowY until clear_port resets FSM asynchronously
                null;
        end case;
    end process NextStateLogic;

    OutputLogic: process(curr_state)
    begin
        term1_en_port <= '0';
        term2_en_port <= '0';
        sum_en_port   <= '0';
        reset_port    <= '0';

        case curr_state is

            when S_Idle =>
                -- Reset datapath registers in the Idle state
                reset_port <= '1';

            when S_GotA =>
                -- Enable loading and storing the first term (A)
                term1_en_port <= '1';

            when S_GotA_Idle =>
                -- After staying up for a clock cycle, go to idle
                term1_en_port <= '0';

            when S_GotB =>
                -- Enable loading and storing the second term (B)
                term2_en_port <= '1';

            when S_GotB_Idle =>
                -- After staying up for a clock cycle, go to idle
                term2_en_port <= '0';

            when S_ShowY =>
                -- Enable calculating and storage of the sum (Y)
                sum_en_port <= '1';

        end case;
    end process OutputLogic;

end behavioral_architecture;

lab5/lab5_controller_tb.vhd
library IEEE;
use IEEE.STD_LOGIC_1164.ALL;
use IEEE.NUMERIC_STD.ALL;

entity lab5_controller_tb is
end entity;

architecture testbench of lab5_controller_tb is

	-- Simulation clock period 100 MHz
    constant CLK_PERIOD : time := 10 ns;

    component lab5_controller is
        Port (
            --timing:
            clk_port            : in std_logic;

            --control inputs:
            load_port           : in std_logic; 
            clear_port          : in std_logic;

            --control outputs:
            term1_en_port       : out std_logic;
            term2_en_port       : out std_logic;
            sum_en_port         : out std_logic;
            reset_port          : out std_logic);
    end component;

    -- Inputs to UUT
    signal tb_clk           : std_logic := '0';
    signal tb_op            : std_logic := '0';
    signal tb_clear         : std_logic := '0';

    -- Outputs from UUT
    signal tb_term1_en      : std_logic;
    signal tb_term2_en      : std_logic;
    signal tb_sum_en        : std_logic;
    signal tb_reset         : std_logic;

begin

    --Instantiate the Unit Under Test (UUT)
    uut: lab5_controller
        port map(
            clk_port        => tb_clk,
            load_port       => tb_op,    -- Connect to tb_op
            clear_port      => tb_clear, -- Connect to tb_clear
            term1_en_port   => tb_term1_en,
            term2_en_port   => tb_term2_en,
            sum_en_port     => tb_sum_en,
            reset_port      => tb_reset );

    --Clock Generation Process
    clkgen_proc: process
    begin
		tb_clk <= '0';
		wait for CLK_PERIOD / 2;

		tb_clk <= '1';
		wait for CLK_PERIOD / 2;
    end process clkgen_proc;

    --Stimulus Process
    stim_proc: process

        -- Procedure to simulate a monopulse for one clock cycle
        procedure pulse(signal sig : out std_logic) is
        begin

            sig <= '1';
            wait for CLK_PERIOD;
            
            sig <= '0';
            wait for CLK_PERIOD;

        end procedure pulse;

    begin

        tb_op    <= '0';
        tb_clear <= '0';

        wait for CLK_PERIOD * 2;

        -- Test 1: Initial State Check
        -- Check initial outputs (reset='1', others='0' in S_Idle)
        wait for CLK_PERIOD * 5;

        -- Test 2: Asynchronous Reset Test (Pulse Clear)
		-- Check state returns to S_Idle (reset='1', others='0')
        pulse(tb_clear);
        wait for CLK_PERIOD * 5;

        -- Test 3: Normal Operation Sequence
        -- 3a: S_Idle -> S_GotA
		-- Check state is S_GotA (term1_en='1', reset='0', others='0')
        pulse(tb_op);
        wait for CLK_PERIOD * 5;

        -- 3b: S_GotA -> S_GotB
        -- Check state is S_GotB (term2_en='1', reset='0', others='0')
        pulse(tb_op);
        wait for CLK_PERIOD * 5;

        -- 3c: S_GotB -> S_ShowY
        -- Check state is S_ShowY (sum_en='1', reset='0', others='0')
        pulse(tb_op);
        wait for CLK_PERIOD * 5;

        -- Stay in S_ShowY until cleared

        -- Test 4: Reset during Operation
		-- Check state returns to S_Idle (reset='1', others='0')
        pulse(tb_clear);
        wait for CLK_PERIOD * 5;

        -- mid-sequence reset test
        pulse(tb_op); -- Idle -> GotA
        wait for CLK_PERIOD * 2;

		-- Should go back to Idle
        pulse(tb_clear);
        wait for CLK_PERIOD * 5;

        wait;
    end process stim_proc;

end testbench;

lab5/lab5_controller_tb.vcd
$date
  Mon May  5 16:17:57 2025
$end
$version
  GHDL v0
$end
$timescale
  1 fs
$end
$scope module standard $end
$upscope $end
$scope module textio $end
$upscope $end
$scope module std_logic_1164 $end
$upscope $end
$scope module numeric_std $end
$upscope $end
$scope module lab5_controller_tb $end
$var reg 1 ! tb_clk $end
$var reg 1 " tb_op $end
$var reg 1 # tb_clear $end
$var reg 1 $ tb_term1_en $end
$var reg 1 % tb_term2_en $end
$var reg 1 & tb_sum_en $end
$var reg 1 ' tb_reset $end
$scope module uut $end
$var reg 1 ( clk_port $end
$var reg 1 ) load_port $end
$var reg 1 * clear_port $end
$var reg 1 + term1_en_port $end
$var reg 1 , term2_en_port $end
$var reg 1 - sum_en_port $end
$var reg 1 . reset_port $end
$comment curr_state is not handled $end
$comment next_state is not handled $end
$upscope $end
$upscope $end
$enddefinitions $end
#0
0!
0"
0#
0$
0%
0&
1'
0(
0)
0*
0+
0,
0-
1.
#5000000
1!
1(
#10000000
0!
0(
#15000000
1!
1(
#20000000
0!
0(
#25000000
1!
1(
#30000000
0!
0(
#35000000
1!
1(
#40000000
0!
0(
#45000000
1!
1(
#50000000
0!
0(
#55000000
1!
1(
#60000000
0!
0(
#65000000
1!
1(
#70000000
0!
1#
0(
1*
#75000000
1!
1(
#80000000
0!
0#
0(
0*
#85000000
1!
1(
#90000000
0!
0(
#95000000
1!
1(
#100000000
0!
0(
#105000000
1!
1(
#110000000
0!
0(
#115000000
1!
1(
#120000000
0!
0(
#125000000
1!
1(
#130000000
0!
0(
#135000000
1!
1(
#140000000
0!
1"
0(
1)
#145000000
1!
1$
0'
1(
1+
0.
#150000000
0!
0"
0(
0)
#155000000
1!
0$
1(
0+
#160000000
0!
0(
#165000000
1!
1(
#170000000
0!
0(
#175000000
1!
1(
#180000000
0!
0(
#185000000
1!
1(
#190000000
0!
0(
#195000000
1!
1(
#200000000
0!
0(
#205000000
1!
1(
#210000000
0!
1"
0(
1)
#215000000
1!
1%
1(
1,
#220000000
0!
0"
0(
0)
#225000000
1!
0%
1(
0,
#230000000
0!
0(
#235000000
1!
1(
#240000000
0!
0(
#245000000
1!
1(
#250000000
0!
0(
#255000000
1!
1(
#260000000
0!
0(
#265000000
1!
1(
#270000000
0!
0(
#275000000
1!
1(
#280000000
0!
1"
0(
1)
#285000000
1!
1&
1(
1-
#290000000
0!
0"
0(
0)
#295000000
1!
1(
#300000000
0!
0(
#305000000
1!
1(
#310000000
0!
0(
#315000000
1!
1(
#320000000
0!
0(
#325000000
1!
1(
#330000000
0!
0(
#335000000
1!
1(
#340000000
0!
0(
#345000000
1!
1(
#350000000
0!
1#
0&
1'
0(
1*
0-
1.
#355000000
1!
1(
#360000000
0!
0#
0(
0*
#365000000
1!
1(
#370000000
0!
0(
#375000000
1!
1(
#380000000
0!
0(
#385000000
1!
1(
#390000000
0!
0(
#395000000
1!
1(
#400000000
0!
0(
#405000000
1!
1(
#410000000
0!
0(
#415000000
1!
1(
#420000000
0!
1"
0(
1)
#425000000
1!
1$
0'
1(
1+
0.
#430000000
0!
0"
0(
0)
#435000000
1!
0$
1(
0+
#440000000
0!
0(
#445000000
1!
1(
#450000000
0!
0(
#455000000
1!
1(
#460000000
0!
1#
1'
0(
1*
1.
#465000000
1!
1(
#470000000
0!
0#
0(
0*
