hw5/SCI_tx.vhd
library ieee;
use ieee.std_logic_1164.all;
use ieee.numeric_std.all;

entity SCI_Tx IS
    port (
        clk         : in  STD_LOGIC;
        Data_in     : in  STD_LOGIC_VECTOR(7 downto 0);
        Load        : in  STD_LOGIC;
        Tx          : out STD_LOGIC;
        Tx_done     : out STD_Logic
    );
end entity SCI_Tx;

architecture behavior of SCI_Tx is

    constant CLOCK_FREQUENCY_CONST : integer := 10_000_000; -- 10 MHz
    constant BAUD_RATE_CONST       : integer := 256_000;    -- 256 kHz
    constant BAUD_PERIOD_CLOCKS    : integer := CLOCK_FREQUENCY_CONST / BAUD_RATE_CONST; -- 39

    -- Baud rate generator counter. Initialized to 0.
    signal baud_rate_counter_r : integer range 0 to BAUD_PERIOD_CLOCKS - 1 := 0;
    signal baud_tick_s         : std_logic; -- Will be pulsed high

    -- Shift register: Initialized to '1' for idle Tx line.
    signal tx_sreg_r           : std_logic_vector(9 downto 0) := (others => '1');

    -- Bit counter for 10 bits Initialized to 0.
    signal bit_count_r         : integer range 0 to 9 := 0;

    -- FSM states and state register. Initialized to S_IDLE.
    type state_t is (S_IDLE, S_TX_BITS, S_TX_DONE_PULSE);
    signal current_state_r     : state_t := S_IDLE;
    signal next_state_s        : state_t;

begin

    -- Baud Rate Tick Generator: Generates a 1-clock pulse (baud_tick_s) at the baud rate.
    process(clk)
    begin
        if rising_edge(clk) then
            baud_tick_s <= '0'; -- Default to low, pulse high for one system clock cycle
            if current_state_r = S_TX_BITS then -- Only count when actively transmitting bits
                if baud_rate_counter_r < BAUD_PERIOD_CLOCKS - 1 then
                    baud_rate_counter_r <= baud_rate_counter_r + 1;
                else
                    baud_rate_counter_r <= 0;
                    baud_tick_s         <= '1';
                end if;
            else
                -- When not in S_TX_BITS (i.e., S_IDLE or S_TX_DONE_PULSE), reset the baud counter.
                baud_rate_counter_r <= 0; 
            end if;
        end if;
    end process;

    -- FSM State Register: Updates current_state_r on clock edge.
    process(clk)
    begin
        if rising_edge(clk) then
            current_state_r <= next_state_s;
        end if;
    end process;

    -- FSM Combinatorial Logic: Determine next_state_s and control output
    process(current_state_r, Load, baud_tick_s, bit_count_r, tx_sreg_r)
    begin
        next_state_s   <= current_state_r;  -- By default, stay in current state
        Tx             <= '1';              -- Default Tx line to idle (high)
        Tx_done        <= '0';              -- Default Tx_done to low

        case current_state_r is
            when S_IDLE =>
                Tx <= '1'; -- Ensure Tx line is idle
                if Load = '1' then
                    -- When Load is asserted, prepare to start transmission.
                    next_state_s <= S_TX_BITS;
                end if;

            when S_TX_BITS =>
                Tx <= tx_sreg_r(0); -- Output the LSB of the shift register (current bit)
                if baud_tick_s = '1' then
                    if bit_count_r < 9 then
                        next_state_s <= S_TX_BITS; -- Remain in S_TX_BITS
                    else -- bit_count_r is 9,  the 10th bit period has just ended.
                        next_state_s <= S_TX_DONE_PULSE; -- All bits sent, move to signal completion.
                    end if;
                end if;

            when S_TX_DONE_PULSE =>
                Tx      <= '1'; -- Tx line return to idle
                Tx_done <= '1'; -- Tx_done high for this one clock cycle.
                next_state_s <= S_IDLE; -- Transition back to S_IDLE.
        end case;
    end process;

    -- Synchronous Datapath Logic: Update (tx_sreg_r, bit_count_r) on clock edge.
    process(clk)
    begin
        if rising_edge(clk) then
            if current_state_r = S_IDLE and next_state_s = S_TX_BITS then 
                -- Load the shift register
                tx_sreg_r   <= '1' & Data_in & '0'; 
                bit_count_r <= 0;  -- Reset bit counter for the new transmission
            
            elsif current_state_r = S_TX_BITS and baud_tick_s = '1' then
                tx_sreg_r   <= '0' & tx_sreg_r(9 downto 1); -- Shift out the LSB
                if bit_count_r < 9 then
                    bit_count_r <= bit_count_r + 1;
                end if;
            end if;
        end if;
    end process;

end architecture behavior;

hw5/SCI_tx_tb.vhd
LIBRARY ieee;
USE ieee.std_logic_1164.ALL;
USE ieee.numeric_std.ALL;

ENTITY SCI_Tx_tb IS
END SCI_Tx_tb;

ARCHITECTURE testbench OF SCI_Tx_tb IS 

    -- Component Declaration for the Unit Under Test (UUT)
    COMPONENT SCI_Tx
    PORT(
        clk      : IN  std_logic;
        Data_in  : IN  std_logic_vector(7 downto 0);
        Load     : IN  std_logic;
        Tx       : OUT std_logic;
        Tx_done  : OUT std_logic
    );
    END COMPONENT;
    
    --Inputs
    signal clk     : std_logic := '0';
    signal Data_in : std_logic_vector(7 downto 0) := (others => '0');
    signal Load    : std_logic := '0';

    --Outputs
    signal Tx      : std_logic;
    signal Tx_done : std_logic;

    -- Clock period definitions
    constant clk_period : time := 100 ns; -- 10 MHz

BEGIN

    -- Instantiate the Unit Under Test (UUT)
    uut: SCI_Tx PORT MAP (
        clk     => clk,
        Data_in => Data_in,
        Load    => Load,
        Tx      => Tx,
        Tx_done => Tx_done
    );

    -- Clock process definitions
    clk_process :process
    begin
        clk <= '0';
        wait for clk_period/2;
        clk <= '1';
        wait for clk_period/2;
    end process;

    -- Stimulus process
    stim_proc: process
    begin        
        -- Initialize Inputs
        Load <= '0';
        Data_in <= (others => '0');
        
        wait for clk_period * 10;
        
        -- Scenario 1: Load data "10101010"
        Data_in <= "10101010";
        Load <= '1';  -- Load the data
        wait for clk_period;
        Load <= '0';

        -- Wait for transmission to complete
        wait for clk_period * 500;
        
        -- Scenario 2: Load data "11001100"
        Data_in <= "11001100";
        Load <= '1';  -- Load the data
        wait for clk_period;
        Load <= '0';

        -- Wait for transmission to complete
        wait for clk_period * 500;

        -- Add more scenarios as necessary

        -- Complete the simulation
        wait;
    end process;

END testbench;

hw5/SCI_tx_tb.vcd
$date
  Fri May 16 16:25:57 2025
$end
$version
  GHDL v0
$end
$timescale
  1 fs
$end
$scope module standard $end
$upscope $end
$scope module textio $end
$upscope $end
$scope module std_logic_1164 $end
$upscope $end
$scope module numeric_std $end
$upscope $end
$scope module sci_tx_tb $end
$var reg 1 ! clk $end
$var reg 8 " data_in[7:0] $end
$var reg 1 # load $end
$var reg 1 $ tx $end
$var reg 1 % tx_done $end
$scope module uut $end
$var reg 1 & clk $end
$var reg 8 ' data_in[7:0] $end
$var reg 1 ( load $end
$var reg 1 ) tx $end
$var reg 1 * tx_done $end
$var integer 32 + baud_rate_counter_r $end
$var reg 1 , baud_tick_s $end
$var reg 10 - tx_sreg_r[9:0] $end
$var integer 32 . bit_count_r $end
$comment current_state_r is not handled $end
$comment next_state_s is not handled $end
$upscope $end
$upscope $end
$enddefinitions $end
#0
0!
b00000000 "
0#
1$
0%
0&
b00000000 '
0(
1)
0*
b0 +
U,
b1111111111 -
b0 .
#50000000
1!
1&
0,
#100000000
0!
0&
#150000000
1!
1&
#200000000
0!
0&
#250000000
1!
1&
#300000000
0!
0&
#350000000
1!
1&
#400000000
0!
0&
#450000000
1!
1&
#500000000
0!
0&
#550000000
1!
1&
#600000000
0!
0&
#650000000
1!
1&
#700000000
0!
0&
#750000000
1!
1&
#800000000
0!
0&
#850000000
1!
1&
#900000000
0!
0&
#950000000
1!
1&
#1000000000
0!
b10101010 "
1#
0&
b10101010 '
1(
#1050000000
1!
0$
1&
0)
b1101010100 -
#1100000000
0!
0#
0&
0(
0)
#1150000000
1!
1&
b1 +
#1200000000
0!
0&
#1250000000
1!
1&
b10 +
#1300000000
0!
0&
#1350000000
1!
1&
b11 +
#1400000000
0!
0&
#1450000000
1!
1&
b100 +
#1500000000
0!
0&
#1550000000
1!
1&
b101 +
#1600000000
0!
0&
#1650000000
1!
1&
b110 +
#1700000000
0!
0&
#1750000000
1!
1&
b111 +
#1800000000
0!
0&
#1850000000
1!
1&
b1000 +
#1900000000
0!
0&
#1950000000
1!
1&
b1001 +
#2000000000
0!
0&
#2050000000
1!
1&
b1010 +
#2100000000
0!
0&
#2150000000
1!
1&
b1011 +
#2200000000
0!
0&
#2250000000
1!
1&
b1100 +
#2300000000
0!
0&
#2350000000
1!
1&
b1101 +
#2400000000
0!
0&
#2450000000
1!
1&
b1110 +
#2500000000
0!
0&
#2550000000
1!
1&
b1111 +
#2600000000
0!
0&
#2650000000
1!
1&
b10000 +
#2700000000
0!
0&
#2750000000
1!
1&
b10001 +
#2800000000
0!
0&
#2850000000
1!
1&
b10010 +
#2900000000
0!
0&
#2950000000
1!
1&
b10011 +
#3000000000
0!
0&
#3050000000
1!
1&
b10100 +
#3100000000
0!
0&
#3150000000
1!
1&
b10101 +
#3200000000
0!
0&
#3250000000
1!
1&
b10110 +
#3300000000
0!
0&
#3350000000
1!
1&
b10111 +
#3400000000
0!
0&
#3450000000
1!
1&
b11000 +
#3500000000
0!
0&
#3550000000
1!
1&
b11001 +
#3600000000
0!
0&
#3650000000
1!
1&
b11010 +
#3700000000
0!
0&
#3750000000
1!
1&
b11011 +
#3800000000
0!
0&
#3850000000
1!
1&
b11100 +
#3900000000
0!
0&
#3950000000
1!
1&
b11101 +
#4000000000
0!
0&
#4050000000
1!
1&
b11110 +
#4100000000
0!
0&
#4150000000
1!
1&
b11111 +
#4200000000
0!
0&
#4250000000
1!
1&
b100000 +
#4300000000
0!
0&
#4350000000
1!
1&
b100001 +
#4400000000
0!
0&
#4450000000
1!
1&
b100010 +
#4500000000
0!
0&
#4550000000
1!
1&
b100011 +
#4600000000
0!
0&
#4650000000
1!
1&
b100100 +
#4700000000
0!
0&
#4750000000
1!
1&
b100101 +
#4800000000
0!
0&
#4850000000
1!
1&
b100110 +
#4900000000
0!
0&
#4950000000
1!
1&
0)
b0 +
1,
#5000000000
0!
0&
#5050000000
1!
1&
0)
b1 +
0,
b0110101010 -
b1 .
#5100000000
0!
0&
#5150000000
1!
1&
b10 +
#5200000000
0!
0&
#5250000000
1!
1&
b11 +
#5300000000
0!
0&
#5350000000
1!
1&
b100 +
#5400000000
0!
0&
#5450000000
1!
1&
b101 +
#5500000000
0!
0&
#5550000000
1!
1&
b110 +
#5600000000
0!
0&
#5650000000
1!
1&
b111 +
#5700000000
0!
0&
#5750000000
1!
1&
b1000 +
#5800000000
0!
0&
#5850000000
1!
1&
b1001 +
#5900000000
0!
0&
#5950000000
1!
1&
b1010 +
#6000000000
0!
0&
#6050000000
1!
1&
b1011 +
#6100000000
0!
0&
#6150000000
1!
1&
b1100 +
#6200000000
0!
0&
#6250000000
1!
1&
b1101 +
#6300000000
0!
0&
#6350000000
1!
1&
b1110 +
#6400000000
0!
0&
#6450000000
1!
1&
b1111 +
#6500000000
0!
0&
#6550000000
1!
1&
b10000 +
#6600000000
0!
0&
#6650000000
1!
1&
b10001 +
#6700000000
0!
0&
#6750000000
1!
1&
b10010 +
#6800000000
0!
0&
#6850000000
1!
1&
b10011 +
#6900000000
0!
0&
#6950000000
1!
1&
b10100 +
#7000000000
0!
0&
#7050000000
1!
1&
b10101 +
#7100000000
0!
0&
#7150000000
1!
1&
b10110 +
#7200000000
0!
0&
#7250000000
1!
1&
b10111 +
#7300000000
0!
0&
#7350000000
1!
1&
b11000 +
#7400000000
0!
0&
#7450000000
1!
1&
b11001 +
#7500000000
0!
0&
#7550000000
1!
1&
b11010 +
#7600000000
0!
0&
#7650000000
1!
1&
b11011 +
#7700000000
0!
0&
#7750000000
1!
1&
b11100 +
#7800000000
0!
0&
#7850000000
1!
1&
b11101 +
#7900000000
0!
0&
#7950000000
1!
1&
b11110 +
#8000000000
0!
0&
#8050000000
1!
1&
b11111 +
#8100000000
0!
0&
#8150000000
1!
1&
b100000 +
#8200000000
0!
0&
#8250000000
1!
1&
b100001 +
#8300000000
0!
0&
#8350000000
1!
1&
b100010 +
#8400000000
0!
0&
#8450000000
1!
1&
b100011 +
#8500000000
0!
0&
#8550000000
1!
1&
b100100 +
#8600000000
0!
0&
#8650000000
1!
1&
b100101 +
#8700000000
0!
0&
#8750000000
1!
1&
b100110 +
#8800000000
0!
0&
#8850000000
1!
1&
0)
b0 +
1,
#8900000000
0!
0&
#8950000000
1!
1$
1&
1)
b1 +
0,
b0011010101 -
b10 .
#9000000000
0!
0&
#9050000000
1!
1&
b10 +
#9100000000
0!
0&
#9150000000
1!
1&
b11 +
#9200000000
0!
0&
#9250000000
1!
1&
b100 +
#9300000000
0!
0&
#9350000000
1!
1&
b101 +
#9400000000
0!
0&
#9450000000
1!
1&
b110 +
#9500000000
0!
0&
#9550000000
1!
1&
b111 +
#9600000000
0!
0&
#9650000000
1!
1&
b1000 +
#9700000000
0!
0&
#9750000000
1!
1&
b1001 +
#9800000000
0!
0&
#9850000000
1!
1&
b1010 +
#9900000000
0!
0&
#9950000000
1!
1&
b1011 +
#10000000000
0!
0&
#10050000000
1!
1&
b1100 +
#10100000000
0!
0&
#10150000000
1!
1&
b1101 +
#10200000000
0!
0&
#10250000000
1!
1&
b1110 +
#10300000000
0!
0&
#10350000000
1!
1&
b1111 +
#10400000000
0!
0&
#10450000000
1!
1&
b10000 +
#10500000000
0!
0&
#10550000000
1!
1&
b10001 +
#10600000000
0!
0&
#10650000000
1!
1&
b10010 +
#10700000000
0!
0&
#10750000000
1!
1&
b10011 +
#10800000000
0!
0&
#10850000000
1!
1&
b10100 +
#10900000000
0!
0&
#10950000000
1!
1&
b10101 +
#11000000000
0!
0&
#11050000000
1!
1&
b10110 +
#11100000000
0!
0&
#11150000000
1!
1&
b10111 +
#11200000000
0!
0&
#11250000000
1!
1&
b11000 +
#11300000000
0!
0&
#11350000000
1!
1&
b11001 +
#11400000000
0!
0&
#11450000000
1!
1&
b11010 +
#11500000000
0!
0&
#11550000000
1!
1&
b11011 +
#11600000000
0!
0&
#11650000000
1!
1&
b11100 +
#11700000000
0!
0&
#11750000000
1!
1&
b11101 +
#11800000000
0!
0&
#11850000000
1!
1&
b11110 +
#11900000000
0!
0&
#11950000000
1!
1&
b11111 +
#12000000000
0!
0&
#12050000000
1!
1&
b100000 +
#12100000000
0!
0&
#12150000000
1!
1&
b100001 +
#12200000000
0!
0&
#12250000000
1!
1&
b100010 +
#12300000000
0!
0&
#12350000000
1!
1&
b100011 +
#12400000000
0!
0&
#12450000000
1!
1&
b100100 +
#12500000000
0!
0&
#12550000000
1!
1&
b100101 +
#12600000000
0!
0&
#12650000000
1!
1&
b100110 +
#12700000000
0!
0&
#12750000000
1!
1&
b0 +
1,
#12800000000
0!
0&
#12850000000
1!
0$
1&
0)
b1 +
0,
b0001101010 -
b11 .
#12900000000
0!
0&
#12950000000
1!
1&
b10 +
#13000000000
0!
0&
#13050000000
1!
1&
b11 +
#13100000000
0!
0&
#13150000000
1!
1&
b100 +
#13200000000
0!
0&
#13250000000
1!
1&
b101 +
#13300000000
0!
0&
#13350000000
1!
1&
b110 +
#13400000000
0!
0&
#13450000000
1!
1&
b111 +
#13500000000
0!
0&
#13550000000
1!
1&
b1000 +
#13600000000
0!
0&
#13650000000
1!
1&
b1001 +
#13700000000
0!
0&
#13750000000
1!
1&
b1010 +
#13800000000
0!
0&
#13850000000
1!
1&
b1011 +
#13900000000
0!
0&
#13950000000
1!
1&
b1100 +
#14000000000
0!
0&
#14050000000
1!
1&
b1101 +
#14100000000
0!
0&
#14150000000
1!
1&
b1110 +
#14200000000
0!
0&
#14250000000
1!
1&
b1111 +
#14300000000
0!
0&
#14350000000
1!
1&
b10000 +
#14400000000
0!
0&
#14450000000
1!
1&
b10001 +
#14500000000
0!
0&
#14550000000
1!
1&
b10010 +
#14600000000
0!
0&
#14650000000
1!
1&
b10011 +
#14700000000
0!
0&
#14750000000
1!
1&
b10100 +
#14800000000
0!
0&
#14850000000
1!
1&
b10101 +
#14900000000
0!
0&
#14950000000
1!
1&
b10110 +
#15000000000
0!
0&
#15050000000
1!
1&
b10111 +
#15100000000
0!
0&
#15150000000
1!
1&
b11000 +
#15200000000
0!
0&
#15250000000
1!
1&
b11001 +
#15300000000
0!
0&
#15350000000
1!
1&
b11010 +
#15400000000
0!
0&
#15450000000
1!
1&
b11011 +
#15500000000
0!
0&
#15550000000
1!
1&
b11100 +
#15600000000
0!
0&
#15650000000
1!
1&
b11101 +
#15700000000
0!
0&
#15750000000
1!
1&
b11110 +
#15800000000
0!
0&
#15850000000
1!
1&
b11111 +
#15900000000
0!
0&
#15950000000
1!
1&
b100000 +
#16000000000
0!
0&
#16050000000
1!
1&
b100001 +
#16100000000
0!
0&
#16150000000
1!
1&
b100010 +
#16200000000
0!
0&
#16250000000
1!
1&
b100011 +
#16300000000
0!
0&
#16350000000
1!
1&
b100100 +
#16400000000
0!
0&
#16450000000
1!
1&
b100101 +
#16500000000
0!
0&
#16550000000
1!
1&
b100110 +
#16600000000
0!
0&
#16650000000
1!
1&
0)
b0 +
1,
#16700000000
0!
0&
#16750000000
1!
1$
1&
1)
b1 +
0,
b0000110101 -
b100 .
#16800000000
0!
0&
#16850000000
1!
1&
b10 +
#16900000000
0!
0&
#16950000000
1!
1&
b11 +
#17000000000
0!
0&
#17050000000
1!
1&
b100 +
#17100000000
0!
0&
#17150000000
1!
1&
b101 +
#17200000000
0!
0&
#17250000000
1!
1&
b110 +
#17300000000
0!
0&
#17350000000
1!
1&
b111 +
#17400000000
0!
0&
#17450000000
1!
1&
b1000 +
#17500000000
0!
0&
#17550000000
1!
1&
b1001 +
#17600000000
0!
0&
#17650000000
1!
1&
b1010 +
#17700000000
0!
0&
#17750000000
1!
1&
b1011 +
#17800000000
0!
0&
#17850000000
1!
1&
b1100 +
#17900000000
0!
0&
#17950000000
1!
1&
b1101 +
#18000000000
0!
0&
#18050000000
1!
1&
b1110 +
#18100000000
0!
0&
#18150000000
1!
1&
b1111 +
#18200000000
0!
0&
#18250000000
1!
1&
b10000 +
#18300000000
0!
0&
#18350000000
1!
1&
b10001 +
#18400000000
0!
0&
#18450000000
1!
1&
b10010 +
#18500000000
0!
0&
#18550000000
1!
1&
b10011 +
#18600000000
0!
0&
#18650000000
1!
1&
b10100 +
#18700000000
0!
0&
#18750000000
1!
1&
b10101 +
#18800000000
0!
0&
#18850000000
1!
1&
b10110 +
#18900000000
0!
0&
#18950000000
1!
1&
b10111 +
#19000000000
0!
0&
#19050000000
1!
1&
b11000 +
#19100000000
0!
0&
#19150000000
1!
1&
b11001 +
#19200000000
0!
0&
#19250000000
1!
1&
b11010 +
#19300000000
0!
0&
#19350000000
1!
1&
b11011 +
#19400000000
0!
0&
#19450000000
1!
1&
b11100 +
#19500000000
0!
0&
#19550000000
1!
1&
b11101 +
#19600000000
0!
0&
#19650000000
1!
1&
b11110 +
#19700000000
0!
0&
#19750000000
1!
1&
b11111 +
#19800000000
0!
0&
#19850000000
1!
1&
b100000 +
#19900000000
0!
0&
#19950000000
1!
1&
b100001 +
#20000000000
0!
0&
#20050000000
1!
1&
b100010 +
#20100000000
0!
0&
#20150000000
1!
1&
b100011 +
#20200000000
0!
0&
#20250000000
1!
1&
b100100 +
#20300000000
0!
0&
#20350000000
1!
1&
b100101 +
#20400000000
0!
0&
#20450000000
1!
1&
b100110 +
#20500000000
0!
0&
#20550000000
1!
1&
b0 +
1,
#20600000000
0!
0&
#20650000000
1!
0$
1&
0)
b1 +
0,
b0000011010 -
b101 .
#20700000000
0!
0&
#20750000000
1!
1&
b10 +
#20800000000
0!
0&
#20850000000
1!
1&
b11 +
#20900000000
0!
0&
#20950000000
1!
1&
b100 +
#21000000000
0!
0&
#21050000000
1!
1&
b101 +
#21100000000
0!
0&
#21150000000
1!
1&
b110 +
#21200000000
0!
0&
#21250000000
1!
1&
b111 +
#21300000000
0!
0&
#21350000000
1!
1&
b1000 +
#21400000000
0!
0&
#21450000000
1!
1&
b1001 +
#21500000000
0!
0&
#21550000000
1!
1&
b1010 +
#21600000000
0!
0&
#21650000000
1!
1&
b1011 +
#21700000000
0!
0&
#21750000000
1!
1&
b1100 +
#21800000000
0!
0&
#21850000000
1!
1&
b1101 +
#21900000000
0!
0&
#21950000000
1!
1&
b1110 +
#22000000000
0!
0&
#22050000000
1!
1&
b1111 +
#22100000000
0!
0&
#22150000000
1!
1&
b10000 +
#22200000000
0!
0&
#22250000000
1!
1&
b10001 +
#22300000000
0!
0&
#22350000000
1!
1&
b10010 +
#22400000000
0!
0&
#22450000000
1!
1&
b10011 +
#22500000000
0!
0&
#22550000000
1!
1&
b10100 +
#22600000000
0!
0&
#22650000000
1!
1&
b10101 +
#22700000000
0!
0&
#22750000000
1!
1&
b10110 +
#22800000000
0!
0&
#22850000000
1!
1&
b10111 +
#22900000000
0!
0&
#22950000000
1!
1&
b11000 +
#23000000000
0!
0&
#23050000000
1!
1&
b11001 +
#23100000000
0!
0&
#23150000000
1!
1&
b11010 +
#23200000000
0!
0&
#23250000000
1!
1&
b11011 +
#23300000000
0!
0&
#23350000000
1!
1&
b11100 +
#23400000000
0!
0&
#23450000000
1!
1&
b11101 +
#23500000000
0!
0&
#23550000000
1!
1&
b11110 +
#23600000000
0!
0&
#23650000000
1!
1&
b11111 +
#23700000000
0!
0&
#23750000000
1!
1&
b100000 +
#23800000000
0!
0&
#23850000000
1!
1&
b100001 +
#23900000000
0!
0&
#23950000000
1!
1&
b100010 +
#24000000000
0!
0&
#24050000000
1!
1&
b100011 +
#24100000000
0!
0&
#24150000000
1!
1&
b100100 +
#24200000000
0!
0&
#24250000000
1!
1&
b100101 +
#24300000000
0!
0&
#24350000000
1!
1&
b100110 +
#24400000000
0!
0&
#24450000000
1!
1&
0)
b0 +
1,
#24500000000
0!
0&
#24550000000
1!
1$
1&
1)
b1 +
0,
b0000001101 -
b110 .
#24600000000
0!
0&
#24650000000
1!
1&
b10 +
#24700000000
0!
0&
#24750000000
1!
1&
b11 +
#24800000000
0!
0&
#24850000000
1!
1&
b100 +
#24900000000
0!
0&
#24950000000
1!
1&
b101 +
#25000000000
0!
0&
#25050000000
1!
1&
b110 +
#25100000000
0!
0&
#25150000000
1!
1&
b111 +
#25200000000
0!
0&
#25250000000
1!
1&
b1000 +
#25300000000
0!
0&
#25350000000
1!
1&
b1001 +
#25400000000
0!
0&
#25450000000
1!
1&
b1010 +
#25500000000
0!
0&
#25550000000
1!
1&
b1011 +
#25600000000
0!
0&
#25650000000
1!
1&
b1100 +
#25700000000
0!
0&
#25750000000
1!
1&
b1101 +
#25800000000
0!
0&
#25850000000
1!
1&
b1110 +
#25900000000
0!
0&
#25950000000
1!
1&
b1111 +
#26000000000
0!
0&
#26050000000
1!
1&
b10000 +
#26100000000
0!
0&
#26150000000
1!
1&
b10001 +
#26200000000
0!
0&
#26250000000
1!
1&
b10010 +
#26300000000
0!
0&
#26350000000
1!
1&
b10011 +
#26400000000
0!
0&
#26450000000
1!
1&
b10100 +
#26500000000
0!
0&
#26550000000
1!
1&
b10101 +
#26600000000
0!
0&
#26650000000
1!
1&
b10110 +
#26700000000
0!
0&
#26750000000
1!
1&
b10111 +
#26800000000
0!
0&
#26850000000
1!
1&
b11000 +
#26900000000
0!
0&
#26950000000
1!
1&
b11001 +
#27000000000
0!
0&
#27050000000
1!
1&
b11010 +
#27100000000
0!
0&
#27150000000
1!
1&
b11011 +
#27200000000
0!
0&
#27250000000
1!
1&
b11100 +
#27300000000
0!
0&
#27350000000
1!
1&
b11101 +
#27400000000
0!
0&
#27450000000
1!
1&
b11110 +
#27500000000
0!
0&
#27550000000
1!
1&
b11111 +
#27600000000
0!
0&
#27650000000
1!
1&
b100000 +
#27700000000
0!
0&
#27750000000
1!
1&
b100001 +
#27800000000
0!
0&
#27850000000
1!
1&
b100010 +
#27900000000
0!
0&
#27950000000
1!
1&
b100011 +
#28000000000
0!
0&
#28050000000
1!
1&
b100100 +
#28100000000
0!
0&
#28150000000
1!
1&
b100101 +
#28200000000
0!
0&
#28250000000
1!
1&
b100110 +
#28300000000
0!
0&
#28350000000
1!
1&
b0 +
1,
#28400000000
0!
0&
#28450000000
1!
0$
1&
0)
b1 +
0,
b0000000110 -
b111 .
#28500000000
0!
0&
#28550000000
1!
1&
b10 +
#28600000000
0!
0&
#28650000000
1!
1&
b11 +
#28700000000
0!
0&
#28750000000
1!
1&
b100 +
#28800000000
0!
0&
#28850000000
1!
1&
b101 +
#28900000000
0!
0&
#28950000000
1!
1&
b110 +
#29000000000
0!
0&
#29050000000
1!
1&
b111 +
#29100000000
0!
0&
#29150000000
1!
1&
b1000 +
#29200000000
0!
0&
#29250000000
1!
1&
b1001 +
#29300000000
0!
0&
#29350000000
1!
1&
b1010 +
#29400000000
0!
0&
#29450000000
1!
1&
b1011 +
#29500000000
0!
0&
#29550000000
1!
1&
b1100 +
#29600000000
0!
0&
#29650000000
1!
1&
b1101 +
#29700000000
0!
0&
#29750000000
1!
1&
b1110 +
#29800000000
0!
0&
#29850000000
1!
1&
b1111 +
#29900000000
0!
0&
#29950000000
1!
1&
b10000 +
#30000000000
0!
0&
#30050000000
1!
1&
b10001 +
#30100000000
0!
0&
#30150000000
1!
1&
b10010 +
#30200000000
0!
0&
#30250000000
1!
1&
b10011 +
#30300000000
0!
0&
#30350000000
1!
1&
b10100 +
#30400000000
0!
0&
#30450000000
1!
1&
b10101 +
#30500000000
0!
0&
#30550000000
1!
1&
b10110 +
#30600000000
0!
0&
#30650000000
1!
1&
b10111 +
#30700000000
0!
0&
#30750000000
1!
1&
b11000 +
#30800000000
0!
0&
#30850000000
1!
1&
b11001 +
#30900000000
0!
0&
#30950000000
1!
1&
b11010 +
#31000000000
0!
0&
#31050000000
1!
1&
b11011 +
#31100000000
0!
0&
#31150000000
1!
1&
b11100 +
#31200000000
0!
0&
#31250000000
1!
1&
b11101 +
#31300000000
0!
0&
#31350000000
1!
1&
b11110 +
#31400000000
0!
0&
#31450000000
1!
1&
b11111 +
#31500000000
0!
0&
#31550000000
1!
1&
b100000 +
#31600000000
0!
0&
#31650000000
1!
1&
b100001 +
#31700000000
0!
0&
#31750000000
1!
1&
b100010 +
#31800000000
0!
0&
#31850000000
1!
1&
b100011 +
#31900000000
0!
0&
#31950000000
1!
1&
b100100 +
#32000000000
0!
0&
#32050000000
1!
1&
b100101 +
#32100000000
0!
0&
#32150000000
1!
1&
b100110 +
#32200000000
0!
0&
#32250000000
1!
1&
0)
b0 +
1,
#32300000000
0!
0&
#32350000000
1!
1$
1&
1)
b1 +
0,
b0000000011 -
b1000 .
#32400000000
0!
0&
#32450000000
1!
1&
b10 +
#32500000000
0!
0&
#32550000000
1!
1&
b11 +
#32600000000
0!
0&
#32650000000
1!
1&
b100 +
#32700000000
0!
0&
#32750000000
1!
1&
b101 +
#32800000000
0!
0&
#32850000000
1!
1&
b110 +
#32900000000
0!
0&
#32950000000
1!
1&
b111 +
#33000000000
0!
0&
#33050000000
1!
1&
b1000 +
#33100000000
0!
0&
#33150000000
1!
1&
b1001 +
#33200000000
0!
0&
#33250000000
1!
1&
b1010 +
#33300000000
0!
0&
#33350000000
1!
1&
b1011 +
#33400000000
0!
0&
#33450000000
1!
1&
b1100 +
#33500000000
0!
0&
#33550000000
1!
1&
b1101 +
#33600000000
0!
0&
#33650000000
1!
1&
b1110 +
#33700000000
0!
0&
#33750000000
1!
1&
b1111 +
#33800000000
0!
0&
#33850000000
1!
1&
b10000 +
#33900000000
0!
0&
#33950000000
1!
1&
b10001 +
#34000000000
0!
0&
#34050000000
1!
1&
b10010 +
#34100000000
0!
0&
#34150000000
1!
1&
b10011 +
#34200000000
0!
0&
#34250000000
1!
1&
b10100 +
#34300000000
0!
0&
#34350000000
1!
1&
b10101 +
#34400000000
0!
0&
#34450000000
1!
1&
b10110 +
#34500000000
0!
0&
#34550000000
1!
1&
b10111 +
#34600000000
0!
0&
#34650000000
1!
1&
b11000 +
#34700000000
0!
0&
#34750000000
1!
1&
b11001 +
#34800000000
0!
0&
#34850000000
1!
1&
b11010 +
#34900000000
0!
0&
#34950000000
1!
1&
b11011 +
#35000000000
0!
0&
#35050000000
1!
1&
b11100 +
#35100000000
0!
0&
#35150000000
1!
1&
b11101 +
#35200000000
0!
0&
#35250000000
1!
1&
b11110 +
#35300000000
0!
0&
#35350000000
1!
1&
b11111 +
#35400000000
0!
0&
#35450000000
1!
1&
b100000 +
#35500000000
0!
0&
#35550000000
1!
1&
b100001 +
#35600000000
0!
0&
#35650000000
1!
1&
b100010 +
#35700000000
0!
0&
#35750000000
1!
1&
b100011 +
#35800000000
0!
0&
#35850000000
1!
1&
b100100 +
#35900000000
0!
0&
#35950000000
1!
1&
b100101 +
#36000000000
0!
0&
#36050000000
1!
1&
b100110 +
#36100000000
0!
0&
#36150000000
1!
1&
b0 +
1,
#36200000000
0!
0&
#36250000000
1!
1&
b1 +
0,
b0000000001 -
b1001 .
#36300000000
0!
0&
#36350000000
1!
1&
b10 +
#36400000000
0!
0&
#36450000000
1!
1&
b11 +
#36500000000
0!
0&
#36550000000
1!
1&
b100 +
#36600000000
0!
0&
#36650000000
1!
1&
b101 +
#36700000000
0!
0&
#36750000000
1!
1&
b110 +
#36800000000
0!
0&
#36850000000
1!
1&
b111 +
#36900000000
0!
0&
#36950000000
1!
1&
b1000 +
#37000000000
0!
0&
#37050000000
1!
1&
b1001 +
#37100000000
0!
0&
#37150000000
1!
1&
b1010 +
#37200000000
0!
0&
#37250000000
1!
1&
b1011 +
#37300000000
0!
0&
#37350000000
1!
1&
b1100 +
#37400000000
0!
0&
#37450000000
1!
1&
b1101 +
#37500000000
0!
0&
#37550000000
1!
1&
b1110 +
#37600000000
0!
0&
#37650000000
1!
1&
b1111 +
#37700000000
0!
0&
#37750000000
1!
1&
b10000 +
#37800000000
0!
0&
#37850000000
1!
1&
b10001 +
#37900000000
0!
0&
#37950000000
1!
1&
b10010 +
#38000000000
0!
0&
#38050000000
1!
1&
b10011 +
#38100000000
0!
0&
#38150000000
1!
1&
b10100 +
#38200000000
0!
0&
#38250000000
1!
1&
b10101 +
#38300000000
0!
0&
#38350000000
1!
1&
b10110 +
#38400000000
0!
0&
#38450000000
1!
1&
b10111 +
#38500000000
0!
0&
#38550000000
1!
1&
b11000 +
#38600000000
0!
0&
