hw5/SCI_tx.vhd
library ieee;
use ieee.std_logic_1164.all;
use ieee.numeric_std.all;

entity SCI_Tx IS
    port (
        clk         : in  STD_LOGIC;
        Data_in     : in  STD_LOGIC_VECTOR(7 downto 0);
        Load        : in  STD_LOGIC;
        Tx          : out STD_LOGIC;
        Tx_done     : out STD_Logic
    );
end entity SCI_Tx;

architecture behavior of SCI_Tx is

    constant CLOCK_FREQUENCY_CONST : integer := 10_000_000; -- 10 MHz
    constant BAUD_RATE_CONST       : integer := 256_000;    -- 256 kHz
    constant BAUD_PERIOD_CLOCKS    : integer := CLOCK_FREQUENCY_CONST / BAUD_RATE_CONST; -- 39

    -- Baud rate generator counter. Initialized to 0.
    signal baud_rate_counter_r : integer range 0 to BAUD_PERIOD_CLOCKS - 1 := 0;
    signal baud_tick_s         : std_logic; -- Will be pulsed high

    -- Shift register: Initialized to '1' for idle Tx line.
    signal tx_sreg_r           : std_logic_vector(9 downto 0) := (others => '1');

    -- Bit counter for 10 bits Initialized to 0.
    signal bit_count_r         : integer range 0 to 9 := 0;

    -- FSM states and state register. Initialized to S_IDLE.
    type state_t is (S_IDLE, S_TX_BITS, S_TX_DONE_PULSE);
    signal current_state_r     : state_t := S_IDLE;
    signal next_state_s        : state_t;

begin

    -- Baud Rate Tick Generator: Generates a 1-clock pulse (baud_tick_s) at the baud rate.
    process(clk)
    begin
        if rising_edge(clk) then
            baud_tick_s <= '0'; -- Default to low, pulse high for one system clock cycle
            if current_state_r = S_TX_BITS then -- Only count when actively transmitting bits
                if baud_rate_counter_r < BAUD_PERIOD_CLOCKS - 1 then
                    baud_rate_counter_r <= baud_rate_counter_r + 1;
                else
                    baud_rate_counter_r <= 0;
                    baud_tick_s         <= '1';
                end if;
            else
                -- When not in S_TX_BITS (i.e., S_IDLE or S_TX_DONE_PULSE), reset the baud counter.
                baud_rate_counter_r <= 0; 
            end if;
        end if;
    end process;

    -- FSM State Register: Updates current_state_r on clock edge.
    process(clk)
    begin
        if rising_edge(clk) then
            current_state_r <= next_state_s;
        end if;
    end process;

    -- FSM Combinatorial Logic: Determine next_state_s and control output
    process(current_state_r, Load, baud_tick_s, bit_count_r, tx_sreg_r)
    begin
        next_state_s   <= current_state_r;  -- By default, stay in current state
        Tx             <= '1';              -- Default Tx line to idle (high)
        Tx_done        <= '0';              -- Default Tx_done to low

        case current_state_r is
            when S_IDLE =>
                Tx <= '1'; -- Ensure Tx line is idle
                if Load = '1' then
                    -- When Load is asserted, prepare to start transmission.
                    next_state_s <= S_TX_BITS;
                end if;

            when S_TX_BITS =>
                Tx <= tx_sreg_r(0); -- Output the LSB of the shift register (current bit)
                if baud_tick_s = '1' then
                    if bit_count_r < 9 then
                        next_state_s <= S_TX_BITS; -- Remain in S_TX_BITS
                    else -- bit_count_r is 9,  the 10th bit period has just ended.
                        next_state_s <= S_TX_DONE_PULSE; -- All bits sent, move to signal completion.
                    end if;
                end if;

            when S_TX_DONE_PULSE =>
                Tx      <= '1'; -- Tx line return to idle
                Tx_done <= '1'; -- Tx_done high for this one clock cycle.
                next_state_s <= S_IDLE; -- Transition back to S_IDLE.
        end case;
    end process;

    -- Synchronous Datapath Logic: Update (tx_sreg_r, bit_count_r) on clock edge.
    process(clk)
    begin
        if rising_edge(clk) then
            if current_state_r = S_IDLE and next_state_s = S_TX_BITS then 
                -- Load the shift register
                tx_sreg_r   <= '1' & Data_in & '0'; 
                bit_count_r <= 0;  -- Reset bit counter for the new transmission
            
            elsif current_state_r = S_TX_BITS and baud_tick_s = '1' then
                tx_sreg_r   <= '0' & tx_sreg_r(9 downto 1); -- Shift out the LSB
                if bit_count_r < 9 then
                    bit_count_r <= bit_count_r + 1;
                end if;
            end if;
        end if;
    end process;

end architecture behavior;

hw5/Queue.vhd
-- Code your design here
library IEEE;
use IEEE.std_logic_1164.all;
use IEEE.numeric_std.all;

ENTITY Queue IS
PORT ( 	clk		:	in	STD_LOGIC; --10 MHz clock
		Write	: 	in 	STD_LOGIC;
		read	: 	in 	STD_LOGIC;
        Data_in	:	in	STD_LOGIC_VECTOR(7 downto 0);
		Data_out:	out	STD_LOGIC_VECTOR(7 downto 0);
        Empty	:	out	STD_LOGIC;
        Full	:	out	STD_LOGIC);
end Queue;


architecture behavior of Queue is

CONSTANT QUEUE_LENGTH : integer := 8;

type regfile is array(0 to QUEUE_LENGTH-1) of STD_LOGIC_VECTOR(7 downto 0);
signal Queue_reg : regfile := (others =>(others => '0'));

signal W_ADDR : integer := 0;
signal R_ADDR : integer := 0;
signal Element_cnt : integer := 0;
signal Full_sig, Empty_sig : std_logic := '0';

BEGIN

process(clk, Element_cnt)
begin
	if rising_edge(clk) then
    
    --Basic Queue Logic
    	if (Write = '1') and (Full_sig = '0') then
        	Queue_reg(W_ADDR) <= Data_in;
            if W_ADDR = QUEUE_LENGTH-1 then
            	W_ADDR <= 0;
      		else
            	W_ADDR <= W_ADDR + 1;
            end if;
        end if;
        
        if (read = '1') and (Empty_sig = '0') then
        	Queue_reg(R_ADDR) <= (others => '0');
        	if R_ADDR = QUEUE_LENGTH-1 then
            	R_ADDR <= 0;
      		else
            	R_ADDR <= R_ADDR + 1;
            end if;
        end if;
        
        
        --Keep track of number of elements to signal Empty or Full. Note that this could easily be embedded into the if/else statements above. I just wanted to make it clear that this counter is separate hardware.
        if (Write = '1') and (Full_sig = '0') then
        	Element_cnt <= Element_cnt + 1;
        elsif (read = '1') and (Empty_sig = '0') then
        	Element_cnt <= Element_cnt - 1;
        end if;
    end if;
    
    --Comparitors for Full_sig and Empty_sig
    Full_sig <= '0';
    Empty_sig <= '0';
    if Element_cnt = QUEUE_LENGTH then
    	Full_sig <= '1';
    elsif Element_cnt = 0 then
    	Empty_sig <= '1';
    end if;
        
end process;

Full <= Full_sig;
Empty <= Empty_sig;
Data_out <= Queue_reg(R_ADDR);

end behavior;

hw5/SCI_Transmitter.vhd
library IEEE;
use IEEE.std_logic_1164.all;
use IEEE.numeric_std.all;

ENTITY SCI_Transmitter IS
PORT (
    clk_port        :   in  STD_LOGIC;
    Data_port       :   in  STD_LOGIC_VECTOR(7 downto 0);
    New_data_port   :   in  STD_LOGIC;
    Tx_port         :   out STD_LOGIC;
    Queue_full_port :   out STD_LOGIC
);
end SCI_Transmitter;

ARCHITECTURE behavior of SCI_Transmitter is

type state_type is (idle, load, transmit);
signal CS, NS : state_type := idle;

signal s_queue_read     : std_logic := '0';
signal s_queue_empty    : std_logic;
signal s_queue_full     : std_logic;
signal s_sci_tx_load    : std_logic := '0';
signal s_sci_tx_done    : std_logic;

Component Queue
PORT (
    clk     :   in  STD_LOGIC;
    Write   :   in  STD_LOGIC;
    read    :   in  STD_LOGIC;
    Data_in :   in  STD_LOGIC_VECTOR(7 downto 0);
    Data_out:   out STD_LOGIC_VECTOR(7 downto 0);
    Empty   :   out STD_LOGIC;
    Full    :   out STD_LOGIC
);
end component;

COMPONENT SCI_Tx
PORT(
    clk      : IN  std_logic;
    Data_in  : IN  std_logic_vector(7 downto 0);
    Load     : IN  std_logic;
    Tx       : OUT std_logic;
    Tx_done  : OUT std_logic
);
END COMPONENT;

signal s_queue_data_out : std_logic_vector(7 downto 0);

begin
    Queue_inst : Queue
    PORT MAP (
        clk         => clk_port,
        Write       => New_data_port,
        read        => s_queue_read,
        Data_in     => Data_port,
        Data_out    => s_queue_data_out,
        Empty       => s_queue_empty,
        Full        => s_queue_full
    );
    Queue_full_port <= s_queue_full;

    SCI_Tx_inst : SCI_Tx
    PORT MAP (
        clk         => clk_port,
        Data_in     => s_queue_data_out,
        Load        => s_sci_tx_load,
        Tx          => Tx_port,
        Tx_done     => s_sci_tx_done
    );

    process(clk_port)
    begin
        if rising_edge(clk_port) then
            CS <= NS;
        end if;
    end process;

    process(CS, s_queue_empty, s_sci_tx_done)
    begin
        s_queue_read    <= '0';
        s_sci_tx_load   <= '0';
        NS              <= CS;
        case CS is
            when idle =>
                if s_queue_empty = '0' then
                    NS <= load;
                else
                    NS <= idle;
                end if;
            when load =>
                s_queue_read  <= '1';
                s_sci_tx_load <= '1';
                NS <= transmit;
            when transmit =>
                if s_sci_tx_done = '1' then
                    NS <= idle;
                else
                    NS <= transmit;
                end if;
        end case;
    end process;
end architecture behavior;

hw5/SCI_Transmitter_tb.vhd
LIBRARY ieee;
USE ieee.std_logic_1164.ALL;
USE ieee.numeric_std.ALL;

ENTITY SCI_Transmitter_tb IS
END SCI_Transmitter_tb;

ARCHITECTURE testbench OF SCI_Transmitter_tb IS

    -- Component Declaration for the Unit Under Test (UUT)
    COMPONENT SCI_Transmitter
    PORT(
        clk_port        : IN  std_logic;
        Data_port       : IN  std_logic_vector(7 downto 0);
        New_data_port   : IN  std_logic;
        Tx_port         : OUT std_logic;
        Queue_full_port : OUT std_logic
    );
    END COMPONENT;

    -- Inputs
    signal clk_port      : std_logic := '0';
    signal Data_port     : std_logic_vector(7 downto 0) := (others => '0');
    signal New_data_port : std_logic := '0';

    -- Outputs
    signal Tx_port       : std_logic;
    signal Queue_full_port : std_logic;

    -- Clock period definitions
    constant clk_period : time := 100 ns;  -- Assuming a 10 MHz clock

BEGIN

    -- Instantiate the Unit Under Test (UUT)
    uut: SCI_Transmitter PORT MAP (
        clk_port        => clk_port,
        Data_port       => Data_port,
        New_data_port   => New_data_port,
        Tx_port         => Tx_port,
        Queue_full_port => Queue_full_port
    );

    -- Clock process definitions
    clk_process : process
    begin
        clk_port <= '0';
        wait for clk_period/2;
        clk_port <= '1';
        wait for clk_period/2;
    end process;

    -- Stimulus process
    stim_proc: process
    begin
        -- Initialize Inputs
        New_data_port <= '0';
        Data_port <= (others => '0');

        wait for clk_period * 10;


        Data_port <= "11110000"; --F0
        New_data_port <= '1';  -- Signal that new data is being written
        wait for clk_period;
        New_data_port <= '0';  -- Reset the new data signal
        wait for clk_period * 5;

        Data_port <= "00001111"; --0F
        New_data_port <= '1';  -- Signal that new data is being written
        wait for clk_period;
        New_data_port <= '0';  -- Reset the new data signal
        wait for clk_period * 5;
        
        Data_port <= "10101010"; --AA
        New_data_port <= '1';  -- Signal that new data is being written
        wait for clk_period;
        New_data_port <= '0';  -- Reset the new data signal
        wait for clk_period * 5;

        Data_port <= "01010011"; --53
        New_data_port <= '1';  -- Signal that new data is being written
        wait for clk_period;
        New_data_port <= '0';  -- Reset the new data signal
        wait for clk_period * 5;
        
        Data_port <= "11010010"; --D2
        New_data_port <= '1';  -- Signal that new data is being written
        wait for clk_period;
        New_data_port <= '0';  -- Reset the new data signal
        wait for clk_period * 5;

        Data_port <= "11111111"; --FF
        New_data_port <= '1';  -- Signal that new data is being written
        wait for clk_period;
        New_data_port <= '0';  -- Reset the new data signal
        wait for clk_period * 5;
        
        Data_port <= "00110001"; --31
        New_data_port <= '1';  -- Signal that new data is being written
        wait for clk_period;
        New_data_port <= '0';  -- Reset the new data signal
        wait for clk_period * 5;

        Data_port <= "01010101"; --55
        New_data_port <= '1';  -- Signal that new data is being written
        wait for clk_period;
        New_data_port <= '0';  -- Reset the new data signal
        wait for clk_period * 5;
		
        Data_port <= "10001100"; --8C
        New_data_port <= '1';  -- Signal that new data is being written
        wait for clk_period;
        New_data_port <= '0';  -- Reset the new data signal
        wait for clk_period * 5;
        
        --Now the queue should be full and adding new data should do nothing
        Data_port <= "10101111"; --AF
        New_data_port <= '1';  -- Signal that new data is being written
        wait for clk_period;
        New_data_port <= '0';  -- Reset the new data signal
        wait for clk_period * 5;
        
        
        wait for clk_period * 1000; --wait for at least one transmission to be done
        
        Data_port <= "11111010"; --FA
        New_data_port <= '1';  -- Signal that new data is being written
        wait for clk_period;
        New_data_port <= '0';  -- Reset the new data signal
        wait for clk_period * 5;
        
        wait;
    end process;

END testbench;

hw5/SCI_Transmitter_tb.vcd
$date
  Fri May 16 17:07:18 2025
$end
$version
  GHDL v0
$end
$timescale
  1 fs
$end
$scope module standard $end
$upscope $end
$scope module textio $end
$upscope $end
$scope module std_logic_1164 $end
$upscope $end
$scope module numeric_std $end
$upscope $end
$scope module sci_transmitter_tb $end
$var reg 1 ! clk_port $end
$var reg 8 " data_port[7:0] $end
$var reg 1 # new_data_port $end
$var reg 1 $ tx_port $end
$var reg 1 % queue_full_port $end
$scope module uut $end
$var reg 1 & clk_port $end
$var reg 8 ' data_port[7:0] $end
$var reg 1 ( new_data_port $end
$var reg 1 ) tx_port $end
$var reg 1 * queue_full_port $end
$comment cs is not handled $end
$comment ns is not handled $end
$var reg 1 + s_queue_read $end
$var reg 1 , s_queue_empty $end
$var reg 1 - s_queue_full $end
$var reg 1 . s_sci_tx_load $end
$var reg 1 / s_sci_tx_done $end
$var reg 8 0 s_queue_data_out[7:0] $end
$scope module queue_inst $end
$var reg 1 1 clk $end
$var reg 1 2 write $end
$var reg 1 3 read $end
$var reg 8 4 data_in[7:0] $end
$var reg 8 5 data_out[7:0] $end
$var reg 1 6 empty $end
$var reg 1 7 full $end
$comment queue_reg is not handled $end
$var integer 32 8 w_addr $end
$var integer 32 9 r_addr $end
$var integer 32 : element_cnt $end
$var reg 1 ; full_sig $end
$var reg 1 < empty_sig $end
$upscope $end
$scope module sci_tx_inst $end
$var reg 1 = clk $end
$var reg 8 > data_in[7:0] $end
$var reg 1 ? load $end
$var reg 1 @ tx $end
$var reg 1 A tx_done $end
$var integer 32 B baud_rate_counter_r $end
$var reg 1 C baud_tick_s $end
$var reg 10 D tx_sreg_r[9:0] $end
$var integer 32 E bit_count_r $end
$comment current_state_r is not handled $end
$comment next_state_s is not handled $end
$upscope $end
$upscope $end
$upscope $end
$enddefinitions $end
#0
0!
b00000000 "
0#
1$
0%
0&
b00000000 '
0(
1)
0*
0+
1,
0-
0.
0/
b00000000 0
01
02
03
b00000000 4
b00000000 5
16
07
b0 8
b0 9
b0 :
0;
1<
0=
b00000000 >
0?
1@
0A
b0 B
UC
b1111111111 D
b0 E
#50000000
1!
1&
11
1=
0C
#100000000
0!
0&
01
0=
#150000000
1!
1&
11
1=
#200000000
0!
0&
01
0=
#250000000
1!
1&
11
1=
#300000000
0!
0&
01
0=
#350000000
1!
1&
11
1=
#400000000
0!
0&
01
0=
#450000000
1!
1&
11
1=
#500000000
0!
0&
01
0=
#550000000
1!
1&
11
1=
#600000000
0!
0&
01
0=
#650000000
1!
1&
11
1=
#700000000
0!
0&
01
0=
#750000000
1!
1&
11
1=
#800000000
0!
0&
01
0=
#850000000
1!
1&
11
1=
#900000000
0!
0&
01
0=
#950000000
1!
1&
11
1=
#1000000000
0!
b11110000 "
1#
0&
b11110000 '
1(
01
12
b11110000 4
0=
#1050000000
1!
1&
0,
b11110000 0
11
b11110000 5
06
b1 8
b1 :
0<
1=
b11110000 >
#1100000000
0!
0#
0&
0(
01
02
0=
#1150000000
1!
1&
1+
1.
11
13
1=
1?
#1200000000
0!
0&
01
0=
#1250000000
1!
0$
1&
0)
0+
1,
0.
b00000000 0
11
03
b00000000 5
16
b1 9
b0 :
1<
1=
b00000000 >
0?
0@
b1111100000 D
#1300000000
0!
0&
01
0=
#1350000000
1!
1&
11
1=
b1 B
#1400000000
0!
0&
01
0=
#1450000000
1!
1&
11
1=
b10 B
#1500000000
0!
0&
01
0=
#1550000000
1!
1&
11
1=
b11 B
#1600000000
0!
b00001111 "
1#
0&
b00001111 '
1(
01
12
b00001111 4
0=
#1650000000
1!
1&
0,
b00001111 0
11
b00001111 5
06
b10 8
b1 :
0<
1=
b00001111 >
b100 B
#1700000000
0!
0#
0&
0(
01
02
0=
#1750000000
1!
1&
11
1=
b101 B
#1800000000
0!
0&
01
0=
#1850000000
1!
1&
11
1=
b110 B
#1900000000
0!
0&
01
0=
#1950000000
1!
1&
11
1=
b111 B
#2000000000
0!
0&
01
0=
#2050000000
1!
1&
11
1=
b1000 B
#2100000000
0!
0&
01
0=
#2150000000
1!
1&
11
1=
b1001 B
#2200000000
0!
b10101010 "
1#
0&
b10101010 '
1(
01
12
b10101010 4
0=
#2250000000
1!
1&
11
b11 8
b10 :
1=
b1010 B
#2300000000
0!
0#
0&
0(
01
02
0=
#2350000000
1!
1&
11
1=
b1011 B
#2400000000
0!
0&
01
0=
#2450000000
1!
1&
11
1=
b1100 B
#2500000000
0!
0&
01
0=
#2550000000
1!
1&
11
1=
b1101 B
#2600000000
0!
0&
01
0=
#2650000000
1!
1&
11
1=
b1110 B
#2700000000
0!
0&
01
0=
#2750000000
1!
1&
11
1=
b1111 B
#2800000000
0!
b01010011 "
1#
0&
b01010011 '
1(
01
12
b01010011 4
0=
#2850000000
1!
1&
11
b100 8
b11 :
1=
b10000 B
#2900000000
0!
0#
0&
0(
01
02
0=
#2950000000
1!
1&
11
1=
b10001 B
#3000000000
0!
0&
01
0=
#3050000000
1!
1&
11
1=
b10010 B
#3100000000
0!
0&
01
0=
#3150000000
1!
1&
11
1=
b10011 B
#3200000000
0!
0&
01
0=
#3250000000
1!
1&
11
1=
b10100 B
#3300000000
0!
0&
01
0=
#3350000000
1!
1&
11
1=
b10101 B
#3400000000
0!
b11010010 "
1#
0&
b11010010 '
1(
01
12
b11010010 4
0=
#3450000000
1!
1&
11
b101 8
b100 :
1=
b10110 B
#3500000000
0!
0#
0&
0(
01
02
0=
#3550000000
1!
1&
11
1=
b10111 B
#3600000000
0!
0&
01
0=
#3650000000
1!
1&
11
1=
b11000 B
#3700000000
0!
0&
01
0=
#3750000000
1!
1&
11
1=
b11001 B
#3800000000
0!
0&
01
0=
#3850000000
1!
1&
11
1=
b11010 B
#3900000000
0!
0&
01
0=
#3950000000
1!
1&
11
1=
b11011 B
#4000000000
0!
b11111111 "
1#
0&
b11111111 '
1(
01
12
b11111111 4
0=
#4050000000
1!
1&
11
b110 8
b101 :
1=
b11100 B
#4100000000
0!
0#
0&
0(
01
02
0=
#4150000000
1!
1&
11
1=
b11101 B
#4200000000
0!
0&
01
0=
#4250000000
1!
1&
11
1=
b11110 B
#4300000000
0!
0&
01
0=
#4350000000
1!
1&
11
1=
b11111 B
#4400000000
0!
0&
01
0=
#4450000000
1!
1&
11
1=
b100000 B
#4500000000
0!
0&
01
0=
#4550000000
1!
1&
11
1=
b100001 B
#4600000000
0!
b00110001 "
1#
0&
b00110001 '
1(
01
12
b00110001 4
0=
#4650000000
1!
1&
11
b111 8
b110 :
1=
b100010 B
#4700000000
0!
0#
0&
0(
01
02
0=
#4750000000
1!
1&
11
1=
b100011 B
#4800000000
0!
0&
01
0=
#4850000000
1!
1&
11
1=
b100100 B
#4900000000
0!
0&
01
0=
#4950000000
1!
1&
11
1=
b100101 B
#5000000000
0!
0&
01
0=
#5050000000
1!
1&
11
1=
b100110 B
#5100000000
0!
0&
01
0=
#5150000000
1!
1&
0)
11
1=
0@
b0 B
1C
#5200000000
0!
b01010101 "
1#
0&
b01010101 '
1(
01
12
b01010101 4
0=
#5250000000
1!
1&
0)
11
b0 8
b111 :
1=
0@
b1 B
0C
b0111110000 D
b1 E
#5300000000
0!
0#
0&
0(
01
02
0=
#5350000000
1!
1&
11
1=
b10 B
#5400000000
0!
0&
01
0=
#5450000000
1!
1&
11
1=
b11 B
#5500000000
0!
0&
01
0=
#5550000000
1!
1&
11
1=
b100 B
#5600000000
0!
0&
01
0=
#5650000000
1!
1&
11
1=
b101 B
#5700000000
0!
0&
01
0=
#5750000000
1!
1&
11
1=
b110 B
#5800000000
0!
b10001100 "
1#
0&
b10001100 '
1(
01
12
b10001100 4
0=
#5850000000
1!
1%
1&
1*
1-
11
17
b1 8
b1000 :
1;
1=
b111 B
#5900000000
0!
0#
0&
0(
01
02
0=
#5950000000
1!
1&
11
1=
b1000 B
#6000000000
0!
0&
01
0=
#6050000000
1!
1&
11
1=
b1001 B
#6100000000
0!
0&
01
0=
#6150000000
1!
1&
11
1=
b1010 B
#6200000000
0!
0&
01
0=
#6250000000
1!
1&
11
1=
b1011 B
#6300000000
0!
0&
01
0=
#6350000000
1!
1&
11
1=
b1100 B
#6400000000
0!
b10101111 "
1#
0&
b10101111 '
1(
01
12
b10101111 4
0=
#6450000000
1!
1&
11
1=
b1101 B
#6500000000
0!
0#
0&
0(
01
02
0=
#6550000000
1!
1&
11
1=
b1110 B
#6600000000
0!
0&
01
0=
#6650000000
1!
1&
11
1=
b1111 B
#6700000000
0!
0&
01
0=
#6750000000
1!
1&
11
1=
b10000 B
#6800000000
0!
0&
01
0=
#6850000000
1!
1&
11
1=
b10001 B
#6900000000
0!
0&
01
0=
#6950000000
1!
1&
11
1=
b10010 B
#7000000000
0!
0&
01
0=
#7050000000
1!
1&
11
1=
b10011 B
#7100000000
0!
0&
01
0=
#7150000000
1!
1&
11
1=
b10100 B
#7200000000
0!
0&
01
0=
#7250000000
1!
1&
11
1=
b10101 B
#7300000000
0!
0&
01
0=
#7350000000
1!
1&
11
1=
b10110 B
#7400000000
0!
0&
01
0=
#7450000000
1!
1&
11
1=
b10111 B
#7500000000
0!
0&
01
0=
#7550000000
1!
1&
11
1=
b11000 B
#7600000000
0!
0&
01
0=
#7650000000
1!
1&
11
1=
b11001 B
#7700000000
0!
0&
01
0=
#7750000000
1!
1&
11
1=
b11010 B
#7800000000
0!
0&
01
0=
#7850000000
1!
1&
11
1=
b11011 B
#7900000000
0!
0&
01
0=
#7950000000
1!
1&
11
1=
b11100 B
#8000000000
0!
0&
01
0=
#8050000000
1!
1&
11
1=
b11101 B
#8100000000
0!
0&
01
0=
#8150000000
1!
1&
11
1=
b11110 B
#8200000000
0!
0&
01
0=
#8250000000
1!
1&
11
1=
b11111 B
#8300000000
0!
0&
01
0=
#8350000000
1!
1&
11
1=
b100000 B
#8400000000
0!
0&
01
0=
#8450000000
1!
1&
11
1=
b100001 B
#8500000000
0!
0&
01
0=
#8550000000
1!
1&
11
1=
b100010 B
#8600000000
0!
0&
01
0=
#8650000000
1!
1&
11
1=
b100011 B
#8700000000
0!
0&
01
0=
#8750000000
1!
1&
11
1=
b100100 B
#8800000000
0!
0&
01
0=
#8850000000
1!
1&
11
1=
b100101 B
#8900000000
0!
0&
01
0=
#8950000000
1!
1&
11
1=
b100110 B
#9000000000
0!
0&
01
0=
#9050000000
1!
1&
0)
11
1=
0@
b0 B
1C
#9100000000
0!
0&
01
0=
#9150000000
1!
1&
0)
11
1=
0@
b1 B
0C
b0011111000 D
b10 E
#9200000000
0!
0&
01
0=
#9250000000
1!
1&
11
1=
b10 B
#9300000000
0!
0&
01
0=
#9350000000
1!
1&
11
1=
b11 B
#9400000000
0!
0&
01
0=
#9450000000
1!
1&
11
1=
b100 B
#9500000000
0!
0&
01
0=
#9550000000
1!
1&
11
1=
b101 B
#9600000000
0!
0&
01
0=
#9650000000
1!
1&
11
1=
b110 B
#9700000000
0!
0&
01
0=
#9750000000
1!
1&
11
1=
b111 B
#9800000000
0!
0&
01
0=
#9850000000
1!
1&
11
1=
b1000 B
#9900000000
0!
0&
01
0=
#9950000000
1!
1&
11
1=
b1001 B
#10000000000
0!
0&
01
0=
#10050000000
1!
1&
11
1=
b1010 B
#10100000000
0!
0&
01
0=
#10150000000
1!
1&
11
1=
b1011 B
#10200000000
0!
0&
01
0=
#10250000000
1!
1&
11
1=
b1100 B
#10300000000
0!
0&
01
0=
#10350000000
1!
1&
11
1=
b1101 B
#10400000000
0!
0&
01
0=
#10450000000
1!
1&
11
1=
b1110 B
#10500000000
0!
0&
01
0=
#10550000000
1!
1&
11
1=
b1111 B
#10600000000
0!
0&
01
0=
#10650000000
1!
1&
11
1=
b10000 B
#10700000000
0!
0&
01
0=
#10750000000
1!
1&
11
1=
b10001 B
#10800000000
0!
0&
01
0=
#10850000000
1!
1&
11
1=
b10010 B
#10900000000
0!
0&
01
0=
#10950000000
1!
1&
11
1=
b10011 B
#11000000000
0!
0&
01
0=
#11050000000
1!
1&
11
1=
b10100 B
#11100000000
0!
0&
01
0=
#11150000000
1!
1&
11
1=
b10101 B
#11200000000
0!
0&
01
0=
#11250000000
1!
1&
11
1=
b10110 B
#11300000000
0!
0&
01
0=
#11350000000
1!
1&
11
1=
b10111 B
#11400000000
0!
0&
01
0=
#11450000000
1!
1&
11
1=
b11000 B
#11500000000
0!
0&
01
0=
#11550000000
1!
1&
11
1=
b11001 B
#11600000000
0!
0&
01
0=
#11650000000
1!
1&
11
1=
b11010 B
#11700000000
0!
0&
01
0=
#11750000000
1!
1&
11
1=
b11011 B
#11800000000
0!
0&
01
0=
#11850000000
1!
1&
11
1=
b11100 B
#11900000000
0!
0&
01
0=
#11950000000
1!
1&
11
1=
b11101 B
#12000000000
0!
0&
01
0=
#12050000000
1!
1&
11
1=
b11110 B
#12100000000
0!
0&
01
0=
#12150000000
1!
1&
11
1=
b11111 B
#12200000000
0!
0&
01
0=
#12250000000
1!
1&
11
1=
b100000 B
#12300000000
0!
0&
01
0=
#12350000000
1!
1&
11
1=
b100001 B
#12400000000
0!
0&
01
0=
#12450000000
1!
1&
11
1=
b100010 B
#12500000000
0!
0&
01
0=
#12550000000
1!
1&
11
1=
b100011 B
#12600000000
0!
0&
01
0=
#12650000000
1!
1&
11
1=
b100100 B
#12700000000
0!
0&
01
0=
#12750000000
1!
1&
11
1=
b100101 B
#12800000000
0!
0&
01
0=
#12850000000
1!
1&
11
1=
b100110 B
#12900000000
0!
0&
01
0=
#12950000000
1!
1&
0)
11
1=
0@
b0 B
1C
#13000000000
0!
0&
01
0=
#13050000000
1!
1&
0)
11
1=
0@
b1 B
0C
b0001111100 D
b11 E
#13100000000
0!
0&
01
0=
#13150000000
1!
1&
11
1=
b10 B
#13200000000
0!
0&
01
0=
#13250000000
1!
1&
11
1=
b11 B
#13300000000
0!
0&
01
0=
#13350000000
1!
1&
11
1=
b100 B
#13400000000
0!
0&
01
0=
#13450000000
1!
1&
11
1=
b101 B
#13500000000
0!
0&
01
0=
#13550000000
1!
1&
11
1=
b110 B
#13600000000
0!
0&
01
0=
#13650000000
1!
1&
11
1=
b111 B
#13700000000
0!
0&
01
0=
#13750000000
1!
1&
11
1=
b1000 B
#13800000000
0!
0&
01
0=
#13850000000
1!
1&
11
1=
b1001 B
#13900000000
0!
0&
01
0=
#13950000000
1!
1&
11
1=
b1010 B
#14000000000
0!
0&
01
0=
#14050000000
1!
1&
11
1=
b1011 B
#14100000000
0!
0&
01
0=
#14150000000
1!
1&
11
1=
b1100 B
#14200000000
0!
0&
01
0=
#14250000000
1!
1&
11
1=
b1101 B
#14300000000
0!
0&
01
0=
#14350000000
1!
1&
11
1=
b1110 B
#14400000000
0!
0&
01
0=
#14450000000
1!
1&
11
1=
b1111 B
#14500000000
0!
0&
01
0=
#14550000000
1!
1&
11
1=
b10000 B
#14600000000
0!
0&
01
0=
#14650000000
1!
1&
11
1=
b10001 B
#14700000000
0!
0&
01
0=
#14750000000
1!
1&
11
1=
b10010 B
#14800000000
0!
0&
01
0=
#14850000000
1!
1&
11
1=
b10011 B
#14900000000
0!
0&
01
0=
#14950000000
1!
1&
11
1=
b10100 B
#15000000000
0!
0&
01
0=
#15050000000
1!
1&
11
1=
b10101 B
#15100000000
0!
0&
01
0=
#15150000000
1!
1&
11
1=
b10110 B
#15200000000
0!
0&
01
0=
#15250000000
1!
1&
11
1=
b10111 B
#15300000000
0!
0&
01
0=
#15350000000
1!
1&
11
1=
b11000 B
#15400000000
0!
0&
01
0=
#15450000000
1!
1&
11
1=
b11001 B
#15500000000
0!
0&
01
0=
#15550000000
1!
1&
11
1=
b11010 B
#15600000000
0!
0&
01
0=
#15650000000
1!
1&
11
1=
b11011 B
#15700000000
0!
0&
01
0=
#15750000000
1!
1&
11
1=
b11100 B
#15800000000
0!
0&
01
0=
#15850000000
1!
1&
11
1=
b11101 B
#15900000000
0!
0&
01
0=
#15950000000
1!
1&
11
1=
b11110 B
#16000000000
0!
0&
01
0=
#16050000000
1!
1&
11
1=
b11111 B
#16100000000
0!
0&
01
0=
#16150000000
1!
1&
11
1=
b100000 B
#16200000000
0!
0&
01
0=
#16250000000
1!
1&
11
1=
b100001 B
#16300000000
0!
0&
01
0=
#16350000000
1!
1&
11
1=
b100010 B
#16400000000
0!
0&
01
0=
#16450000000
1!
1&
11
1=
b100011 B
#16500000000
0!
0&
01
0=
#16550000000
1!
1&
11
1=
b100100 B
#16600000000
0!
0&
01
0=
#16650000000
1!
1&
11
1=
b100101 B
#16700000000
0!
0&
01
0=
#16750000000
1!
1&
11
1=
b100110 B
#16800000000
0!
0&
01
0=
#16850000000
1!
1&
0)
11
1=
0@
b0 B
1C
#16900000000
0!
0&
01
0=
#16950000000
1!
1&
0)
11
1=
0@
b1 B
0C
b0000111110 D
b100 E
#17000000000
0!
0&
01
0=
#17050000000
1!
1&
11
1=
b10 B
#17100000000
0!
0&
01
0=
#17150000000
1!
1&
11
1=
b11 B
#17200000000
0!
0&
01
0=
#17250000000
1!
1&
11
1=
b100 B
#17300000000
0!
0&
01
0=
#17350000000
1!
1&
11
1=
b101 B
#17400000000
0!
0&
01
0=
#17450000000
1!
1&
11
1=
b110 B
#17500000000
0!
0&
01
0=
#17550000000
1!
1&
11
1=
b111 B
#17600000000
0!
0&
01
0=
#17650000000
1!
1&
11
1=
b1000 B
#17700000000
0!
0&
01
0=
#17750000000
1!
1&
11
1=
b1001 B
#17800000000
0!
0&
01
0=
#17850000000
1!
1&
11
1=
b1010 B
#17900000000
0!
0&
01
0=
#17950000000
1!
1&
11
1=
b1011 B
#18000000000
0!
0&
01
0=
#18050000000
1!
1&
11
1=
b1100 B
#18100000000
0!
0&
01
0=
#18150000000
1!
1&
11
1=
b1101 B
#18200000000
0!
0&
01
0=
#18250000000
1!
1&
11
1=
b1110 B
#18300000000
0!
0&
01
0=
#18350000000
1!
1&
11
1=
b1111 B
#18400000000
0!
0&
01
0=
#18450000000
1!
1&
11
1=
b10000 B
#18500000000
0!
0&
01
0=
