hw5/stack.vhd
library IEEE;
use IEEE.std_logic_1164.all;
use IEEE.numeric_std.all;

entity Stack IS
PORT ( 	clk		:	in	STD_LOGIC; --10 MHz clock
		Push	: 	in 	STD_LOGIC;
		Pop		: 	in 	STD_LOGIC;
        Clear	: 	in	STD_LOGIC;
        Data_in	:	in	STD_LOGIC_VECTOR(7 downto 0);
        Full	:	out	STD_LOGIC;
        Empty	:	out	STD_LOGIC;
		Data_out:	out	STD_LOGIC_VECTOR(7 downto 0));
end Stack;


architecture behavior of Stack is

    constant STACK_DEPTH: integer := 8;

    type t_stack_reg is array(0 to STACK_DEPTH - 1) of std_logic_vector(7 downto 0);

    -- Stack declaration
    signal sp : integer := 0; -- Stack pointer. Starts at 0
    signal stack_reg : t_stack_reg := (others => (others => '0'));

begin

--code your design here. This is all done with datapath components (no FSM).
--Carefully think about which elements should be synchronous versus asynchronous

    stack_proc: process(clk)
    begin
        -- Push, pop, clear are synchronous
        if rising_edge(clk) then

            if Clear = '1' then

                stack_reg <= (others => (others => '0'));
                sp <= 0;

            elsif Pop = '1' then

                -- Check if stack is empty
                if sp > 0 then
                    sp <= sp - 1;
                end if;

            elsif Push = '1' then

                -- Check if stack is full
                if sp < STACK_DEPTH then
                    stack_reg(sp) <= Data_in;
                    sp <= sp + 1;
                end if;

            end if;
        end if;

    end process stack_proc;

    
    -- Asynchronous assignments
    process (sp, stack_reg)
    begin

        if sp > 0 then

            Data_out <= stack_reg(sp - 1);

        else

            Data_out <= "00000000";

        end if;

    end process;

    Empty <= '1' when sp = 0 else '0';
    Full  <= '1' when sp = STACK_DEPTH else '0';

end behavior;

hw5/stack_tb.vhd
-- Code your testbench here
library IEEE;
use IEEE.std_logic_1164.all;

entity Stack_tb is
end Stack_tb;

architecture testbench of Stack_tb is

component Stack IS
PORT ( 	clk		:	in	STD_LOGIC; --10 MHz clock
		Push	: 	in 	STD_LOGIC;
		Pop		: 	in 	STD_LOGIC;
        Clear	: 	in	STD_LOGIC;
        Data_in	:	in	STD_LOGIC_VECTOR(7 downto 0);
        Full	:	out	STD_LOGIC;
        Empty	:	out	STD_LOGIC;
		Data_out:	out	STD_LOGIC_VECTOR(7 downto 0));
end component;



signal 	clk		:	STD_LOGIC := '0'; --10 MHz clock
signal 	Push	: 	STD_LOGIC := '0';
signal 	Pop		: 	STD_LOGIC := '0';
signal 	Clear	: 	STD_LOGIC := '0';
signal 	Data_in	:	STD_LOGIC_VECTOR(7 downto 0) := (others => '0');
signal 	Full	:	STD_LOGIC := '0';
signal 	Empty	:	STD_LOGIC := '0';
signal 	Data_out:	STD_LOGIC_VECTOR(7 downto 0) := (others => '0');


begin

uut : Stack PORT MAP(
		clk  => CLK,
		Push => Push,
        Pop => Pop,
        Clear => Clear,
        Data_in => Data_in,
        Full => Full,
        Empty => Empty,
		Data_out => Data_out);
    
    
clk_proc : process
BEGIN

  CLK <= '0';
  wait for 5 ns;   

  CLK <= '1';
  wait for 5 ns;

END PROCESS clk_proc;

stim_proc : process
begin
	
    wait for 10 ns;
    
    Data_in <= "00000001";--0x01
    Push <= '1';
    Wait for 10 ns;
    Push <= '0';

	Wait for 10 ns;
    Data_in <= "00000011";--0x03
    Push <= '1';
    Wait for 10 ns;
    Push <= '0';
    
    Wait for 10 ns;
    Data_in <= "00000111";--0x07
    Push <= '1';
    Wait for 10 ns;
    Push <= '0';

	Wait for 10 ns;
    Data_in <= "00001111";--0x0F
    Push <= '1';
    Wait for 10 ns;
    Push <= '0';
    
    Wait for 10 ns;
    Data_in <= "00011111";--0x1F
    Push <= '1';
    Wait for 10 ns;
    Push <= '0';
	
    Wait for 10 ns;
    Data_in <= "00111111";--0x3F
    Push <= '1';
    Wait for 10 ns;
    Push <= '0';
    
    Wait for 10 ns;
    Data_in <= "01111111";--0x7F
    Push <= '1';
    Wait for 10 ns;
    Push <= '0';
	
    Wait for 10 ns;
    Data_in <= "11111111";--0xFF
    Push <= '1';
    Wait for 10 ns;
    Push <= '0';
    
    Wait for 10 ns;
    Data_in <= "01010101";--0x55 (the stack should be full and this won't get put anywhere)
    Push <= '1';
    Wait for 10 ns;
    Push <= '0';
    
    
    wait for 20 ns;
    Pop <= '1';
    wait for 10 ns;
    Pop <= '0';
    
    wait for 20 ns;
    Pop <= '1';
    wait for 10 ns;
    Pop <= '0';
    
    Wait for 10 ns;
    Data_in <= "10101010";--0xAA
    Push <= '1';
    Wait for 10 ns;
    Push <= '0';
    
    
    wait for 20 ns;
    Pop <= '1';
    wait for 10 ns;
    Pop <= '0';
    
    wait for 20 ns;
    Clear <= '1';
    wait for 10 ns;
    Clear <= '0';
    
    Wait for 10 ns;
    Data_in <= "01111111";--0x7F
    Push <= '1';
    Wait for 10 ns;
    Push <= '0';
	
    Wait for 10 ns;
    Data_in <= "11111111";--0xFF
    Push <= '1';
    Wait for 10 ns;
    Push <= '0';
    
    wait for 20 ns;
    Pop <= '1';
    wait for 10 ns;
    Pop <= '0';
    
     wait for 20 ns;
    Pop <= '1';
    wait for 10 ns;
    Pop <= '0';
    
     wait for 20 ns; --(The stack should be empty and nothing happens)
    Pop <= '1';
    wait for 10 ns;
    Pop <= '0';
    
    wait;
end process stim_proc;
end testbench;

hw5/stack_tb.vcd
$date
  Fri May 16 13:20:50 2025
$end
$version
  GHDL v0
$end
$timescale
  1 fs
$end
$scope module standard $end
$upscope $end
$scope module textio $end
$upscope $end
$scope module std_logic_1164 $end
$upscope $end
$scope module numeric_std $end
$upscope $end
$scope module stack_tb $end
$var reg 1 ! clk $end
$var reg 1 " push $end
$var reg 1 # pop $end
$var reg 1 $ clear $end
$var reg 8 % data_in[7:0] $end
$var reg 1 & full $end
$var reg 1 ' empty $end
$var reg 8 ( data_out[7:0] $end
$scope module uut $end
$var reg 1 ) clk $end
$var reg 1 * push $end
$var reg 1 + pop $end
$var reg 1 , clear $end
$var reg 8 - data_in[7:0] $end
$var reg 1 . full $end
$var reg 1 / empty $end
$var reg 8 0 data_out[7:0] $end
$var integer 32 1 sp $end
$comment stack_reg is not handled $end
$upscope $end
$upscope $end
$enddefinitions $end
#0
0!
0"
0#
0$
b00000000 %
0&
1'
b00000000 (
0)
0*
0+
0,
b00000000 -
0.
1/
b00000000 0
b0 1
#5000000
1!
1)
#10000000
0!
1"
b00000001 %
0)
1*
b00000001 -
#15000000
1!
0'
b00000001 (
1)
0/
b00000001 0
b1 1
#20000000
0!
0"
0)
0*
#25000000
1!
1)
#30000000
0!
1"
b00000011 %
0)
1*
b00000011 -
#35000000
1!
b00000011 (
1)
b00000011 0
b10 1
#40000000
0!
0"
0)
0*
#45000000
1!
1)
#50000000
0!
1"
b00000111 %
0)
1*
b00000111 -
#55000000
1!
b00000111 (
1)
b00000111 0
b11 1
#60000000
0!
0"
0)
0*
#65000000
1!
1)
#70000000
0!
1"
b00001111 %
0)
1*
b00001111 -
#75000000
1!
b00001111 (
1)
b00001111 0
b100 1
#80000000
0!
0"
0)
0*
#85000000
1!
1)
#90000000
0!
1"
b00011111 %
0)
1*
b00011111 -
#95000000
1!
b00011111 (
1)
b00011111 0
b101 1
#100000000
0!
0"
0)
0*
#105000000
1!
1)
#110000000
0!
1"
b00111111 %
0)
1*
b00111111 -
#115000000
1!
b00111111 (
1)
b00111111 0
b110 1
#120000000
0!
0"
0)
0*
#125000000
1!
1)
#130000000
0!
1"
b01111111 %
0)
1*
b01111111 -
#135000000
1!
b01111111 (
1)
b01111111 0
b111 1
#140000000
0!
0"
0)
0*
#145000000
1!
1)
#150000000
0!
1"
b11111111 %
0)
1*
b11111111 -
#155000000
1!
1&
b11111111 (
1)
1.
b11111111 0
b1000 1
#160000000
0!
0"
0)
0*
#165000000
1!
1)
#170000000
0!
1"
b01010101 %
0)
1*
b01010101 -
#175000000
1!
1)
#180000000
0!
0"
0)
0*
#185000000
1!
1)
#190000000
0!
0)
#195000000
1!
1)
#200000000
0!
1#
0)
1+
#205000000
1!
0&
b01111111 (
1)
0.
b01111111 0
b111 1
#210000000
0!
0#
0)
0+
#215000000
1!
1)
#220000000
0!
0)
#225000000
1!
1)
#230000000
0!
1#
0)
1+
#235000000
1!
b00111111 (
1)
b00111111 0
b110 1
#240000000
0!
0#
0)
0+
#245000000
1!
1)
#250000000
0!
1"
b10101010 %
0)
1*
b10101010 -
#255000000
1!
b10101010 (
1)
b10101010 0
b111 1
#260000000
0!
0"
0)
0*
#265000000
1!
1)
#270000000
0!
0)
#275000000
1!
1)
#280000000
0!
1#
0)
1+
#285000000
1!
b00111111 (
1)
b00111111 0
b110 1
#290000000
0!
0#
0)
0+
#295000000
1!
1)
#300000000
0!
0)
#305000000
1!
1)
#310000000
0!
1$
0)
1,
#315000000
1!
1'
b00000000 (
1)
1/
b00000000 0
b0 1
#320000000
0!
0$
0)
0,
#325000000
1!
1)
#330000000
0!
1"
b01111111 %
0)
1*
b01111111 -
#335000000
1!
0'
b01111111 (
1)
0/
b01111111 0
b1 1
#340000000
0!
0"
0)
0*
#345000000
1!
1)
#350000000
0!
1"
b11111111 %
0)
1*
b11111111 -
#355000000
1!
b11111111 (
1)
b11111111 0
b10 1
#360000000
0!
0"
0)
0*
#365000000
1!
1)
#370000000
0!
0)
#375000000
1!
1)
#380000000
0!
1#
0)
1+
#385000000
1!
b01111111 (
1)
b01111111 0
b1 1
#390000000
0!
0#
0)
0+
#395000000
1!
1)
#400000000
0!
0)
#405000000
1!
1)
#410000000
0!
1#
0)
1+
#415000000
1!
1'
b00000000 (
1)
1/
b00000000 0
b0 1
#420000000
0!
0#
0)
0+
#425000000
1!
1)
#430000000
0!
0)
#435000000
1!
1)
#440000000
0!
1#
0)
1+
#445000000
1!
1)
#450000000
0!
0#
0)
0+
